Workbook
Name TARIFA_LAND: #REF!
Name TARIFA_OUTBOUND: #REF!
Name TARIFA_SEA: #REF!
Name TOLERANCIA_COSTO: #REF!
Name TOLERANCIA_PCT: #REF!

Sheet Summary
C3: Type | D3: M01 | E3: M19 | F3: M23 | G3: M45 | H3: M46
C4: Sea %PCT | D4: =IFERROR(_xlfn.XLOOKUP(D$3,Sea!$CU$6:$CU$12,Sea!$CY$6:$CY$12,0),0) -> 0.14803945 | E4: =IFERROR(_xlfn.XLOOKUP(E$3,Sea!$CU$6:$CU$12,Sea!$CY$6:$CY$12,0),0) -> 0.49475976 | F4: =IFERROR(_xlfn.XLOOKUP(F$3,Sea!$CU$6:$CU$12,Sea!$CY$6:$CY$12,0),0) -> 0.034281248 | G4: =IFERROR(_xlfn.XLOOKUP(G$3,Sea!$CU$6:$CU$12,Sea!$CY$6:$CY$12,0),0) -> 0.29154587 | H4: =IFERROR(_xlfn.XLOOKUP(H$3,Sea!$CU$6:$CU$12,Sea!$CY$6:$CY$12,0),0) -> 0.031373675
C5: Land %PCT | D5: =IFERROR(_xlfn.XLOOKUP(D$3,land!$CC$3:$CC$10,land!$CE$3:$CE$10,0),0) -> 0 | E5: =IFERROR(_xlfn.XLOOKUP(E$3,land!$CC$3:$CC$10,land!$CE$3:$CE$10,0),0) -> 0.17730461 | F5: =IFERROR(_xlfn.XLOOKUP(F$3,land!$CC$3:$CC$10,land!$CE$3:$CE$10,0),0) -> 0.33799952 | G5: =IFERROR(_xlfn.XLOOKUP(G$3,land!$CC$3:$CC$10,land!$CE$3:$CE$10,0),0) -> 0.05411606 | H5: =IFERROR(_xlfn.XLOOKUP(H$3,land!$CC$3:$CC$10,land!$CE$3:$CE$10,0),0) -> 0.43057981
C6: Outbound %PCT | D6: =IFERROR(_xlfn.XLOOKUP(D$3,Outbound!$BS$9:$BS$14,Outbound!$BU$9:$BU$14,0),0) -> 0.21335361 | E6: =IFERROR(_xlfn.XLOOKUP(E$3,Outbound!$BS$9:$BS$14,Outbound!$BU$9:$BU$14,0),0) -> 0.40998995 | F6: =IFERROR(_xlfn.XLOOKUP(F$3,Outbound!$BS$9:$BS$14,Outbound!$BU$9:$BU$14,0),0) -> 0.031679472 | G6: =IFERROR(_xlfn.XLOOKUP(G$3,Outbound!$BS$9:$BS$14,Outbound!$BU$9:$BU$14,0),0) -> 0.3156942 | H6: =IFERROR(_xlfn.XLOOKUP(H$3,Outbound!$BS$9:$BS$14,Outbound!$BU$9:$BU$14,0),0) -> 0.029282767
B9: Viewer | C9: Arg. Var $ | D9: M01 | E9: M19 | F9: M23 | G9: M45 | H9: M46
B10: Sea | C10: =SUM(D10:H10) -> 135561.06 | D10: =IFERROR(_xlfn.XLOOKUP(D$9,Sea!$CU$6:$CU$12,Sea!$CX$6:$CX$12,0),0) -> 20068.385 | E10: =IFERROR(_xlfn.XLOOKUP(E$9,Sea!$CU$6:$CU$12,Sea!$CX$6:$CX$12,0),0) -> 67070.158 | F10: =IFERROR(_xlfn.XLOOKUP(F$9,Sea!$CU$6:$CU$12,Sea!$CX$6:$CX$12,0),0) -> 4647.2024 | G10: =IFERROR(_xlfn.XLOOKUP(G$9,Sea!$CU$6:$CU$12,Sea!$CX$6:$CX$12,0),0) -> 39522.267 | H10: =IFERROR(_xlfn.XLOOKUP(H$9,Sea!$CU$6:$CU$12,Sea!$CX$6:$CX$12,0),0) -> 4253.0487
B11: Land | C11: =SUM(D11:H11) -> 4339.476 | E11: =IFERROR(_xlfn.XLOOKUP(E$9,land!$CC$3:$CC$10,land!$CD$3:$CD$10,0),0) -> 769.40912 | F11: =IFERROR(_xlfn.XLOOKUP(F$9,land!$CC$3:$CC$10,land!$CD$3:$CD$10,0),0) -> 1466.7408 | G11: =IFERROR(_xlfn.XLOOKUP(G$9,land!$CC$3:$CC$10,land!$CD$3:$CD$10,0),0) -> 234.83535 | H11: =IFERROR(_xlfn.XLOOKUP(H$9,land!$CC$3:$CC$10,land!$CD$3:$CD$10,0),0) -> 1868.4908
B12: Outbound | C12: =SUM(D12:H12) -> 126981.16 | D12: =IFERROR(_xlfn.XLOOKUP(D$9,Outbound!$BS$9:$BS$14,Outbound!$BT$9:$BT$14,0),0) -> 27091.89 | E12: =IFERROR(_xlfn.XLOOKUP(E$9,Outbound!$BS$9:$BS$14,Outbound!$BT$9:$BT$14,0),0) -> 52061.002 | F12: =IFERROR(_xlfn.XLOOKUP(F$9,Outbound!$BS$9:$BS$14,Outbound!$BT$9:$BT$14,0),0) -> 4022.6962 | G12: =IFERROR(_xlfn.XLOOKUP(G$9,Outbound!$BS$9:$BS$14,Outbound!$BT$9:$BT$14,0),0) -> 40087.217 | H12: =IFERROR(_xlfn.XLOOKUP(H$9,Outbound!$BS$9:$BS$14,Outbound!$BT$9:$BT$14,0),0) -> 3718.3599

Sheet Outbound
B1: Data | BC1: Complementari information | BG1: Extraction of transactions | BS1: Output
B3: {=_xlfn.SEQUENCE(1,50)} -> 1 | C3: 2 | D3: 3 | E3: 4 | F3: 5 | G3: 6 | H3: 7 | I3: 8 | J3: 9 | K3: 10 | L3: 11 | M3: 12 | N3: 13 | O3: 14 | P3: 15 | Q3: 16 | R3: 17 | S3: 18 | T3: 19 | U3: 20 | V3: 21 | W3: 22 | X3: 23 | Y3: 24 | Z3: 25 | AA3: 26 | AB3: 27 | AC3: 28 | AD3: 29 | AE3: 30 | AF3: 31 | AG3: 32 | AH3: 33 | AI3: 34 | AJ3: 35 | AK3: 36 | AL3: 37 | AM3: 38 | AN3: 39 | AO3: 40 | AP3: 41 | AQ3: 42 | AR3: 43 | AS3: 44 | AT3: 45 | AU3: 46 | AV3: 47 | AW3: 48 | AX3: 49 | AY3: 50 | BG3: {=_xlfn.TOROW(IF($B$4:$AY$4="x",_xlfn.ANCHORARRAY(B3),1/0),3)} -> 1 | BH3: 2 | BI3: 3 | BJ3: 4 | BK3: 5 | BL3: 13 | BM3: 14 | BN3: 43 | BO3: 44 | BV3: Frida| Martha
B4: X | C4: X | D4: X | E4: X | F4: x | N4: x | O4: x | AR4: x | AS4: x | BG4: {=_xlfn.TOROW(IF($B$4:$AY$4="x",B8:AY8,1/0),3)} -> Inbound/Outbound | BH4: Method | BI4: Reference | BJ4: BU | BK4: Gross Weight | BL4: Customer | BM4: Address | BN4: Item | BO4: Qty Pzas | BV4: Cuanto Fact
BG6: Expand
R7: Pallets | U7: Cartons | X7: Pallets | AA7: Cartons | AD7: Pallets | AG7: Covers | AJ7: Delivery Information | AM7: Invoice Information | AR7: Shipping Information | AU7: SAT Information
B8: Inbound/Outbound | C8: Method | D8: Reference | E8: BU | F8: Gross Weight | G8: Waybill Number | H8: Transport Name | I8: Container Number | J8: On Board | K8: Port Drop Off | L8: Reference | M8: Security Seal | N8: Customer | O8: Address | P8: Company | Q8: Address | R8: Pieces | S8: Net Weight (Kgs) | T8: C. PLT gross weight | U8: Pieces | V8: Net Weight (Kgs) | W8: Gross Weight (Kgs) | X8: Pieces | Y8: Net Weight (Kgs) | Z8: Part. PLT gross weight | AA8: Pieces | AB8: Net Weight (Kgs) | AC8: Gross Weight (Kgs) | AD8: Wood | AE8: Plastic | AF8: No define | AG8: Wood | AH8: Plastic | AI8: No define | AJ8: Number | AK8: Status | AL8: Creation | AM8: OU | AN8: Number | AO8: Creation | AP8: Amount | AQ8: Currency | AR8: Item | AS8: Qty Pzas | AT8: UOM | AU8: Code | AV8: Description | AW8: UOM | AX8: Description | AY8: Fracción Arancelaria | AZ8: Description | BC8: Reference | BD8: Cost (USD) | BE8: Fix Cost | BG8: Inbound/Outbound | BH8: Method | BI8: Reference | BJ8: Customer | BK8: Addres | BL8: BU | BM8: Item | BN8: Qty Pzas | BO8: Gross Weight | BP8: %Proportion | BQ8: Calc_Exp | BS8: BU | BT8: Log. Exp | BU8: %PCT | BV8: Rec. Exp | BW8: Balance | BX8: %Pct Allow
B9: Outbound | C9: Land | D9: {=_xlfn.REGEXEXTRACT(G9,"FG-R-\d{4}LE\d{2}")} -> FG-R-2180LE25 | E9: M23 | F9: {=_xlfn.SWITCH(TRUE,T9>0,T9,Z9)} -> 1098.8 | G9: FG-R-2180LE25.M46-M45-2 | H9: 3 BROTHERS | I9: H06059 | J9: 2026/04/01 00:00:00 | K9: 2026/04/01 00:00:00 | L9: FG-R-2180LE25.M46-M45 | M9: UL-5606471 | N9: JOHNSON ELECTRIC NORTH AMERICA, INC. | O9: (TDS) Transcontinental Distribution Services, Inc 14213 Transportation Ave | P9: Johnson Electric Group Mexico, S. de R. L. de C.V. | Q9: Boulevard Morelos # 1109,Mega Parque Industrial Aeropuerto de Calera,98519, Calera | R9: 5 | S9: 993.8 | T9: 1098.8 | U9: 100 | V9: 870.6 | W9: 993.8 | X9: 0 | Y9: 0 | Z9: 0 | AA9: 0 | AB9: 0 | AC9: 0 | AD9: 0 | AE9: 5 | AF9: 0 | AG9: 0 | AH9: 5 | AI9: 0 | AJ9: 6171311 | AK9: Closed | AL9: 2026-04-02 | AM9: JE JMX OU | AN9: 202300058566 | AO9: 01-APR-26 | AP9: 22122.35 | AQ9: USD | AR9: 1908-1E90003RN | AS9: 600 | AT9: EA | AU9: 40151503 | AV9: Bombas centrífugas | AW9: H87 | AX9: Pieza | AY9: 8413309902 | AZ9: Para agua | BC9: FG-R-2180LE25 | BD9: 5775 | BE9: 5775 | BG9: {=_xlfn.LET(_xlpm.list,$BC$9:$BC$33,_xlpm.data,_xlfn.CHOOSECOLS($B$8:$AZ$263,1,2,3,13,14,4,43,44,5),_xlpm.out,_xlfn.DROP(_xlfn.REDUCE("",_xlfn.SEQUENCE(ROWS(_xlpm.list)),_xlfn.LAMBDA(_xlpm.a,_xlpm.b,_xlfn.VSTACK(_xlpm.a,_xlfn._xlws.FILTER(_xlpm.data,_xlfn.CHOOSECOLS(_xlpm.data,3)=INDEX(_xlpm.list,_xlpm.b),"No data")))),1),_xlpm.out)} -> Outbound | BH9: Land | BI9: FG-R-2180LE25 | BJ9: JOHNSON ELECTRIC NORTH AMERICA, INC. | BK9: (TDS) Transcontinental Distribution Services, Inc 14213 Transportation Ave | BL9: M23 | BM9: 1908-1E90003RN | BN9: 600 | BO9: 1098.8 | BP9: =BO9/SUMIFS($BO:$BO,$BI:$BI,BI9) -> 0.061965597 | BQ9: =_xlfn.XLOOKUP(BI9,$BC:$BC,$BE:$BE)*BP9 -> 357.85133 | BS9: {=_xlfn.DROP(_xlfn.GROUPBY($BL$8:$BL$263,BQ8:BQ263,_xlfn.HSTACK(_xleta.SUM,_xleta.PERCENTOF),1,1),1)} -> M01 | BT9: 27091.89 | BU9: 0.21335361 | BW9: =BT9-BV9 -> 27091.89 | BX9: =BW9/BW$14 -> 0.28523434
B10: Outbound | C10: Land | D10: {=_xlfn.REGEXEXTRACT(G10,"FG-R-\d{4}LE\d{2}")} -> FG-R-2180LE25 | E10: M23 | F10: {=_xlfn.SWITCH(TRUE,T10>0,T10,Z10)} -> 1538.32 | G10: FG-R-2180LE25.M46-M45-2 | H10: 3 BROTHERS | I10: H06059 | J10: 2026/04/01 00:00:00 | K10: 2026/04/01 00:00:00 | L10: FG-R-2180LE25.M46-M45 | M10: UL-5606471 | N10: JOHNSON ELECTRIC NORTH AMERICA, INC. | O10: (TDS) Transcontinental Distribution Services, Inc 14213 Transportation Ave | P10: Johnson Electric Group Mexico, S. de R. L. de C.V. | Q10: Boulevard Morelos # 1109,Mega Parque Industrial Aeropuerto de Calera,98519, Calera | R10: 7 | S10: 1391.32 | T10: 1538.32 | U10: 140 | V10: 1218.84 | W10: 1391.32 | X10: 0 | Y10: 0 | Z10: 0 | AA10: 0 | AB10: 0 | AC10: 0 | AD10: 0 | AE10: 7 | AF10: 0 | AG10: 0 | AH10: 7 | AI10: 0 | AJ10: 6171313 | AK10: Closed | AL10: 2026-04-02 | AM10: JE JMX OU | AN10: 202300058567 | AO10: 01-APR-26 | AP10: 30971.29 | AQ10: USD | AR10: 1908-1E90003RN | AS10: 840 | AT10: EA | AU10: 40151503 | AV10: Bombas centrífugas | AW10: H87 | AX10: Pieza | AY10: 8413309902 | AZ10: Para agua | BC10: FG-R-2181LE25 | BD10: 4545 | BE10: 4545 | BG10: Outbound | BH10: Land | BI10: FG-R-2180LE25 | BJ10: JOHNSON ELECTRIC NORTH AMERICA, INC. | BK10: (TDS) Transcontinental Distribution Services, Inc 14213 Transportation Ave | BL10: M23 | BM10: 1908-1E90003RN | BN10: 840 | BO10: 1538.32 | BP10: =BO10/SUMIFS($BO:$BO,$BI:$BI,BI10) -> 0.086751836 | BQ10: =_xlfn.XLOOKUP(BI10,$BC:$BC,$BE:$BE)*BP10 -> 500.99186 | BS10: M19 | BT10: 52061.002 | BU10: 0.40998995 | BV10: 32000 | BW10: =BT10-BV10 -> 20061.002 | BX10: =BW10/BW$14 -> 0.21121031
B11: Outbound | C11: Land | D11: {=_xlfn.REGEXEXTRACT(G11,"FG-R-\d{4}LE\d{2}")} -> FG-R-2180LE25 | E11: M23 | F11: {=_xlfn.SWITCH(TRUE,T11>0,T11,Z11)} -> 80.628 | G11: FG-R-2180LE25.M46-M45-2 | H11: 3 BROTHERS | I11: H06059 | J11: 2026/04/01 00:00:00 | K11: 2026/04/01 00:00:00 | L11: FG-R-2180LE25.M46-M45 | M11: UL-5606471 | N11: JOHNSON ELECTRIC NORTH AMERICA, INC. | O11: (TDS) Transcontinental Distribution Services, Inc 14213 Transportation Ave | P11: Johnson Electric Group Mexico, S. de R. L. de C.V. | Q11: Boulevard Morelos # 1109,Mega Parque Industrial Aeropuerto de Calera,98519, Calera | R11: 0 | S11: 0 | T11: 0 | U11: 0 | V11: 0 | W11: 0 | X11: 1 | Y11: 59.628 | Z11: 80.628 | AA11: 6 | AB11: 52.236 | AC11: 59.628 | AD11: 1 | AE11: 0 | AF11: 0 | AG11: 0 | AH11: 1 | AI11: 0 | AJ11: 6171332 | AK11: Closed | AL11: 2026-04-02 | AM11: JE JMX OU | AN11: 202300058569 | AO11: 01-APR-26 | AP11: 1455.55 | AQ11: USD | AR11: 1908-1E90003R1 | AS11: 36 | AT11: EA | AU11: 40151503 | AV11: Bombas centrífugas | AW11: H87 | AX11: Pieza | AY11: 8413309902 | AZ11: Para agua | BC11: FG-R-2182LE25 | BD11: 6025 | BE11: 6025 | BG11: Outbound | BH11: Land | BI11: FG-R-2180LE25 | BJ11: JOHNSON ELECTRIC NORTH AMERICA, INC. | BK11: (TDS) Transcontinental Distribution Services, Inc 14213 Transportation Ave | BL11: M23 | BM11: 1908-1E90003R1 | BN11: 36 | BO11: 80.628 | BP11: =BO11/SUMIFS($BO:$BO,$BI:$BI,BI11) -> 0.0045469259 | BQ11: =_xlfn.XLOOKUP(BI11,$BC:$BC,$BE:$BE)*BP11 -> 26.258497 | BS11: M23 | BT11: 4022.6962 | BU11: 0.031679472 | BW11: =BT11-BV11 -> 4022.6962 | BX11: =BW11/BW$14 -> 0.042352568
B12: Outbound | C12: Land | D12: {=_xlfn.REGEXEXTRACT(G12,"FG-R-\d{4}LE\d{2}")} -> FG-R-2180LE25 | E12: M45 | F12: {=_xlfn.SWITCH(TRUE,T12>0,T12,Z12)} -> 5299.296 | G12: FG-R-2180LE25.M46-M45 | H12: 3 BROTHERS | I12: H06059 | J12: 2026/04/01 00:00:00 | K12: 2026/04/01 00:00:00 | L12: FG-R-2180LE25.M46-M45 | M12: UL-5606471 | N12: JOHNSON ELECTRIC NORTH AMERICA, INC. | O12: APX WH 6001 GLOBAL DISTRIBUTION WAY LOUISVILLE, KY 40228 | P12: Johnson Electric Group Mexico, S. de R. L. de C.V. | Q12: Boulevard Morelos # 1109,Mega Parque Industrial Aeropuerto de Calera,98519, Calera | R12: 12 | S12: 5077.296 | T12: 5299.296 | U12: 504 | V12: 4886.784 | W12: 5077.296 | X12: 0 | Y12: 0 | Z12: 0 | AA12: 0 | AB12: 0 | AC12: 0 | AD12: 12 | AE12: 0 | AF12: 0 | AG12: 12 | AH12: 0 | AI12: 0 | AJ12: 6171300 | AK12: Closed | AL12: 2026-04-02 | AM12: JE JMX OU | AN12: 202300058563 | AO12: 01-APR-26 | AP12: 36914.88 | AQ12: USD | AR12: 1999-1E30016EU | AS12: 6048 | AT12: EA | AU12: 40151500 | AV12: Bombas | AW12: H87 | AX12: Pieza | AY12: 8413709999 | AZ12: Las demás | BC12: FG-R-2183LE25 | BD12: 5197 | BE12: 5197 | BG12: Outbound | BH12: Land | BI12: FG-R-2180LE25 | BJ12: JOHNSON ELECTRIC NORTH AMERICA, INC. | BK12: APX WH 6001 GLOBAL DISTRIBUTION WAY LOUISVILLE, KY 40228 | BL12: M45 | BM12: 1999-1E30016EU | BN12: 6048 | BO12: 5299.296 | BP12: =BO12/SUMIFS($BO:$BO,$BI:$BI,BI12) -> 0.29884787 | BQ12: =_xlfn.XLOOKUP(BI12,$BC:$BC,$BE:$BE)*BP12 -> 1725.8465 | BS12: M45 | BT12: 40087.217 | BU12: 0.3156942 | BW12: =BT12-BV12 -> 40087.217 | BX12: =BW12/BW$14 -> 0.42205439
B13: Outbound | C13: Land | D13: {=_xlfn.REGEXEXTRACT(G13,"FG-R-\d{4}LE\d{2}")} -> FG-R-2180LE25 | E13: M45 | F13: {=_xlfn.SWITCH(TRUE,T13>0,T13,Z13)} -> 3974.472 | G13: FG-R-2180LE25.M46-M45 | H13: 3 BROTHERS | I13: H06059 | J13: 2026/04/01 00:00:00 | K13: 2026/04/01 00:00:00 | L13: FG-R-2180LE25.M46-M45 | M13: UL-5606471 | N13: JOHNSON ELECTRIC NORTH AMERICA, INC. | O13: APX WH 6001 GLOBAL DISTRIBUTION WAY LOUISVILLE, KY 40228 | P13: Johnson Electric Group Mexico, S. de R. L. de C.V. | Q13: Boulevard Morelos # 1109,Mega Parque Industrial Aeropuerto de Calera,98519, Calera | R13: 9 | S13: 3807.972 | T13: 3974.472 | U13: 378 | V13: 3665.088 | W13: 3807.972 | X13: 0 | Y13: 0 | Z13: 0 | AA13: 0 | AB13: 0 | AC13: 0 | AD13: 9 | AE13: 0 | AF13: 0 | AG13: 9 | AH13: 0 | AI13: 0 | AJ13: 6171301 | AK13: Closed | AL13: 2026-04-02 | AM13: JE JMX OU | AN13: 202300058564 | AO13: 01-APR-26 | AP13: 27686.16 | AQ13: USD | AR13: 1999-1E30016EU | AS13: 4536 | AT13: EA | AU13: 40151500 | AV13: Bombas | AW13: H87 | AX13: Pieza | AY13: 8413709999 | AZ13: Las demás | BC13: FG-R-2184LE25 | BD13: 906.60277 | BE13: 4918.7603 | BG13: Outbound | BH13: Land | BI13: FG-R-2180LE25 | BJ13: JOHNSON ELECTRIC NORTH AMERICA, INC. | BK13: APX WH 6001 GLOBAL DISTRIBUTION WAY LOUISVILLE, KY 40228 | BL13: M45 | BM13: 1999-1E30016EU | BN13: 4536 | BO13: 3974.472 | BP13: =BO13/SUMIFS($BO:$BO,$BI:$BI,BI13) -> 0.2241359 | BQ13: =_xlfn.XLOOKUP(BI13,$BC:$BC,$BE:$BE)*BP13 -> 1294.3848 | BS13: M46 | BT13: 3718.3599 | BU13: 0.029282767 | BW13: =BT13-BV13 -> 3718.3599 | BX13: =BW13/BW$14 -> 0.039148392
B14: Outbound | C14: Land | D14: {=_xlfn.REGEXEXTRACT(G14,"FG-R-\d{4}LE\d{2}")} -> FG-R-2180LE25 | E14: M45 | F14: {=_xlfn.SWITCH(TRUE,T14>0,T14,Z14)} -> 5740.904 | G14: FG-R-2180LE25.M46-M45 | H14: 3 BROTHERS | I14: H06059 | J14: 2026/04/01 00:00:00 | K14: 2026/04/01 00:00:00 | L14: FG-R-2180LE25.M46-M45 | M14: UL-5606471 | N14: JOHNSON ELECTRIC NORTH AMERICA, INC. | O14: APX WH 6001 GLOBAL DISTRIBUTION WAY LOUISVILLE, KY 40228 | P14: Johnson Electric Group Mexico, S. de R. L. de C.V. | Q14: Boulevard Morelos # 1109,Mega Parque Industrial Aeropuerto de Calera,98519, Calera | R14: 13 | S14: 5500.404 | T14: 5740.904 | U14: 546 | V14: 5294.016 | W14: 5500.404 | X14: 0 | Y14: 0 | Z14: 0 | AA14: 0 | AB14: 0 | AC14: 0 | AD14: 13 | AE14: 0 | AF14: 0 | AG14: 13 | AH14: 0 | AI14: 0 | AJ14: 6171302 | AK14: Closed | AL14: 2026-04-02 | AM14: JE JMX OU | AN14: 202300058565 | AO14: 01-APR-26 | AP14: 39991.12 | AQ14: USD | AR14: 1999-1E30016EU | AS14: 6552 | AT14: EA | AU14: 40151500 | AV14: Bombas | AW14: H87 | AX14: Pieza | AY14: 8413709999 | AZ14: Las demás | BC14: FG-R-2186LE26 | BD14: 5775 | BE14: 5775 | BG14: Outbound | BH14: Land | BI14: FG-R-2180LE25 | BJ14: JOHNSON ELECTRIC NORTH AMERICA, INC. | BK14: APX WH 6001 GLOBAL DISTRIBUTION WAY LOUISVILLE, KY 40228 | BL14: M45 | BM14: 1999-1E30016EU | BN14: 6552 | BO14: 5740.904 | BP14: =BO14/SUMIFS($BO:$BO,$BI:$BI,BI14) -> 0.32375186 | BQ14: =_xlfn.XLOOKUP(BI14,$BC:$BC,$BE:$BE)*BP14 -> 1869.667 | BS14: Total | BT14: 126981.16 | BU14: 1 | BW14: =SUM(BW9:BW13) -> 94981.164
B15: Outbound | C15: Land | D15: {=_xlfn.REGEXEXTRACT(G15,"FG-R-\d{4}LE\d{2}")} -> FG-R-2181LE25 | E15: M01 | F15: {=_xlfn.SWITCH(TRUE,T15>0,T15,Z15)} -> 1161.36 | G15: FG-R-2181LE25.M01-M45 | H15: 3 BROTHERS | I15: 560602 | J15: 2026/04/03 00:00:00 | K15: 2026/04/03 00:00:00 | L15: FG-R-2181LE25.M01-M45 | M15: UL-5606473 | N15: JOHNSON ELECTRIC NORTH AMERICA, INC. | O15: Memphis Distribution Services 3893 Crowfarn | P15: Johnson Electric Group Mexico, S. de R. L. de C.V. | Q15: Boulevard Morelos # 1109,Mega Parque Industrial Aeropuerto de Calera,98519, Calera | R15: 2 | S15: 1107.36 | T15: 1161.36 | U15: 160 | V15: 432 | W15: 1107.36 | X15: 0 | Y15: 0 | Z15: 0 | AA15: 0 | AB15: 0 | AC15: 0 | AD15: 2 | AE15: 0 | AF15: 0 | AG15: 2 | AH15: 0 | AI15: 0 | AJ15: 6173338 | AK15: Closed | AL15: 2026-04-03 | AM15: JE JMX OU | AN15: 202300058592 | AO15: 02-APR-26 | AP15: 7368.28 | AQ15: USD | AR15: 1999-1WP0063AN | AS15: 4000 | AT15: EA | AU15: 40151500 | AV15: Bombas | AW15: H87 | AX15: Pieza | AY15: 8413700700 | AZ15: Bombas de agua, reconocibles como diseñadas exclusivamente para el sistema de limpiaparabrisas, para uso automotriz | BC15: FG-R-2187LE26 | BD15: 5197 | BE15: 5197 | BG15: Outbound | BH15: Land | BI15: FG-R-2181LE25 | BJ15: JOHNSON ELECTRIC NORTH AMERICA, INC. | BK15: Memphis Distribution Services 3893 Crowfarn | BL15: M01 | BM15: 1999-1WP0063AN | BN15: 4000 | BO15: 1161.36 | BP15: =BO15/SUMIFS($BO:$BO,$BI:$BI,BI15) -> 0.20079361 | BQ15: =_xlfn.XLOOKUP(BI15,$BC:$BC,$BE:$BE)*BP15 -> 912.60697
B16: Outbound | C16: Land | D16: {=_xlfn.REGEXEXTRACT(G16,"FG-R-\d{4}LE\d{2}")} -> FG-R-2181LE25 | E16: M01 | F16: {=_xlfn.SWITCH(TRUE,T16>0,T16,Z16)} -> 825.724 | G16: FG-R-2181LE25.M01-M45 | H16: 3 BROTHERS | I16: 560602 | J16: 2026/04/03 00:00:00 | K16: 2026/04/03 00:00:00 | L16: FG-R-2181LE25.M01-M45 | M16: UL-5606473 | N16: JOHNSON ELECTRIC NORTH AMERICA, INC. | O16: Memphis Distribution Services 3893 Crowfarn | P16: Johnson Electric Group Mexico, S. de R. L. de C.V. | Q16: Boulevard Morelos # 1109,Mega Parque Industrial Aeropuerto de Calera,98519, Calera | R16: 2 | S16: 788.724 | T16: 825.724 | U16: 180 | V16: 734.4 | W16: 788.724 | X16: 0 | Y16: 0 | Z16: 0 | AA16: 0 | AB16: 0 | AC16: 0 | AD16: 2 | AE16: 0 | AF16: 0 | AG16: 2 | AH16: 0 | AI16: 0 | AJ16: 6173300 | AK16: Closed | AL16: 2026-04-03 | AM16: JE JMX OU | AN16: 202300058580 | AO16: 02-APR-26 | AP16: 11450.02 | AQ16: USD | AR16: 1999-1WP0045AN | AS16: 7200 | AT16: EA | AU16: 40151500 | AV16: Bombas | AW16: H87 | AX16: Pieza | AY16: 8413700700 | AZ16: Bombas de agua, reconocibles como diseñadas exclusivamente para el sistema de limpiaparabrisas, para uso automotriz | BC16: FG-R-2188LE26 | BD16: 4545 | BE16: 4545 | BG16: Outbound | BH16: Land | BI16: FG-R-2181LE25 | BJ16: JOHNSON ELECTRIC NORTH AMERICA, INC. | BK16: Memphis Distribution Services 3893 Crowfarn | BL16: M01 | BM16: 1999-1WP0045AN | BN16: 7200 | BO16: 825.724 | BP16: =BO16/SUMIFS($BO:$BO,$BI:$BI,BI16) -> 0.14276375 | BQ16: =_xlfn.XLOOKUP(BI16,$BC:$BC,$BE:$BE)*BP16 -> 648.86123
B17: Outbound | C17: Land | D17: {=_xlfn.REGEXEXTRACT(G17,"FG-R-\d{4}LE\d{2}")} -> FG-R-2181LE25 | E17: M01 | F17: {=_xlfn.SWITCH(TRUE,T17>0,T17,Z17)} -> 311.113 | G17: FG-R-2181LE25.M01-M45 | H17: 3 BROTHERS | I17: 560602 | J17: 2026/04/03 00:00:00 | K17: 2026/04/03 00:00:00 | L17: FG-R-2181LE25.M01-M45 | M17: UL-5606473 | N17: JOHNSON ELECTRIC NORTH AMERICA, INC. | O17: Memphis Distribution Services 3893 Crowfarn | P17: Johnson Electric Group Mexico, S. de R. L. de C.V. | Q17: Boulevard Morelos # 1109,Mega Parque Industrial Aeropuerto de Calera,98519, Calera | R17: 1 | S17: 292.113 | T17: 311.113 | U17: 90 | V17: 250.56 | W17: 292.113 | X17: 0 | Y17: 0 | Z17: 0 | AA17: 0 | AB17: 0 | AC17: 0 | AD17: 1 | AE17: 0 | AF17: 0 | AG17: 1 | AH17: 0 | AI17: 0 | AJ17: 6173298 | AK17: Closed | AL17: 2026-04-03 | AM17: JE JMX OU | AN17: 202300058579 | AO17: 02-APR-26 | AP17: 4034.34 | AQ17: USD | AR17: 1999-1WP0046AN | AS17: 2160 | AT17: EA | AU17: 40151500 | AV17: Bombas | AW17: H87 | AX17: Pieza | AY17: 8413700700 | AZ17: Bombas de agua, reconocibles como diseñadas exclusivamente para el sistema de limpiaparabrisas, para uso automotriz | BC17: FG-R-2189LE26 | BD17: 6025 | BE17: 6025 | BG17: Outbound | BH17: Land | BI17: FG-R-2181LE25 | BJ17: JOHNSON ELECTRIC NORTH AMERICA, INC. | BK17: Memphis Distribution Services 3893 Crowfarn | BL17: M01 | BM17: 1999-1WP0046AN | BN17: 2160 | BO17: 311.113 | BP17: =BO17/SUMIFS($BO:$BO,$BI:$BI,BI17) -> 0.053789956 | BQ17: =_xlfn.XLOOKUP(BI17,$BC:$BC,$BE:$BE)*BP17 -> 244.47535
B18: Outbound | C18: Land | D18: {=_xlfn.REGEXEXTRACT(G18,"FG-R-\d{4}LE\d{2}")} -> FG-R-2181LE25 | E18: M01 | F18: {=_xlfn.SWITCH(TRUE,T18>0,T18,Z18)} -> 329.88 | G18: FG-R-2181LE25.M01-M45 | H18: 3 BROTHERS | I18: 560602 | J18: 2026/04/03 00:00:00 | K18: 2026/04/03 00:00:00 | L18: FG-R-2181LE25.M01-M45 | M18: UL-5606473 | N18: JOHNSON ELECTRIC NORTH AMERICA, INC. | O18: Memphis Distribution Services 3893 Crowfarn | P18: Johnson Electric Group Mexico, S. de R. L. de C.V. | Q18: Boulevard Morelos # 1109,Mega Parque Industrial Aeropuerto de Calera,98519, Calera | R18: 3 | S18: 254.88 | T18: 329.88 | U18: 0 | V18: 254.88 | W18: 254.88 | X18: 0 | Y18: 0 | Z18: 0 | AA18: 0 | AB18: 0 | AC18: 0 | AD18: 3 | AE18: 0 | AF18: 0 | AG18: 3 | AH18: 0 | AI18: 0 | AJ18: 6173279 | AK18: Closed | AL18: 2026-04-03 | AM18: JE JMX OU | AN18: 202300058581 | AO18: 02-APR-26 | AP18: 11555.28 | AQ18: USD | AR18: 1916-1010002EP/MX | AS18: 4320 | AT18: EA | AU18: 26101200 | AV18: Motores eléctricos de corriente directa DC | AW18: H87 | AX18: Pieza | AY18: 8501101004 | AZ18: Accionados exclusivamente por corriente continua | BC18: FG-R-2190LE26 | BD18: 5197 | BE18: 5197 | BG18: Outbound | BH18: Land | BI18: FG-R-2181LE25 | BJ18: JOHNSON ELECTRIC NORTH AMERICA, INC. | BK18: Memphis Distribution Services 3893 Crowfarn | BL18: M01 | BM18: 1916-1010002EP/MX | BN18: 4320 | BO18: 329.88 | BP18: =BO18/SUMIFS($BO:$BO,$BI:$BI,BI18) -> 0.057034681 | BQ18: =_xlfn.XLOOKUP(BI18,$BC:$BC,$BE:$BE)*BP18 -> 259.22262
B19: Outbound | C19: Land | D19: {=_xlfn.REGEXEXTRACT(G19,"FG-R-\d{4}LE\d{2}")} -> FG-R-2181LE25 | E19: M01 | F19: {=_xlfn.SWITCH(TRUE,T19>0,T19,Z19)} -> 329.88 | G19: FG-R-2181LE25.M01-M45 | H19: 3 BROTHERS | I19: 560602 | J19: 2026/04/03 00:00:00 | K19: 2026/04/03 00:00:00 | L19: FG-R-2181LE25.M01-M45 | M19: UL-5606473 | N19: JOHNSON ELECTRIC NORTH AMERICA, INC. | O19: Memphis Distribution Services 3893 Crowfarn | P19: Johnson Electric Group Mexico, S. de R. L. de C.V. | Q19: Boulevard Morelos # 1109,Mega Parque Industrial Aeropuerto de Calera,98519, Calera | R19: 3 | S19: 254.88 | T19: 329.88 | U19: 0 | V19: 254.88 | W19: 254.88 | X19: 0 | Y19: 0 | Z19: 0 | AA19: 0 | AB19: 0 | AC19: 0 | AD19: 3 | AE19: 0 | AF19: 0 | AG19: 3 | AH19: 0 | AI19: 0 | AJ19: 6173280 | AK19: Closed | AL19: 2026-04-03 | AM19: JE JMX OU | AN19: 202300058582 | AO19: 02-APR-26 | AP19: 11555.28 | AQ19: USD | AR19: 1916-1010002EP/MX | AS19: 4320 | AT19: EA | AU19: 26101200 | AV19: Motores eléctricos de corriente directa DC | AW19: H87 | AX19: Pieza | AY19: 8501101004 | AZ19: Accionados exclusivamente por corriente continua | BC19: FG-R-2191LE26 | BD19: 0 | BE19: 4918.7603 | BG19: Outbound | BH19: Land | BI19: FG-R-2181LE25 | BJ19: JOHNSON ELECTRIC NORTH AMERICA, INC. | BK19: Memphis Distribution Services 3893 Crowfarn | BL19: M01 | BM19: 1916-1010002EP/MX | BN19: 4320 | BO19: 329.88 | BP19: =BO19/SUMIFS($BO:$BO,$BI:$BI,BI19) -> 0.057034681 | BQ19: =_xlfn.XLOOKUP(BI19,$BC:$BC,$BE:$BE)*BP19 -> 259.22262
B20: Outbound | C20: Land | D20: {=_xlfn.REGEXEXTRACT(G20,"FG-R-\d{4}LE\d{2}")} -> FG-R-2181LE25 | E20: M01 | F20: {=_xlfn.SWITCH(TRUE,T20>0,T20,Z20)} -> 297.91232 | G20: FG-R-2181LE25.M01-M45 | H20: 3 BROTHERS | I20: 560602 | J20: 2026/04/03 00:00:00 | K20: 2026/04/03 00:00:00 | L20: FG-R-2181LE25.M01-M45 | M20: UL-5606473 | N20: JOHNSON ELECTRIC NORTH AMERICA, INC. | O20: Memphis Distribution Services 3893 Crowfarn | P20: Johnson Electric Group Mexico, S. de R. L. de C.V. | Q20: Boulevard Morelos # 1109,Mega Parque Industrial Aeropuerto de Calera,98519, Calera | R20: 1 | S20: 278.91232 | T20: 297.91232 | U20: 70 | V20: 278.88 | W20: 278.91232 | X20: 0 | Y20: 0 | Z20: 0 | AA20: 0 | AB20: 0 | AC20: 0 | AD20: 1 | AE20: 0 | AF20: 0 | AG20: 1 | AH20: 0 | AI20: 0 | AJ20: 6173294 | AK20: Closed | AL20: 2026-04-03 | AM20: JE JMX OU | AN20: 202300058576 | AO20: 02-APR-26 | AP20: 5376.11 | AQ20: USD | AR20: 1999-1WP0105EN | AS20: 2100 | AT20: EA | AU20: 25171506 | AV20: Bomba de lava parabrisas | AW20: H87 | AX20: Pieza | AY20: 8413700700 | AZ20: Bombas de agua, reconocibles como diseñadas exclusivamente para el sistema de limpiaparabrisas, para uso automotriz | BC20: FG-R-2192LE26 | BD20: 316.85912 | BE20: 4918.7603 | BG20: Outbound | BH20: Land | BI20: FG-R-2181LE25 | BJ20: JOHNSON ELECTRIC NORTH AMERICA, INC. | BK20: Memphis Distribution Services 3893 Crowfarn | BL20: M01 | BM20: 1999-1WP0105EN | BN20: 2100 | BO20: 297.91232 | BP20: =BO20/SUMIFS($BO:$BO,$BI:$BI,BI20) -> 0.051507621 | BQ20: =_xlfn.XLOOKUP(BI20,$BC:$BC,$BE:$BE)*BP20 -> 234.10214
B21: Outbound | C21: Land | D21: {=_xlfn.REGEXEXTRACT(G21,"FG-R-\d{4}LE\d{2}")} -> FG-R-2181LE25 | E21: M01 | F21: {=_xlfn.SWITCH(TRUE,T21>0,T21,Z21)} -> 117.16 | G21: FG-R-2181LE25.M01-M45 | H21: 3 BROTHERS | I21: 560602 | J21: 2026/04/03 00:00:00 | K21: 2026/04/03 00:00:00 | L21: FG-R-2181LE25.M01-M45 | M21: UL-5606473 | N21: JOHNSON ELECTRIC NORTH AMERICA, INC. | O21: Memphis Distribution Services 3893 Crowfarn | P21: Johnson Electric Group Mexico, S. de R. L. de C.V. | Q21: Boulevard Morelos # 1109,Mega Parque Industrial Aeropuerto de Calera,98519, Calera | R21: 1 | S21: 92.16 | T21: 117.16 | U21: 0 | V21: 92.16 | W21: 92.16 | X21: 0 | Y21: 0 | Z21: 0 | AA21: 0 | AB21: 0 | AC21: 0 | AD21: 1 | AE21: 0 | AF21: 0 | AG21: 1 | AH21: 0 | AI21: 0 | AJ21: 6173285 | AK21: Closed | AL21: 2026-04-03 | AM21: JE JMX OU | AN21: 202300058590 | AO21: 02-APR-26 | AP21: 3998.61 | AQ21: USD | AR21: 1916-1010004EN | AS21: 1440 | AT21: EA | AU21: 26101200 | AV21: Motores eléctricos de corriente directa DC | AW21: H87 | AX21: Pieza | AY21: 8501101004 | AZ21: Accionados exclusivamente por corriente continua | BC21: FG-R-2193LE26 | BD21: 0 | BE21: 4918.7603 | BG21: Outbound | BH21: Land | BI21: FG-R-2181LE25 | BJ21: JOHNSON ELECTRIC NORTH AMERICA, INC. | BK21: Memphis Distribution Services 3893 Crowfarn | BL21: M01 | BM21: 1916-1010004EN | BN21: 1440 | BO21: 117.16 | BP21: =BO21/SUMIFS($BO:$BO,$BI:$BI,BI21) -> 0.020256406 | BQ21: =_xlfn.XLOOKUP(BI21,$BC:$BC,$BE:$BE)*BP21 -> 92.065365
B22: Outbound | C22: Land | D22: {=_xlfn.REGEXEXTRACT(G22,"FG-R-\d{4}LE\d{2}")} -> FG-R-2181LE25 | E22: M01 | F22: {=_xlfn.SWITCH(TRUE,T22>0,T22,Z22)} -> 504.6 | G22: FG-R-2181LE25.M01-M45 | H22: 3 BROTHERS | I22: 560602 | J22: 2026/04/03 00:00:00 | K22: 2026/04/03 00:00:00 | L22: FG-R-2181LE25.M01-M45 | M22: UL-5606473 | N22: JOHNSON ELECTRIC NORTH AMERICA, INC. | O22: Memphis Distribution Services 3893 Crowfarn | P22: Johnson Electric Group Mexico, S. de R. L. de C.V. | Q22: Boulevard Morelos # 1109,Mega Parque Industrial Aeropuerto de Calera,98519, Calera | R22: 1 | S22: 477.6 | T22: 504.6 | U22: 60 | V22: 441.6 | W22: 477.6 | X22: 0 | Y22: 0 | Z22: 0 | AA22: 0 | AB22: 0 | AC22: 0 | AD22: 1 | AE22: 0 | AF22: 0 | AG22: 1 | AH22: 0 | AI22: 0 | AJ22: 6173297 | AK22: Closed | AL22: 2026-04-03 | AM22: JE JMX OU | AN22: 202300058578 | AO22: 02-APR-26 | AP22: 7290.29 | AQ22: USD | AR22: 1999-1WP0055AN | AS22: 4800 | AT22: EA | AU22: 40151500 | AV22: Bombas | AW22: H87 | AX22: Pieza | AY22: 8413700700 | AZ22: Bombas de agua, reconocibles como diseñadas exclusivamente para el sistema de limpiaparabrisas, para uso automotriz | BC22: FG-R-2194LE26 | BD22: 0 | BE22: 4918.7603 | BG22: Outbound | BH22: Land | BI22: FG-R-2181LE25 | BJ22: JOHNSON ELECTRIC NORTH AMERICA, INC. | BK22: Memphis Distribution Services 3893 Crowfarn | BL22: M01 | BM22: 1999-1WP0055AN | BN22: 4800 | BO22: 504.6 | BP22: =BO22/SUMIFS($BO:$BO,$BI:$BI,BI22) -> 0.087242937 | BQ22: =_xlfn.XLOOKUP(BI22,$BC:$BC,$BE:$BE)*BP22 -> 396.51915
B23: Outbound | C23: Land | D23: {=_xlfn.REGEXEXTRACT(G23,"FG-R-\d{4}LE\d{2}")} -> FG-R-2181LE25 | E23: M01 | F23: {=_xlfn.SWITCH(TRUE,T23>0,T23,Z23)} -> 633.24 | G23: FG-R-2181LE25.M01-M45 | H23: 3 BROTHERS | I23: 560602 | J23: 2026/04/03 00:00:00 | K23: 2026/04/03 00:00:00 | L23: FG-R-2181LE25.M01-M45 | M23: UL-5606473 | N23: JOHNSON ELECTRIC NORTH AMERICA, INC. | O23: Memphis Distribution Services 3893 Crowfarn | P23: Johnson Electric Group Mexico, S. de R. L. de C.V. | Q23: Boulevard Morelos # 1109,Mega Parque Industrial Aeropuerto de Calera,98519, Calera | R23: 1 | S23: 606.24 | T23: 633.24 | U23: 60 | V23: 570.24 | W23: 606.24 | X23: 0 | Y23: 0 | Z23: 0 | AA23: 0 | AB23: 0 | AC23: 0 | AD23: 1 | AE23: 0 | AF23: 0 | AG23: 1 | AH23: 0 | AI23: 0 | AJ23: 6173296 | AK23: Closed | AL23: 2026-04-03 | AM23: JE JMX OU | AN23: 202300058577 | AO23: 02-APR-26 | AP23: 10229.52 | AQ23: USD | AR23: 1999-1WP0113EN | AS23: 4800 | AT23: EA | AU23: 25171506 | AV23: Bomba de lava parabrisas | AW23: H87 | AX23: Pieza | AY23: 8413700700 | AZ23: Bombas de agua, reconocibles como diseñadas exclusivamente para el sistema de limpiaparabrisas, para uso automotriz | BC23: FG-R-2195LE26 | BD23: 0 | BE23: 4918.7603 | BG23: Outbound | BH23: Land | BI23: FG-R-2181LE25 | BJ23: JOHNSON ELECTRIC NORTH AMERICA, INC. | BK23: Memphis Distribution Services 3893 Crowfarn | BL23: M01 | BM23: 1999-1WP0113EN | BN23: 4800 | BO23: 633.24 | BP23: =BO23/SUMIFS($BO:$BO,$BI:$BI,BI23) -> 0.10948418 | BQ23: =_xlfn.XLOOKUP(BI23,$BC:$BC,$BE:$BE)*BP23 -> 497.6056
B24: Outbound | C24: Land | D24: {=_xlfn.REGEXEXTRACT(G24,"FG-R-\d{4}LE\d{2}")} -> FG-R-2181LE25 | E24: M01 | F24: {=_xlfn.SWITCH(TRUE,T24>0,T24,Z24)} -> 439.84 | G24: FG-R-2181LE25.M01-M45 | H24: 3 BROTHERS | I24: 560602 | J24: 2026/04/03 00:00:00 | K24: 2026/04/03 00:00:00 | L24: FG-R-2181LE25.M01-M45 | M24: UL-5606473 | N24: JOHNSON ELECTRIC NORTH AMERICA, INC. | O24: Memphis Distribution Services 3893 Crowfarn | P24: Johnson Electric Group Mexico, S. de R. L. de C.V. | Q24: Boulevard Morelos # 1109,Mega Parque Industrial Aeropuerto de Calera,98519, Calera | R24: 4 | S24: 339.84 | T24: 439.84 | U24: 0 | V24: 339.84 | W24: 339.84 | X24: 0 | Y24: 0 | Z24: 0 | AA24: 0 | AB24: 0 | AC24: 0 | AD24: 4 | AE24: 0 | AF24: 0 | AG24: 4 | AH24: 0 | AI24: 0 | AJ24: 6173283 | AK24: Closed | AL24: 2026-04-03 | AM24: JE JMX OU | AN24: 202300058588 | AO24: 02-APR-26 | AP24: 15407.04 | AQ24: USD | AR24: 1916-1010002EP/MX | AS24: 5760 | AT24: EA | AU24: 26101200 | AV24: Motores eléctricos de corriente directa DC | AW24: H87 | AX24: Pieza | AY24: 8501101004 | AZ24: Accionados exclusivamente por corriente continua | BC24: FG-R-2197LE26 | BD24: 0 | BE24: 4918.7603 | BG24: Outbound | BH24: Land | BI24: FG-R-2181LE25 | BJ24: JOHNSON ELECTRIC NORTH AMERICA, INC. | BK24: Memphis Distribution Services 3893 Crowfarn | BL24: M01 | BM24: 1916-1010002EP/MX | BN24: 5760 | BO24: 439.84 | BP24: =BO24/SUMIFS($BO:$BO,$BI:$BI,BI24) -> 0.076046241 | BQ24: =_xlfn.XLOOKUP(BI24,$BC:$BC,$BE:$BE)*BP24 -> 345.63017
B25: Outbound | C25: Land | D25: {=_xlfn.REGEXEXTRACT(G25,"FG-R-\d{4}LE\d{2}")} -> FG-R-2181LE25 | E25: M01 | F25: {=_xlfn.SWITCH(TRUE,T25>0,T25,Z25)} -> 585.8 | G25: FG-R-2181LE25.M01-M45 | H25: 3 BROTHERS | I25: 560602 | J25: 2026/04/03 00:00:00 | K25: 2026/04/03 00:00:00 | L25: FG-R-2181LE25.M01-M45 | M25: UL-5606473 | N25: JOHNSON ELECTRIC NORTH AMERICA, INC. | O25: Memphis Distribution Services 3893 Crowfarn | P25: Johnson Electric Group Mexico, S. de R. L. de C.V. | Q25: Boulevard Morelos # 1109,Mega Parque Industrial Aeropuerto de Calera,98519, Calera | R25: 5 | S25: 460.8 | T25: 585.8 | U25: 0 | V25: 460.8 | W25: 460.8 | X25: 0 | Y25: 0 | Z25: 0 | AA25: 0 | AB25: 0 | AC25: 0 | AD25: 5 | AE25: 0 | AF25: 0 | AG25: 5 | AH25: 0 | AI25: 0 | AJ25: 6173284 | AK25: Closed | AL25: 2026-04-03 | AM25: JE JMX OU | AN25: 202300058589 | AO25: 02-APR-26 | AP25: 19993.05 | AQ25: USD | AR25: 1916-1010004EN | AS25: 7200 | AT25: EA | AU25: 26101200 | AV25: Motores eléctricos de corriente directa DC | AW25: H87 | AX25: Pieza | AY25: 8501101004 | AZ25: Accionados exclusivamente por corriente continua | BC25: FG-R-2198LE26 | BD25: 0 | BE25: 4918.7603 | BG25: Outbound | BH25: Land | BI25: FG-R-2181LE25 | BJ25: JOHNSON ELECTRIC NORTH AMERICA, INC. | BK25: Memphis Distribution Services 3893 Crowfarn | BL25: M01 | BM25: 1916-1010004EN | BN25: 7200 | BO25: 585.8 | BP25: =BO25/SUMIFS($BO:$BO,$BI:$BI,BI25) -> 0.10128203 | BQ25: =_xlfn.XLOOKUP(BI25,$BC:$BC,$BE:$BE)*BP25 -> 460.32683
B26: Outbound | C26: Land | D26: {=_xlfn.REGEXEXTRACT(G26,"FG-R-\d{4}LE\d{2}")} -> FG-R-2181LE25 | E26: M46 | F26: {=_xlfn.SWITCH(TRUE,T26>0,T26,Z26)} -> 122.44 | G26: FG-R-2181LE25.M01-M45 | H26: 3 BROTHERS | I26: 560602 | J26: 2026/04/03 00:00:00 | K26: 2026/04/03 00:00:00 | L26: FG-R-2181LE25.M01-M45 | M26: UL-5606473 | N26: JOHNSON ELECTRIC NORTH AMERICA, INC. | O26: Memphis Distribution Services 3893 Crowfarn | P26: Johnson Electric Group Mexico, S. de R. L. de C.V. | Q26: Boulevard Morelos # 1109,Mega Parque Industrial Aeropuerto de Calera,98519, Calera | R26: 1 | S26: 101.44 | T26: 122.44 | U26: 50 | V26: 26.44 | W26: 101.44 | X26: 0 | Y26: 0 | Z26: 0 | AA26: 0 | AB26: 0 | AC26: 0 | AD26: 1 | AE26: 0 | AF26: 0 | AG26: 1 | AH26: 0 | AI26: 0 | AJ26: 6173291 | AK26: Closed | AL26: 2026-04-03 | AM26: JE JMX OU | AN26: 202300058574 | AO26: 02-APR-26 | AP26: 1346.81 | AQ26: USD | AR26: 1651-EQH0040EN | AS26: 200 | AT26: EA | AU26: 26101100 | AV26: Motores eléctricos de corriente alterna AC | AW26: H87 | AX26: Pieza | AY26: 8501101004 | AZ26: Accionados exclusivamente por corriente continua | BC26: FG-R-2199LE26 | BD26: 0 | BE26: 4918.7603 | BG26: Outbound | BH26: Land | BI26: FG-R-2181LE25 | BJ26: JOHNSON ELECTRIC NORTH AMERICA, INC. | BK26: Memphis Distribution Services 3893 Crowfarn | BL26: M46 | BM26: 1651-EQH0040EN | BN26: 200 | BO26: 122.44 | BP26: =BO26/SUMIFS($BO:$BO,$BI:$BI,BI26) -> 0.021169293 | BQ26: =_xlfn.XLOOKUP(BI26,$BC:$BC,$BE:$BE)*BP26 -> 96.214436
... B33: Outbound | C33: Land | D33: {=_xlfn.REGEXEXTRACT(G33,"FG-R-\d{4}LE\d{2}")} -> FG-R-2184LE25 | E33: M19 | F33: {=_xlfn.SWITCH(TRUE,T33>0,T33,Z33)} -> 468.552 | G33: FG-R-2184LE25.M19 | H33: 3 BROTHERS | I33: 561367 | J33: 2026/04/03 00:00:00 | K33: 2026/04/03 00:00:00 | L33: FG-R-2184LE25.M19 | M33: UL-5609967 | N33: SAIA-BURGESS AUTOMOTIVE ACTUATORS, LLC | O33: 755 Bill Jones Drive | P33: JOHNSON ELECTRIC NORTH AMERICA | Q33: 47660 HALYARD DRIVE | R33: 1 | S33: 447.552 | T33: 468.552 | U33: 54 | V33: 420.12 | W33: 447.552 | X33: 0 | Y33: 0 | Z33: 0 | AA33: 0 | AB33: 0 | AC33: 0 | AD33: 1 | AE33: 0 | AF33: 0 | AG33: 1 | AH33: 0 | AI33: 0 | AJ33: 6173326 | AK33: Closed | AL33: 2026-04-03 | AM33: JE USA OU | AN33: 202000289783 | AO33: 02-APR-26 | AP33: 4814.88 | AQ33: USD | AR33: 1999-5YY1256EN | AS33: 216 | AT33: EA | AU33: 26101200 | AV33: Motores eléctricos de corriente directa DC | AW33: H87 | AX33: Pieza | AY33: 8501310500 | AZ33: Motores con potencia superior o igual a 186 W (¼ CP), excepto lo comprendido en las fracciones arancelarias 8501.31.03 y 8501.31.04 | BC33: FG-R-2206LE26 | BD33: 0 | BE33: 4918.7603 | BG33: Outbound | BH33: Land | BI33: FG-R-2182LE25 | BJ33: JOHNSON ELECTRIC NORTH AMERICA, INC. | BK33: APX WH 6001 GLOBAL DISTRIBUTION WAY LOUISVILLE, KY 40228 | BL33: M45 | BM33: 1999-1E30016EU | BN33: 3528 | BO33: 3091.256 | BP33: =BO33/SUMIFS($BO:$BO,$BI:$BI,BI33) -> 0.25676748 | BQ33: =_xlfn.XLOOKUP(BI33,$BC:$BC,$BE:$BE)*BP33 -> 1547.024
B34: Outbound | C34: Land | D34: {=_xlfn.REGEXEXTRACT(G34,"FG-R-\d{4}LE\d{2}")} -> FG-R-2184LE25 | E34: M19 | F34: {=_xlfn.SWITCH(TRUE,T34>0,T34,Z34)} -> 468.552 | G34: FG-R-2184LE25.M19 | H34: 3 BROTHERS | I34: 561367 | J34: 2026/04/03 00:00:00 | K34: 2026/04/03 00:00:00 | L34: FG-R-2184LE25.M19 | M34: UL-5609967 | N34: SAIA-BURGESS AUTOMOTIVE ACTUATORS, LLC | O34: 755 Bill Jones Drive | P34: JOHNSON ELECTRIC NORTH AMERICA | Q34: 47660 HALYARD DRIVE | R34: 1 | S34: 447.552 | T34: 468.552 | U34: 54 | V34: 420.12 | W34: 447.552 | X34: 0 | Y34: 0 | Z34: 0 | AA34: 0 | AB34: 0 | AC34: 0 | AD34: 1 | AE34: 0 | AF34: 0 | AG34: 1 | AH34: 0 | AI34: 0 | AJ34: 6173326 | AK34: Closed | AL34: 2026-04-03 | AM34: JE USA OU | AN34: 202000289784 | AO34: 02-APR-26 | AP34: 4150.76 | AQ34: USD | AR34: 1999-5YY1256EN | AS34: 216 | AT34: EA | AU34: 26101200 | AV34: Motores eléctricos de corriente directa DC | AW34: H87 | AX34: Pieza | AY34: 8501310500 | AZ34: Motores con potencia superior o igual a 186 W (¼ CP), excepto lo comprendido en las fracciones arancelarias 8501.31.03 y 8501.31.04 | BG34: Outbound | BH34: Land | BI34: FG-R-2182LE25 | BJ34: JOHNSON ELECTRIC NORTH AMERICA, INC. | BK34: APX WH 6001 GLOBAL DISTRIBUTION WAY LOUISVILLE, KY 40228 | BL34: M45 | BM34: 1999-1E30016EU | BN34: 3024 | BO34: 2649.648 | BP34: =BO34/SUMIFS($BO:$BO,$BI:$BI,BI34) -> 0.22008641 | BQ34: =_xlfn.XLOOKUP(BI34,$BC:$BC,$BE:$BE)*BP34 -> 1326.0206
B35: Outbound | C35: Land | D35: {=_xlfn.REGEXEXTRACT(G35,"FG-R-\d{4}LE\d{2}")} -> FG-R-2184LE25 | E35: M19 | F35: {=_xlfn.SWITCH(TRUE,T35>0,T35,Z35)} -> 3262.476 | G35: FG-R-2184LE25.M19 | H35: 3 BROTHERS | I35: 561367 | J35: 2026/04/03 00:00:00 | K35: 2026/04/03 00:00:00 | L35: FG-R-2184LE25.M19 | M35: UL-5609967 | N35: SAIA-BURGESS AUTOMOTIVE ACTUATORS, LLC | O35: 755 Bill Jones Drive | P35: JOHNSON ELECTRIC NORTH AMERICA | Q35: 47660 HALYARD DRIVE | R35: 7 | S35: 3115.476 | T35: 3262.476 | U35: 378 | V35: 2923.452 | W35: 3115.476 | X35: 0 | Y35: 0 | Z35: 0 | AA35: 0 | AB35: 0 | AC35: 0 | AD35: 7 | AE35: 0 | AF35: 0 | AG35: 7 | AH35: 0 | AI35: 0 | AJ35: 6173322 | AK35: Closed | AL35: 2026-04-03 | AM35: JE USA OU | AN35: 202000289780 | AO35: 02-APR-26 | AP35: 34829.27 | AQ35: USD | AR35: 1999-5YY2043EN | AS35: 1134 | AT35: EA | AU35: 26101200 | AV35: Motores eléctricos de corriente directa DC | AW35: H87 | AX35: Pieza | AY35: 8501320500 | AZ35: Motores de potencia igual o inferior a 3.75 kW (5 CP) | BG35: Outbound | BH35: Land | BI35: FG-R-2183LE25 | BJ35: SAIA-BURGESS AUTOMOTIVE ACTUATORS, LLC | BK35: 755 BILL JONES DRIVE | BL35: M19 | BM35: 1999-5YY0871EN | BN35: 27 | BO35: 93.92 | BP35: =BO35/SUMIFS($BO:$BO,$BI:$BI,BI35) -> 0.0019003739 | BQ35: =_xlfn.XLOOKUP(BI35,$BC:$BC,$BE:$BE)*BP35 -> 9.8762434
B36: Outbound | C36: Land | D36: {=_xlfn.REGEXEXTRACT(G36,"FG-R-\d{4}LE\d{2}")} -> FG-R-2184LE25 | E36: M19 | F36: {=_xlfn.SWITCH(TRUE,T36>0,T36,Z36)} -> 3262.476 | G36: FG-R-2184LE25.M19 | H36: 3 BROTHERS | I36: 561367 | J36: 2026/04/03 00:00:00 | K36: 2026/04/03 00:00:00 | L36: FG-R-2184LE25.M19 | M36: UL-5609967 | N36: SAIA-BURGESS AUTOMOTIVE ACTUATORS, LLC | O36: 755 Bill Jones Drive | P36: JOHNSON ELECTRIC NORTH AMERICA | Q36: 47660 HALYARD DRIVE | R36: 7 | S36: 3115.476 | T36: 3262.476 | U36: 378 | V36: 2923.452 | W36: 3115.476 | X36: 0 | Y36: 0 | Z36: 0 | AA36: 0 | AB36: 0 | AC36: 0 | AD36: 7 | AE36: 0 | AF36: 0 | AG36: 7 | AH36: 0 | AI36: 0 | AJ36: 6173322 | AK36: Closed | AL36: 2026-04-03 | AM36: JE USA OU | AN36: 202000289781 | AO36: 02-APR-26 | AP36: 26121.96 | AQ36: USD | AR36: 1999-5YY2043EN | AS36: 1134 | AT36: EA | AU36: 26101200 | AV36: Motores eléctricos de corriente directa DC | AW36: H87 | AX36: Pieza | AY36: 8501320500 | AZ36: Motores de potencia igual o inferior a 3.75 kW (5 CP) | BG36: Outbound | BH36: Land | BI36: FG-R-2183LE25 | BJ36: SAIA-BURGESS AUTOMOTIVE ACTUATORS, LLC | BK36: 755 Bill Jones Drive | BL36: M19 | BM36: 1999-5YY1445EN | BN36: 1512 | BO36: 3326.736 | BP36: =BO36/SUMIFS($BO:$BO,$BI:$BI,BI36) -> 0.067313058 | BQ36: =_xlfn.XLOOKUP(BI36,$BC:$BC,$BE:$BE)*BP36 -> 349.82596
B37: Outbound | C37: Land | D37: {=_xlfn.REGEXEXTRACT(G37,"FG-R-\d{4}LE\d{2}")} -> FG-R-2182LE25 | E37: M23 | F37: {=_xlfn.SWITCH(TRUE,T37>0,T37,Z37)} -> 879.04 | G37: FG-R-2182LE25.M46-M45 | H37: 3 BROTHERS | I37: 562325 | J37: 2026/04/03 00:00:00 | K37: 2026/04/03 00:00:00 | L37: FG-R-2182LE25.M46-M45-2 | M37: UL-5606474 | N37: JOHNSON ELECTRIC NORTH AMERICA, INC. | O37: (TDS) Transcontinental Distribution Services, Inc 14213 Transportation Ave | P37: Johnson Electric Group Mexico, S. de R. L. de C.V. | Q37: Boulevard Morelos # 1109,Mega Parque Industrial Aeropuerto de Calera,98519, Calera | R37: 4 | S37: 795.04 | T37: 879.04 | U37: 80 | V37: 696.48 | W37: 795.04 | X37: 0 | Y37: 0 | Z37: 0 | AA37: 0 | AB37: 0 | AC37: 0 | AD37: 4 | AE37: 0 | AF37: 0 | AG37: 0 | AH37: 4 | AI37: 0 | AJ37: 6173261 | AK37: Closed | AL37: 2026-04-03 | AM37: JE JMX OU | AN37: 202300058572 | AO37: 02-APR-26 | AP37: 18152.08 | AQ37: USD | AR37: 1908-1E90003RN | AS37: 480 | AT37: EA | AU37: 40151503 | AV37: Bombas centrífugas | AW37: H87 | AX37: Pieza | AY37: 8413309902 | AZ37: Para agua | BG37: Outbound | BH37: Land | BI37: FG-R-2183LE25 | BJ37: SAIA-BURGESS AUTOMOTIVE ACTUATORS, LLC | BK37: 755 Bill Jones Drive | BL37: M19 | BM37: 1999-5YY1445EN | BN37: 1512 | BO37: 3326.736 | BP37: =BO37/SUMIFS($BO:$BO,$BI:$BI,BI37) -> 0.067313058 | BQ37: =_xlfn.XLOOKUP(BI37,$BC:$BC,$BE:$BE)*BP37 -> 349.82596
B38: Outbound | C38: Land | D38: {=_xlfn.REGEXEXTRACT(G38,"FG-R-\d{4}LE\d{2}")} -> FG-R-2182LE25 | E38: M46 | F38: {=_xlfn.SWITCH(TRUE,T38>0,T38,Z38)} -> 14.618 | G38: FG-R-2182LE25.M46-M45-2 | H38: 3 BROTHERS | I38: 562325 | J38: 2026/04/03 00:00:00 | K38: 2026/04/03 00:00:00 | L38: FG-R-2182LE25.M46-M45-2 | M38: UL-5606474 | N38: JOHNSON ELECTRIC NORTH AMERICA, INC. | O38: (TDS) Transcontinental Distribution Services, Inc 14213 Transportation Ave | P38: Johnson Electric Group Mexico, S. de R. L. de C.V. | Q38: Boulevard Morelos # 1109,Mega Parque Industrial Aeropuerto de Calera,98519, Calera | R38: 0 | S38: 0 | T38: 0 | U38: 0 | V38: 0 | W38: 0 | X38: 1 | Y38: 2.618 | Z38: 14.618 | AA38: 1 | AB38: 1.5 | AC38: 2.618 | AD38: 1 | AE38: 0 | AF38: 0 | AG38: 1 | AH38: 0 | AI38: 0 | AJ38: 6173335 | AK38: Closed | AL38: 2026-04-03 | AM38: JE JMX OU | AN38: 202300058596 | AO38: 02-APR-26 | AP38: 101.17 | AQ38: USD | AR38: 1651-MYY0054EN | AS38: 10 | AT38: EA | AU38: 26101200 | AV38: Motores eléctricos de corriente directa DC | AW38: H87 | AX38: Pieza | AY38: 8501101004 | AZ38: Accionados exclusivamente por corriente continua | BG38: Outbound | BH38: Land | BI38: FG-R-2183LE25 | BJ38: SAIA-BURGESS AUTOMOTIVE ACTUATORS, LLC | BK38: 755 Bill Jones Drive | BL38: M19 | BM38: 1999-5YY1445EN | BN38: 1512 | BO38: 3326.736 | BP38: =BO38/SUMIFS($BO:$BO,$BI:$BI,BI38) -> 0.067313058 | BQ38: =_xlfn.XLOOKUP(BI38,$BC:$BC,$BE:$BE)*BP38 -> 349.82596
B39: Outbound | C39: Land | D39: {=_xlfn.REGEXEXTRACT(G39,"FG-R-\d{4}LE\d{2}")} -> FG-R-2182LE25 | E39: M46 | F39: {=_xlfn.SWITCH(TRUE,T39>0,T39,Z39)} -> 105.268 | G39: FG-R-2182LE25.M46-M45-2 | H39: 3 BROTHERS | I39: 562325 | J39: 2026/04/03 00:00:00 | K39: 2026/04/03 00:00:00 | L39: FG-R-2182LE25.M46-M45-2 | M39: UL-5606474 | N39: JOHNSON ELECTRIC NORTH AMERICA, INC. | O39: (TDS) Transcontinental Distribution Services, Inc 14213 Transportation Ave | P39: Johnson Electric Group Mexico, S. de R. L. de C.V. | Q39: Boulevard Morelos # 1109,Mega Parque Industrial Aeropuerto de Calera,98519, Calera | R39: 0 | S39: 0 | T39: 0 | U39: 0 | V39: 0 | W39: 0 | X39: 1 | Y39: 93.268 | Z39: 105.268 | AA39: 14 | AB39: 77.616 | AC39: 93.268 | AD39: 1 | AE39: 0 | AF39: 0 | AG39: 1 | AH39: 0 | AI39: 0 | AJ39: 6173334 | AK39: Closed | AL39: 2026-04-03 | AM39: JE JMX OU | AN39: 202300058594 | AO39: 02-APR-26 | AP39: 5076.34 | AQ39: USD | AR39: 1651-MYY0047EN | AS39: 504 | AT39: EA | AU39: 26101200 | AV39: Motores eléctricos de corriente directa DC | AW39: H87 | AX39: Pieza | AY39: 8501101004 | AZ39: Accionados exclusivamente por corriente continua | BG39: Outbound | BH39: Land | BI39: FG-R-2183LE25 | BJ39: SAIA-BURGESS AUTOMOTIVE ACTUATORS, LLC | BK39: 755 Bill Jones Drive | BL39: M19 | BM39: 1999-5YY2044EN | BN39: 4050 | BO39: 12591.3 | BP39: =BO39/SUMIFS($BO:$BO,$BI:$BI,BI39) -> 0.25477192 | BQ39: =_xlfn.XLOOKUP(BI39,$BC:$BC,$BE:$BE)*BP39 -> 1324.0497
B40: Outbound | C40: Land | D40: {=_xlfn.REGEXEXTRACT(G40,"FG-R-\d{4}LE\d{2}")} -> FG-R-2182LE25 | E40: M45 | F40: {=_xlfn.SWITCH(TRUE,T40>0,T40,Z40)} -> 5299.296 | G40: FG-R-2182LE25.M46-M45-2 | H40: 3 BROTHERS | I40: 562325 | J40: 2026/04/03 00:00:00 | K40: 2026/04/03 00:00:00 | L40: FG-R-2182LE25.M46-M45-2 | M40: UL-5606474 | N40: JOHNSON ELECTRIC NORTH AMERICA, INC. | O40: APX WH 6001 GLOBAL DISTRIBUTION WAY LOUISVILLE, KY 40228 | P40: Johnson Electric Group Mexico, S. de R. L. de C.V. | Q40: Boulevard Morelos # 1109,Mega Parque Industrial Aeropuerto de Calera,98519, Calera | R40: 12 | S40: 5077.296 | T40: 5299.296 | U40: 504 | V40: 4886.784 | W40: 5077.296 | X40: 0 | Y40: 0 | Z40: 0 | AA40: 0 | AB40: 0 | AC40: 0 | AD40: 12 | AE40: 0 | AF40: 0 | AG40: 12 | AH40: 0 | AI40: 0 | AJ40: 6173339 | AK40: Closed | AL40: 2026-04-03 | AM40: JE JMX OU | AN40: 202300058593 | AO40: 02-APR-26 | AP40: 36297.6 | AQ40: USD | AR40: 1999-1E30016EU | AS40: 6048 | AT40: EA | AU40: 40151500 | AV40: Bombas | AW40: H87 | AX40: Pieza | AY40: 8413709999 | AZ40: Las demás | BG40: Outbound | BH40: Land | BI40: FG-R-2183LE25 | BJ40: SAIA-BURGESS AUTOMOTIVE ACTUATORS, LLC | BK40: 755 Bill Jones Drive | BL40: M19 | BM40: 1999-5YY2044EN | BN40: 4050 | BO40: 12591.3 | BP40: =BO40/SUMIFS($BO:$BO,$BI:$BI,BI40) -> 0.25477192 | BQ40: =_xlfn.XLOOKUP(BI40,$BC:$BC,$BE:$BE)*BP40 -> 1324.0497
B41: Outbound | C41: Land | D41: {=_xlfn.REGEXEXTRACT(G41,"FG-R-\d{4}LE\d{2}")} -> FG-R-2182LE25 | E41: M45 | F41: {=_xlfn.SWITCH(TRUE,T41>0,T41,Z41)} -> 3091.256 | G41: FG-R-2182LE25.M46-M45-2 | H41: 3 BROTHERS | I41: 562325 | J41: 2026/04/03 00:00:00 | K41: 2026/04/03 00:00:00 | L41: FG-R-2182LE25.M46-M45-2 | M41: UL-5606474 | N41: JOHNSON ELECTRIC NORTH AMERICA, INC. | O41: APX WH 6001 GLOBAL DISTRIBUTION WAY LOUISVILLE, KY 40228 | P41: Johnson Electric Group Mexico, S. de R. L. de C.V. | Q41: Boulevard Morelos # 1109,Mega Parque Industrial Aeropuerto de Calera,98519, Calera | R41: 7 | S41: 2961.756 | T41: 3091.256 | U41: 294 | V41: 2850.624 | W41: 2961.756 | X41: 0 | Y41: 0 | Z41: 0 | AA41: 0 | AB41: 0 | AC41: 0 | AD41: 7 | AE41: 0 | AF41: 0 | AG41: 7 | AH41: 0 | AI41: 0 | AJ41: 6173336 | AK41: Closed | AL41: 2026-04-03 | AM41: JE JMX OU | AN41: 202300058599 | AO41: 02-APR-26 | AP41: 21173.6 | AQ41: USD | AR41: 1999-1E30016EU | AS41: 3528 | AT41: EA | AU41: 40151500 | AV41: Bombas | AW41: H87 | AX41: Pieza | AY41: 8413709999 | AZ41: Las demás | BG41: Outbound | BH41: Land | BI41: FG-R-2183LE25 | BJ41: SAIA-BURGESS AUTOMOTIVE ACTUATORS, LLC | BK41: 755 Bill Jones Drive | BL41: M19 | BM41: 1999-5YY2044EN | BN41: 4050 | BO41: 12591.3 | BP41: =BO41/SUMIFS($BO:$BO,$BI:$BI,BI41) -> 0.25477192 | BQ41: =_xlfn.XLOOKUP(BI41,$BC:$BC,$BE:$BE)*BP41 -> 1324.0497
B42: Outbound | C42: Land | D42: {=_xlfn.REGEXEXTRACT(G42,"FG-R-\d{4}LE\d{2}")} -> FG-R-2182LE25 | E42: M45 | F42: {=_xlfn.SWITCH(TRUE,T42>0,T42,Z42)} -> 2649.648 | G42: FG-R-2182LE25.M46-M45-2 | H42: 3 BROTHERS | I42: 562325 | J42: 2026/04/03 00:00:00 | K42: 2026/04/03 00:00:00 | L42: FG-R-2182LE25.M46-M45-2 | M42: UL-5606474 | N42: JOHNSON ELECTRIC NORTH AMERICA, INC. | O42: APX WH 6001 GLOBAL DISTRIBUTION WAY LOUISVILLE, KY 40228 | P42: Johnson Electric Group Mexico, S. de R. L. de C.V. | Q42: Boulevard Morelos # 1109,Mega Parque Industrial Aeropuerto de Calera,98519, Calera | R42: 6 | S42: 2538.648 | T42: 2649.648 | U42: 252 | V42: 2443.392 | W42: 2538.648 | X42: 0 | Y42: 0 | Z42: 0 | AA42: 0 | AB42: 0 | AC42: 0 | AD42: 6 | AE42: 0 | AF42: 0 | AG42: 6 | AH42: 0 | AI42: 0 | AJ42: 6173337 | AK42: Closed | AL42: 2026-04-03 | AM42: JE JMX OU | AN42: 202300058600 | AO42: 02-APR-26 | AP42: 18148.8 | AQ42: USD | AR42: 1999-1E30016EU | AS42: 3024 | AT42: EA | AU42: 40151500 | AV42: Bombas | AW42: H87 | AX42: Pieza | AY42: 8413709999 | AZ42: Las demás | BG42: Outbound | BH42: Land | BI42: FG-R-2183LE25 | BJ42: SAIA-BURGESS AUTOMOTIVE ACTUATORS, LLC | BK42: 755 Bill Jones Drive | BL42: M19 | BM42: 1999-5YY0937EN | BN42: 50 | BO42: 175.62 | BP42: =BO42/SUMIFS($BO:$BO,$BI:$BI,BI42) -> 0.0035534888 | BQ42: =_xlfn.XLOOKUP(BI42,$BC:$BC,$BE:$BE)*BP42 -> 18.467482
B43: Outbound | C43: Land | D43: {=_xlfn.REGEXEXTRACT(G43,"FG-R-\d{4}LE\d{2}")} -> FG-R-2183LE25 | E43: M19 | F43: {=_xlfn.SWITCH(TRUE,T43>0,T43,Z43)} -> 93.92 | G43: FG-R-2183LE25.M19 | H43: 3 BROTHERS | I43: H06253 | J43: 2026/04/03 00:00:00 | K43: 2026/04/03 00:00:00 | L43: FG-R-2183LE25.M19 | M43: UL-5609966 | N43: SAIA-BURGESS AUTOMOTIVE ACTUATORS, LLC | O43: 755 BILL JONES DRIVE | P43: JOHNSON ELECTRIC NORTH AMERICA | Q43: 47660 HALYARD DRIVE | R43: 0 | S43: 0 | T43: 0 | U43: 0 | V43: 0 | W43: 0 | X43: 1 | Y43: 70.92 | Z43: 93.92 | AA43: 9 | AB43: 63.18 | AC43: 70.92 | AD43: 1 | AE43: 0 | AF43: 0 | AG43: 1 | AH43: 0 | AI43: 0 | AJ43: 6173352 | AK43: Closed | AL43: 2026-04-03 | AM43: JE USA OU | AN43: 202000289795 | AO43: 02-APR-26 | AP43: 1510.35 | AQ43: USD | AR43: 1999-5YY0871EN | AS43: 27 | AT43: EA | AU43: 26101200 | AV43: Motores eléctricos de corriente directa DC | AW43: H87 | AX43: Pieza | AY43: 8501310500 | AZ43: Motores con potencia superior o igual a 186 W (¼ CP), excepto lo comprendido en las fracciones arancelarias 8501.31.03 y 8501.31.04 | BG43: Outbound | BH43: Land | BI43: FG-R-2183LE25 | BJ43: SAIA-BURGESS AUTOMOTIVE ACTUATORS, LLC | BK43: 755 Bill Jones Drive | BL43: M19 | BM43: 1999-5YY2043EN | BN43: 486 | BO43: 1398.204 | BP43: =BO43/SUMIFS($BO:$BO,$BI:$BI,BI43) -> 0.02829121 | BQ43: =_xlfn.XLOOKUP(BI43,$BC:$BC,$BE:$BE)*BP43 -> 147.02942
B44: Outbound | C44: Land | D44: {=_xlfn.REGEXEXTRACT(G44,"FG-R-\d{4}LE\d{2}")} -> FG-R-2183LE25 | E44: M19 | F44: {=_xlfn.SWITCH(TRUE,T44>0,T44,Z44)} -> 3326.736 | G44: FG-R-2183LE25.M19 | H44: 3 BROTHERS | I44: H06253 | J44: 2026/04/03 00:00:00 | K44: 2026/04/03 00:00:00 | L44: FG-R-2183LE25.M19 | M44: UL-5609966 | N44: SAIA-BURGESS AUTOMOTIVE ACTUATORS, LLC | O44: 755 Bill Jones Drive | P44: JOHNSON ELECTRIC NORTH AMERICA | Q44: 47660 HALYARD DRIVE | R44: 7 | S44: 3179.736 | T44: 3326.736 | U44: 378 | V44: 2987.712 | W44: 3179.736 | X44: 0 | Y44: 0 | Z44: 0 | AA44: 0 | AB44: 0 | AC44: 0 | AD44: 7 | AE44: 0 | AF44: 0 | AG44: 7 | AH44: 0 | AI44: 0 | AJ44: 6175284 | AK44: Closed | AL44: 2026-04-03 | AM44: JE USA OU | AN44: 202000289807 | AO44: 03-APR-26 | AP44: 1833.98 | AQ44: USD | AR44: 1999-5YY1445EN | AS44: 1512 | AT44: EA | AU44: 26101200 | AV44: Motores eléctricos de corriente directa DC | AW44: H87 | AX44: Pieza | AY44: 8501310500 | AZ44: Motores con potencia superior o igual a 186 W (¼ CP), excepto lo comprendido en las fracciones arancelarias 8501.31.03 y 8501.31.04 | BG44: Outbound | BH44: Land | BI44: FG-R-2184LE25 | BJ44: SAIA-BURGESS AUTOMOTIVE ACTUATORS, LLC | BK44: 755 Bill Jones Drive | BL44: M19 | BM44: 1999-5YY1255EN | BN44: 5184 | BO44: 11245.248 | BP44: =BO44/SUMIFS($BO:$BO,$BI:$BI,BI44) -> 0.32901014 | BQ44: =_xlfn.XLOOKUP(BI44,$BC:$BC,$BE:$BE)*BP44 -> 1618.322
B45: Outbound | C45: Land | D45: {=_xlfn.REGEXEXTRACT(G45,"FG-R-\d{4}LE\d{2}")} -> FG-R-2183LE25 | E45: M19 | F45: {=_xlfn.SWITCH(TRUE,T45>0,T45,Z45)} -> 3326.736 | G45: FG-R-2183LE25.M19 | H45: 3 BROTHERS | I45: H06253 | J45: 2026/04/03 00:00:00 | K45: 2026/04/03 00:00:00 | L45: FG-R-2183LE25.M19 | M45: UL-5609966 | N45: SAIA-BURGESS AUTOMOTIVE ACTUATORS, LLC | O45: 755 Bill Jones Drive | P45: JOHNSON ELECTRIC NORTH AMERICA | Q45: 47660 HALYARD DRIVE | R45: 7 | S45: 3179.736 | T45: 3326.736 | U45: 378 | V45: 2987.712 | W45: 3179.736 | X45: 0 | Y45: 0 | Z45: 0 | AA45: 0 | AB45: 0 | AC45: 0 | AD45: 7 | AE45: 0 | AF45: 0 | AG45: 7 | AH45: 0 | AI45: 0 | AJ45: 6175284 | AK45: Closed | AL45: 2026-04-03 | AM45: JE USA OU | AN45: 202000289808 | AO45: 03-APR-26 | AP45: 54018.95 | AQ45: USD | AR45: 1999-5YY1445EN | AS45: 1512 | AT45: EA | AU45: 26101200 | AV45: Motores eléctricos de corriente directa DC | AW45: H87 | AX45: Pieza | AY45: 8501310500 | AZ45: Motores con potencia superior o igual a 186 W (¼ CP), excepto lo comprendido en las fracciones arancelarias 8501.31.03 y 8501.31.04 | BG45: Outbound | BH45: Land | BI45: FG-R-2184LE25 | BJ45: SAIA-BURGESS AUTOMOTIVE ACTUATORS, LLC | BK45: 755 Bill Jones Drive | BL45: M19 | BM45: 1999-5YY1255EN | BN45: 5184 | BO45: 11245.248 | BP45: =BO45/SUMIFS($BO:$BO,$BI:$BI,BI45) -> 0.32901014 | BQ45: =_xlfn.XLOOKUP(BI45,$BC:$BC,$BE:$BE)*BP45 -> 1618.322
... B263: Outbound | C263: Land | D263: {=_xlfn.REGEXEXTRACT(G263,"FG-R-\d{4}LE\d{2}")} -> FG-R-2202LE26 | E263: M19 | F263: {=_xlfn.SWITCH(TRUE,T263>0,T263,Z263)} -> 3801.984 | G263: FG-R-2202LE26.M19 | H263: ALFER | I263: SNLU212425 | J263: 2026/04/27 00:00:00 | K263: 2026/04/27 00:00:00 | L263: FG-R-2202LE26.M19 | M263: UL-5610060 | N263: SAIA-BURGESS AUTOMOTIVE ACTUATORS, LLC | O263: 755 Bill Jones Drive | P263: JOHNSON ELECTRIC NORTH AMERICA | Q263: 47660 HALYARD DRIVE | R263: 8 | S263: 3633.984 | T263: 3801.984 | U263: 432 | V263: 3414.528 | W263: 3633.984 | X263: 0 | Y263: 0 | Z263: 0 | AA263: 0 | AB263: 0 | AC263: 0 | AD263: 8 | AE263: 0 | AF263: 0 | AG263: 8 | AH263: 0 | AI263: 0 | AJ263: 6217294 | AK263: Closed | AL263: 2026-04-27 | AM263: JE USA OU | AN263: 202000290646 | AO263: 27-APR-26 | AP263: 34747.92 | AQ263: USD | AR263: 1999-5YY1145EN | AS263: 1728 | AT263: EA | AU263: 26101200 | AV263: Motores eléctricos de corriente directa DC | AW263: H87 | AX263: Pieza | AY263: 8501310500 | AZ263: Motores con potencia superior o igual a 186 W (¼ CP), excepto lo comprendido en las fracciones arancelarias 8501.31.03 y 8501.31.04 | BG263: Outbound | BH263: Land | BI263: FG-R-2206LE26 | BJ263: SAIA-BURGESS AUTOMOTIVE ACTUATORS, LLC | BK263: 755 Bill Jones Drive | BL263: M19 | BM263: 1999-5YY1145EN | BN263: 1944 | BO263: 4277.232 | BP263: =BO263/SUMIFS($BO:$BO,$BI:$BI,BI263) -> 0.14494571 | BQ263: =_xlfn.XLOOKUP(BI263,$BC:$BC,$BE:$BE)*BP263 -> 712.95321
B268: ═══════════════════════════════════════════════════════════════════════════════════════
B269: 🧪 SECCIÓN W18 - PRUEBA SEMANA 18 (Exportaciones) - Costo Fijo: $1,500 USD
BG270: W18 Extraction | BS270: W18 Output | BW270: Fix Cost W18
BG271: Inbound/Outbound | BH271: Method | BI271: Reference | BJ271: BU | BK271: Gross Weight | BL271: Customer | BM271: Address | BN271: Item | BO271: Qty Pzas | BP271: %Proportion | BQ271: Calc_Exp | BS271: BU | BT271: Log. Exp | BU271: %PCT | BW271: 1500

Sheet Sea
B1: {=_xlfn.SEQUENCE(1,85)} -> 1 | C1: 2 | D1: 3 | E1: 4 | F1: 5 | G1: 6 | H1: 7 | I1: 8 | J1: 9 | K1: 10 | L1: 11 | M1: 12 | N1: 13 | O1: 14 | P1: 15 | Q1: 16 | R1: 17 | S1: 18 | T1: 19 | U1: 20 | V1: 21 | W1: 22 | X1: 23 | Y1: 24 | Z1: 25 | AA1: 26 | AB1: 27 | AC1: 28 | AD1: 29 | AE1: 30 | AF1: 31 | AG1: 32 | AH1: 33 | AI1: 34 | AJ1: 35 | AK1: 36 | AL1: 37 | AM1: 38 | AN1: 39 | AO1: 40 | AP1: 41 | AQ1: 42 | AR1: 43 | AS1: 44 | AT1: 45 | AU1: 46 | AV1: 47 | AW1: 48 | AX1: 49 | AY1: 50 | AZ1: 51 | BA1: 52 | BB1: 53 | BC1: 54 | BD1: 55 | BE1: 56 | BF1: 57 | BG1: 58 | BH1: 59 | BI1: 60 | BJ1: 61 | BK1: 62 | BL1: 63 | BM1: 64 | BN1: 65 | BO1: 66 | BP1: 67 | BQ1: 68 | BR1: 69 | BS1: 70 | BT1: 71 | BU1: 72 | BV1: 73 | BW1: 74 | BX1: 75 | BY1: 76 | BZ1: 77 | CA1: 78 | CB1: 79 | CC1: 80 | CD1: 81 | CE1: 82 | CF1: 83 | CG1: 84 | CH1: 85 | CN1: {=_xlfn.TOROW(IF($B$2:$CH$2="X",_xlfn.ANCHORARRAY(B1),1/0),3)} -> 1 | CO1: 15 | CP1: 51 | CQ1: 66 | CS1: Container Cost
B2: X | P2: X | AW2: WHSU5760194 | AZ2: X | BO2: X | CN2: {=_xlfn.TOROW(IF($B$2:$CH$2="X",B5:CH5,1/0),3)} -> BU | CO2: Item Code | CP2: Container Number | CQ2: Total Gross Weight | CS2: 2500
AR3: =AR8/AQ8 -> 50000 | AS3: =AR3*0.0001 -> 5 | AZ3: PRO NUMBER/ TRACKING #
B5: BU | C5: Sales Order Number | D5: Sales Coordinator | E5: Oversea Sales Coordinator | F5: Customer Number | G5: Customer Name | H5: Customer Ship-to Address | I5: Customer Alternative Name | J5: Demand Class Code | K5: Sub Application Code | L5: Order Type | M5: Shipment Priority Code | N5: Line Number | O5: Shipment Number | P5: Item Code | Q5: Item Revision | R5: Item Category | S5: Item Description | T5: Payment Term | U5: Customer Po Number | V5: Printed Customer Part number | W5: Total Requested Quantity | X5: Ship Method Code | Y5: SO Line FOB Code(Incoterm) | Z5: Fob Code(Incoterm) | AA5: Freight Terms Code (Incoterm Named Place) | AB5: Port of Loading | AC5: Destination | AD5: Promise Date | AE5: Customer Request Date | AF5: Schedule Ship Date | AG5: Subinventory | AH5: D.O. Number/PO Doc. Number | AI5: D.O. Creation Date/Actual Shipment Date | AJ5: Actual Ship Date | AK5: Shipped Quantity | AL5: Bill to Customer Number | AM5: Invoice Number | AN5: Invoice Date | AO5: Invoice Creation Date Time | AP5: Invoice Currency Code | AQ5: Invoice Unit Selling Price | AR5: Invoice Amount in Prime | AS5: Functional Currency Code | AT5: Invoice Amount in Functional Currency | AU5: Last Update By | AV5: Forwarder | AW5: Vessel Name | AX5: ETD Date | AY5: ETA Date | AZ5: Container Number | BA5: Shipment Volume | BB5: Waybill | BC5: Motor Per Carton | BD5: Weight UOM | BE5: Carton Gross Weight | BF5: Carton NET Weight | BG5: Carton Measurement UOM | BH5: Carton Length | BI5: Carton Width | BJ5: Carton Height | BK5: Number of Carton per Pallet | BL5: Weight UOM | BM5: Pallet Gross Weight | BN5: Pallet Net Weight | BO5: Total Gross Weight | BP5: Pallet Measurement UOM | BQ5: Pallet Length | BR5: Pallet Width | BS5: Pallet Height | BT5: Number of Full Pallet | BU5: Number of Non-Full Pallet | BV5: Total number of Pallet | BW5: Number of Full Carton | BX5: Number of Non-Full Carton | BY5: Total number of Carton | BZ5: Number of Motor in Full Pallet | CA5: Number of Motor in Non-Full Pallet | CB5: Total number of Motor | CC5: Total Motor Net Weight | CD5: Pallet Code | CE5: Carton Code | CF5: HS Code | CG5: Operating Unit | CJ5: List unig cont | CN5: BU | CO5: Item Code | CP5: Container Number | CQ5: Total Gross Weight | CR5: %Pond | CS5: Cost | CU5: Bu | CV5: Amount(USD) | CW5: Count | CX5: New Amoutn
B6: M01 | C6: 1015082406 | F6: 34798 | G6: JOHNSON ELECTRIC NORTH AMERICA INC. | H6: Tax ID JEG120120DD4 BOULEVARD MORELOS NO. 1109 MEGA PARQUE INDUSTRIAL AEROPUERTO DE CALERA C.P. 98519 CALERA ZACATECAS MX | I6: XEXX010101000 | J6: JEN | K6: A99 | L6: BI-INTERNAL-SWO-IM-MX | M6: FLOW | N6: 2 | O6: 1 | P6: CPPMSF3253/7EN | Q6: C | R6: DIRECT.FERRITE MAGNET.WET MAGNET: Grade 4 & 5 | S6: MAGNET (WET) | T6: TT45ASA | U6: 50950080806 | W6: 153120 | X6: SEA | Y6: CIP | Z6: CIP | AA6: MANZANILLO | AB6: HONG KONG | AC6: MANZANILLO | AD6: 46083 | AE6: 46153 | AF6: 46090 | AG6: NOR-MXA | AH6: 6123034 | AI6: 46083 | AJ6: 46083 | AK6: 153120 | AL6: 34798 | AM6: 101513753670 | AN6: 46083 | AO6: 46083.638 | AP6: USD | AQ6: 0.03348 | AR6: 5126.46 | AS6: USD | AT6: 5126.46 | AU6: JOHN JH SHI | AV6: OOCL-SEA-GEN | AW6: XIN OU ZHOU V.077E | AX6: 46093 | AY6: 46142 | AZ6: FBIU5071920 | BA6: 40' | BB6: OOLU2038497840 | BO6: 1500 | CG6: JE IM OU | CJ6: {=_xlfn._xlws.SORT(_xlfn.UNIQUE(_xlfn._xlws.FILTER($AZ$6:$AZ$1217,$AZ$6:$AZ$1217<>"")))} -> AMFU4236030 | CN6: {=_xlfn.LET(_xlpm.list,_xlfn.ANCHORARRAY(CJ6),_xlpm.data,_xlfn.CHOOSECOLS($B$5:$CG$1217,1,15,51,66),_xlpm.out,_xlfn.DROP(_xlfn.REDUCE("",_xlfn.SEQUENCE(ROWS(_xlpm.list)),_xlfn.LAMBDA(_xlpm.a,_xlpm.b,_xlfn.VSTACK(_xlpm.a,_xlfn._xlws.FILTER(_xlpm.data,_xlfn.CHOOSECOLS(_xlpm.data,3)=INDEX(_xlpm.list,_xlpm.b),"No data")))),1),_xlpm.out)} -> Capex | CO6: CAPEX-08 | CP6: AMFU4236030 | CQ6: 0 | CR6: =IFERROR(CQ6/(SUMIFS(CQ:CQ,CP:CP,CP6)),100%) -> 1 | CS6: =CR6*$CS$2 -> 2500 | CU6: {=_xlfn._xlws.SORT(_xlfn.UNIQUE(CN6:CN1167))} -> Capex | CV6: =SUMIFS(CS:CS,CN:CN,CU6) -> 7500 | CW6: 0
B7: M01 | C7: 1015082410 | F7: 34798 | G7: JOHNSON ELECTRIC NORTH AMERICA INC. | H7: Tax ID JEG120120DD4 BOULEVARD MORELOS NO. 1109 MEGA PARQUE INDUSTRIAL AEROPUERTO DE CALERA C.P. 98519 CALERA ZACATECAS MX | I7: XEXX010101000 | J7: JEN | K7: A99 | L7: BI-INTERNAL-SWO-IM-MX | M7: FLOW | N7: 4 | O7: 1 | P7: 1318-1030030EN | Q7: A | R7: DIRECT-JMX.PLASTIC MOULDING PARTS.OTHERS | S7: O-RING | T7: TT45ASA | U7: 50950080808 | W7: 50000 | X7: SEA | Y7: CIP | Z7: CIP | AA7: MANZANILLO | AB7: HONG KONG | AC7: MANZANILLO | AD7: 46083 | AE7: 46139 | AF7: 46090 | AG7: NOR-MXA | AH7: 6123037 | AI7: 46083 | AJ7: 46083 | AK7: 50000 | AL7: 34798 | AM7: 101513753673 | AN7: 46083 | AO7: 46083.638 | AP7: USD | AQ7: 0.02018 | AR7: 1009 | AS7: USD | AT7: 1009 | AU7: JOHN JH SHI | AV7: OOCL-SEA-GEN | AW7: XIN OU ZHOU V.077E | AX7: 46093 | AY7: 46142 | AZ7: FBIU5071920 | BA7: 40' | BB7: OOLU2038497840 | BE7: 0 | BF7: 0 | BM7: 0 | BN7: 0 | BO7: 20 | CG7: JE IM OU | CJ7: CAAU7526547 | CN7: Capex | CO7: CAPEX-08 | CP7: AMFU4236030 | CQ7: 0 | CR7: =IFERROR(CQ7/(SUMIFS(CQ:CQ,CP:CP,CP7)),100%) -> 1 | CS7: =CR7*$CS$2 -> 2500 | CU7: M01 | CV7: =SUMIFS(CS:CS,CN:CN,CU7) -> 20068.385 | CW7: 1 | CX7: =CV7 -> 20068.385 | CY7: =CX7/$CX$13 -> 0.14803945
B8: M01 | C8: 1015082413 | F8: 34798 | G8: JOHNSON ELECTRIC NORTH AMERICA INC. | H8: Tax ID JEG120120DD4 BOULEVARD MORELOS NO. 1109 MEGA PARQUE INDUSTRIAL AEROPUERTO DE CALERA C.P. 98519 CALERA ZACATECAS MX | I8: XEXX010101000 | J8: JEN | K8: A99 | L8: BI-INTERNAL-SWO-IM-MX | M8: FLOW | N8: 6 | O8: 1 | P8: 1318-1030018EN | Q8: B | R8: DIRECT-JMX.CONNECTOR / TERMINAL.SEAL | S8: SEAL | T8: TT45ASA | U8: 50950080812 | W8: 50000 | X8: SEA | Y8: CIP | Z8: CIP | AA8: MANZANILLO | AB8: HONG KONG | AC8: MANZANILLO | AD8: 46083 | AE8: 46153 | AF8: 46090 | AG8: NOR-MXA | AH8: 6123036 | AI8: 46083 | AJ8: 46083 | AK8: 50000 | AL8: 34798 | AM8: 101513753672 | AN8: 46083 | AO8: 46083.638 | AP8: USD | AQ8: 0.09412 | AR8: 4706 | AS8: USD | AT8: 4706 | AU8: JOHN JH SHI | AV8: OOCL-SEA-GEN | AW8: XIN OU ZHOU V.077E | AX8: 46093 | AY8: 46142 | AZ8: FBIU5071920 | BA8: 40' | BB8: OOLU2038497840 | BE8: 0 | BF8: 0 | BM8: 0 | BN8: 0 | BO8: 10 | CG8: JE IM OU | CJ8: CAIU8394197 | CN8: M19 | CO8: 1275-5YY0561EN | CP8: CAAU7526547 | CQ8: 1065.008 | CR8: =IFERROR(CQ8/(SUMIFS(CQ:CQ,CP:CP,CP8)),100%) -> 0.09407719 | CS8: =CR8*$CS$2 -> 235.19298 | CU8: M19 | CV8: =SUMIFS(CS:CS,CN:CN,CU8) -> 67070.158 | CW8: 1 | CX8: =CV8 -> 67070.158 | CY8: =CX8/$CX$13 -> 0.49475976
B9: M01 | C9: 1015082415 | F9: 34798 | G9: JOHNSON ELECTRIC NORTH AMERICA INC. | H9: Tax ID JEG120120DD4 BOULEVARD MORELOS NO. 1109 MEGA PARQUE INDUSTRIAL AEROPUERTO DE CALERA C.P. 98519 CALERA ZACATECAS MX | I9: XEXX010101000 | J9: JEN | K9: A99 | L9: BI-INTERNAL-SWO-IM-MX | M9: FLOW | N9: 7 | O9: 1 | P9: 1318-1030054EN | Q9: A | R9: DIRECT-JMX.CONNECTOR / TERMINAL.SEAL | S9: SEAL | T9: TT45ASA | U9: 50950080817 | W9: 80000 | X9: SEA | Y9: CIP | Z9: CIP | AA9: MANZANILLO | AB9: HONG KONG | AC9: MANZANILLO | AD9: 46083 | AE9: 46132 | AF9: 46090 | AG9: NOR-MXA | AH9: 6123035 | AI9: 46083 | AJ9: 46083 | AK9: 80000 | AL9: 34798 | AM9: 101513753671 | AN9: 46083 | AO9: 46083.638 | AP9: USD | AQ9: 0.05215 | AR9: 4172 | AS9: USD | AT9: 4172 | AU9: JOHN JH SHI | AV9: OOCL-SEA-GEN | AW9: XIN OU ZHOU V.077E | AX9: 46093 | AY9: 46142 | AZ9: FBIU5071920 | BA9: 40' | BB9: OOLU2038497840 | BE9: 0 | BF9: 0 | BM9: 0 | BN9: 0 | BO9: 10 | CG9: JE IM OU | CJ9: CCLU7673540 | CN9: M19 | CO9: 1275-5YY0783EN | CP9: CAAU7526547 | CQ9: 198.3128 | CR9: =IFERROR(CQ9/(SUMIFS(CQ:CQ,CP:CP,CP9)),100%) -> 0.017517907 | CS9: =CR9*$CS$2 -> 43.794767 | CU9: M23 | CV9: =SUMIFS(CS:CS,CN:CN,CU9) -> 4647.2024 | CW9: 1 | CX9: =CV9 -> 4647.2024 | CY9: =CX9/$CX$13 -> 0.034281248
B10: M01 | C10: 1015082415 | F10: 34798 | G10: JOHNSON ELECTRIC NORTH AMERICA INC. | H10: Tax ID JEG120120DD4 BOULEVARD MORELOS NO. 1109 MEGA PARQUE INDUSTRIAL AEROPUERTO DE CALERA C.P. 98519 CALERA ZACATECAS MX | I10: XEXX010101000 | J10: JEN | K10: A99 | L10: BI-INTERNAL-SWO-IM-MX | M10: FLOW | N10: 5 | O10: 1 | P10: 1318-1030054EN | Q10: A | R10: DIRECT-JMX.CONNECTOR / TERMINAL.SEAL | S10: SEAL | T10: TT45ASA | U10: 50950080817 | W10: 40000 | X10: SEA | Y10: CIP | Z10: CIP | AA10: MANZANILLO | AB10: HONG KONG | AC10: MANZANILLO | AD10: 46083 | AE10: 46139 | AF10: 46090 | AG10: NOR-MXA | AH10: 6123035 | AI10: 46083 | AJ10: 46083 | AK10: 40000 | AL10: 34798 | AM10: 101513753671 | AN10: 46083 | AO10: 46083.638 | AP10: USD | AQ10: 0.05215 | AR10: 2086 | AS10: USD | AT10: 2086 | AU10: JOHN JH SHI | AV10: OOCL-SEA-GEN | AW10: XIN OU ZHOU V.077E | AX10: 46093 | AY10: 46142 | AZ10: FBIU5071920 | BA10: 40' | BB10: OOLU2038497840 | BE10: 0 | BF10: 0 | BM10: 0 | BN10: 0 | BO10: 10 | CG10: JE IM OU | CJ10: CCLU7843605 | CN10: M19 | CO10: 1275-5YY0564EN | CP10: CAAU7526547 | CQ10: 354.4716 | CR10: =IFERROR(CQ10/(SUMIFS(CQ:CQ,CP:CP,CP10)),100%) -> 0.031312152 | CS10: =CR10*$CS$2 -> 78.280379 | CU10: M45 | CV10: =SUMIFS(CS:CS,CN:CN,CU10) -> 39522.267 | CW10: 1 | CX10: =CV10 -> 39522.267 | CY10: =CX10/$CX$13 -> 0.29154587
B11: M01 | C11: 1015082416 | F11: 34798 | G11: JOHNSON ELECTRIC NORTH AMERICA INC. | H11: Tax ID JEG120120DD4 BOULEVARD MORELOS NO. 1109 MEGA PARQUE INDUSTRIAL AEROPUERTO DE CALERA C.P. 98519 CALERA ZACATECAS MX | I11: XEXX010101000 | J11: JEN | K11: A99 | L11: BI-INTERNAL-SWO-IM-MX | M11: FLOW | N11: 4 | O11: 1 | P11: 1307-1030122EN | Q11: A | R11: DIRECT-JMX.FERRITE MAGNET.WET MAGNET: Grade 4 & 5 | S11: MAGNET | T11: TT45ASA | U11: 50950080814 | W11: 92800 | X11: SEA | Y11: CIP | Z11: CIP | AA11: MANZANILLO | AB11: HONG KONG | AC11: MANZANILLO | AD11: 46083 | AE11: 46139 | AF11: 46090 | AG11: NOR-MXA | AH11: 6123038 | AI11: 46083 | AJ11: 46083 | AK11: 92800 | AL11: 34798 | AM11: 101513753674 | AN11: 46083 | AO11: 46083.638 | AP11: USD | AQ11: 0.02512 | AR11: 2331.14 | AS11: USD | AT11: 2331.14 | AU11: JOHN JH SHI | AV11: OOCL-SEA-GEN | AW11: XIN OU ZHOU V.077E | AX11: 46093 | AY11: 46142 | AZ11: FBIU5071920 | BA11: 40' | BB11: OOLU2038497840 | BE11: 0 | BF11: 0 | BM11: 0 | BN11: 0 | BO11: 1500 | CG11: JE IM OU | CJ11: CSGU2004557 | CN11: M19 | CO11: 1275-5YY0696EN | CP11: CAAU7526547 | CQ11: 224.1176 | CR11: =IFERROR(CQ11/(SUMIFS(CQ:CQ,CP:CP,CP11)),100%) -> 0.019797367 | CS11: =CR11*$CS$2 -> 49.493417 | CU11: M46 | CV11: =SUMIFS(CS:CS,CN:CN,CU11) -> 4253.0487 | CW11: 1 | CX11: =CV11 -> 4253.0487 | CY11: =CX11/$CX$13 -> 0.031373675
B12: M01 | C12: 1015082901 | F12: 34798 | G12: JOHNSON ELECTRIC NORTH AMERICA INC. | H12: Tax ID JEG120120DD4 BOULEVARD MORELOS NO. 1109 MEGA PARQUE INDUSTRIAL AEROPUERTO DE CALERA C.P. 98519 CALERA ZACATECAS MX | I12: XEXX010101000 | J12: JEN | K12: A99 | L12: BI-INTERNAL-SWO-IM-MX | M12: FLOW | N12: 1 | O12: 1 | P12: 0060-1050290-YEN | Q12: A | R12: DIRECT-JMX.RAW MAGNET WIRE.CU WIRE ULTRA THICK SIZE (OD >300mm) | S12: POLYAMIDE-IMIDE MAGNET WIRE 1-AIW/220 | T12: TT45ASA | U12: 50950081370 | W12: 1475.48 | X12: SEA | Y12: CIP | Z12: CIP | AA12: MANZANILLO | AB12: HONG KONG | AC12: MANZANILLO | AD12: 46084 | AE12: 46146 | AF12: 46090 | AG12: NOR-MXA | AH12: 6123069 | AI12: 46083 | AJ12: 46083 | AK12: 1475.48 | AL12: 34798 | AM12: 101513753675 | AN12: 46083 | AO12: 46083.638 | AP12: USD | AQ12: 12.33275 | AR12: 18196.73 | AS12: USD | AT12: 18196.73 | AU12: JOHN JH SHI | AV12: OOCL-SEA-GEN | AW12: XIN OU ZHOU V.077E | AX12: 46093 | AY12: 46142 | AZ12: FBIU5071920 | BA12: 40' | BB12: OOLU2038497840 | BO12: =AR12/AQ12 -> 1475.4803 | CG12: JE IM OU | CJ12: CSGU6547742 | CN12: M45 | CO12: 1346-12C0011EN | CP12: CAAU7526547 | CQ12: 472.5282 | CR12: =IFERROR(CQ12/(SUMIFS(CQ:CQ,CP:CP,CP12)),100%) -> 0.041740649 | CS12: =CR12*$CS$2 -> 104.35162 | CU12: MCS | CV12: =SUMIFS(CS:CS,CN:CN,CU12) -> 6938.9393
B13: M01 | C13: 1015083179 | F13: 34798 | G13: JOHNSON ELECTRIC NORTH AMERICA INC. | H13: Tax ID JEG120120DD4 BOULEVARD MORELOS NO. 1109 MEGA PARQUE INDUSTRIAL AEROPUERTO DE CALERA C.P. 98519 CALERA ZACATECAS MX | I13: XEXX010101000 | J13: JEN | K13: A99 | L13: BI-INTERNAL-SWO-IM-MX | M13: FLOW | N13: 2 | O13: 1 | P13: 1307-1030122EN | Q13: A | R13: DIRECT-JMX.FERRITE MAGNET.WET MAGNET: Grade 4 & 5 | S13: MAGNET | T13: TT45ASA | U13: 50950081525 | W13: 92800 | X13: AIR | Y13: CIP | Z13: CIP | AA13: MANZANILLO | AB13: HONG KONG | AC13: MANZANILLO | AD13: 46083 | AE13: 46097 | AF13: 46090 | AG13: NOR-MXA | AH13: 6122651 | AI13: 46083 | AJ13: 46083 | AK13: 92800 | AL13: 34798 | AM13: 101513753573 | AN13: 46083 | AO13: 46083.44 | AP13: USD | AQ13: 0.02512 | AR13: 2331.14 | AS13: USD | AT13: 2331.14 | AU13: DICK ZJ WU | AV13: AIR | AW13: CV5165 | AX13: 46087 | AY13: 46095 | BA13: AIR | BB13: HKGA26533803 | BE13: 0 | BF13: 0 | BM13: 0 | BN13: 0 | BO13: 4000 | CG13: JE IM OU | CJ13: CSLU6094186 | CN13: M19 | CO13: 1330-5YY0182EN | CP13: CAAU7526547 | CQ13: 1229.4492 | CR13: =IFERROR(CQ13/(SUMIFS(CQ:CQ,CP:CP,CP13)),100%) -> 0.10860306 | CS13: =CR13*$CS$2 -> 271.50765 | CU13: Total | CV13: =SUM(CV6:CV12) -> 150000 | CX13: =SUM(CX7:CX12) -> 135561.06
B14: M01 | C14: 1015083179 | F14: 34798 | G14: JOHNSON ELECTRIC NORTH AMERICA INC. | H14: Tax ID JEG120120DD4 BOULEVARD MORELOS NO. 1109 MEGA PARQUE INDUSTRIAL AEROPUERTO DE CALERA C.P. 98519 CALERA ZACATECAS MX | I14: XEXX010101000 | J14: JEN | K14: A99 | L14: BI-INTERNAL-SWO-IM-MX | M14: FLOW | N14: 3 | O14: 1 | P14: 1307-1030122EN | Q14: A | R14: DIRECT-JMX.FERRITE MAGNET.WET MAGNET: Grade 4 & 5 | S14: MAGNET | T14: TT45ASA | U14: 50950081525 | W14: 92800 | X14: AIR | Y14: CIP | Z14: CIP | AA14: MANZANILLO | AB14: HONG KONG | AC14: MANZANILLO | AD14: 46083 | AE14: 46132 | AF14: 46090 | AG14: NOR-MXA | AH14: 6122651 | AI14: 46083 | AJ14: 46083 | AK14: 92800 | AL14: 34798 | AM14: 101513753573 | AN14: 46083 | AO14: 46083.44 | AP14: USD | AQ14: 0.02512 | AR14: 2331.14 | AS14: USD | AT14: 2331.14 | AU14: DICK ZJ WU | AV14: AIR | AW14: CV5165 | AX14: 46087 | AY14: 46095 | BA14: AIR | BB14: HKGA26533803 | BE14: 0 | BF14: 0 | BM14: 0 | BN14: 0 | BO14: 4000 | CG14: JE IM OU | CJ14: CSLU6140168 | CN14: M19 | CO14: 1330-5YY0256EN | CP14: CAAU7526547 | CQ14: 217.002 | CR14: =IFERROR(CQ14/(SUMIFS(CQ:CQ,CP:CP,CP14)),100%) -> 0.019168812 | CS14: =CR14*$CS$2 -> 47.922031
B15: M01 | C15: 1015083179 | F15: 34798 | G15: JOHNSON ELECTRIC NORTH AMERICA INC. | H15: Tax ID JEG120120DD4 BOULEVARD MORELOS NO. 1109 MEGA PARQUE INDUSTRIAL AEROPUERTO DE CALERA C.P. 98519 CALERA ZACATECAS MX | I15: XEXX010101000 | J15: JEN | K15: A99 | L15: BI-INTERNAL-SWO-IM-MX | M15: FLOW | N15: 1 | O15: 1 | P15: 1307-1030122EN | Q15: A | R15: DIRECT-JMX.FERRITE MAGNET.WET MAGNET: Grade 4 & 5 | S15: MAGNET | T15: TT45ASA | U15: 50950081525 | W15: 92800 | X15: AIR | Y15: CIP | Z15: CIP | AA15: MANZANILLO | AB15: HONG KONG | AC15: MANZANILLO | AD15: 46083 | AE15: 46139 | AF15: 46090 | AG15: NOR-MXA | AH15: 6122651 | AI15: 46083 | AJ15: 46083 | AK15: 92800 | AL15: 34798 | AM15: 101513753573 | AN15: 46083 | AO15: 46083.44 | AP15: USD | AQ15: 0.02512 | AR15: 2331.14 | AS15: USD | AT15: 2331.14 | AU15: DICK ZJ WU | AV15: AIR | AW15: CV5165 | AX15: 46087 | AY15: 46095 | BA15: AIR | BB15: HKGA26533803 | BE15: 0 | BF15: 0 | BM15: 0 | BN15: 0 | BO15: 4000 | CG15: JE IM OU | CJ15: CSLU6151413 | CN15: M19 | CO15: 1330-5YY0168EN | CP15: CAAU7526547 | CQ15: 256.992 | CR15: =IFERROR(CQ15/(SUMIFS(CQ:CQ,CP:CP,CP15)),100%) -> 0.022701318 | CS15: =CR15*$CS$2 -> 56.753295
B16: M19 | C16: 1195009925 | F16: 34798 | G16: JOHNSON ELECTRIC NORTH AMERICA INC. | H16: Tax ID JEG120120DD4 BOULEVARD MORELOS NO. 1109 MEGA PARQUE INDUSTRIAL AEROPUERTO DE CALERA C.P. 98519 CALERA ZACATECAS MX | I16: XEXX010101000 | J16: JEN | K16: Q06 | L16: PC-INTERNAL-SWO-IM-MX | M16: FLOW | N16: 1 | O16: 1 | P16: 1616-5YY3186-MTEN | Q16: A | R16: DIRECT.CATALOG PASSIVE ELECTRONIC.AXIAL LEADED MLCC | S16: CAPACITOR 8340114 | T16: TT45ASA | U16: 50950079458 | W16: 40000 | X16: SEA | Y16: CIP | Z16: CIP | AA16: MANZANILLO | AB16: HONG KONG | AC16: MANZANILLO | AD16: 46083 | AE16: 46139 | AF16: 46090 | AG16: NOR-J19 | AH16: 6123033 | AI16: 46083 | AJ16: 46083 | AK16: 40000 | AL16: 34798 | AM16: 101513753665 | AN16: 46083 | AO16: 46083.638 | AP16: USD | AQ16: 0.0633 | AR16: 2532 | AS16: USD | AT16: 2532 | AU16: JOHN JH SHI | AV16: OOCL-SEA-GEN | AW16: XIN OU ZHOU V.077E | AX16: 46093 | AY16: 46142 | AZ16: FBIU5071920 | BA16: 40' | BB16: OOLU2038497840 | BE16: 0 | BF16: 0 | BM16: 0 | BN16: 0 | BO16: 150 | CG16: JE IM OU | CJ16: CSNU6595689 | CN16: M19 | CO16: 1301-5YY0306EN0093 | CP16: CAAU7526547 | CQ16: 493.40628 | CR16: =IFERROR(CQ16/(SUMIFS(CQ:CQ,CP:CP,CP16)),100%) -> 0.043584909 | CS16: =CR16*$CS$2 -> 108.96227
B17: M19 | C17: 1195010094 | F17: 34798 | G17: JOHNSON ELECTRIC NORTH AMERICA INC. | H17: Tax ID JEG120120DD4 BOULEVARD MORELOS NO. 1109 MEGA PARQUE INDUSTRIAL AEROPUERTO DE CALERA C.P. 98519 CALERA ZACATECAS MX | I17: XEXX010101000 | J17: JEN | K17: Q06 | L17: PC-INTERNAL-SWO-IM-MX | M17: FLOW | N17: 1 | O17: 1 | P17: CPCSSSP2001/EP | Q17: B | R17: DIRECT.OTHER METAL/PLASTIC PARTS(CATALOGUE).SPRING | S17: SPRING 8130167 | T17: TT45ASA | U17: 50950081209 | W17: 64000 | X17: SEA | Y17: CIP | Z17: CIP | AA17: MANZANILLO | AB17: HONG KONG | AC17: MANZANILLO | AD17: 46083 | AE17: 46153 | AF17: 46090 | AG17: NOR-J19 | AH17: 6123031 | AI17: 46083 | AJ17: 46083 | AK17: 64000 | AL17: 34798 | AM17: 101513753663 | AN17: 46083 | AO17: 46083.638 | AP17: USD | AQ17: 0.00526 | AR17: 336.64 | AS17: USD | AT17: 336.64 | AU17: JOHN JH SHI | AV17: OOCL-SEA-GEN | AW17: XIN OU ZHOU V.077E | AX17: 46093 | AY17: 46142 | AZ17: FBIU5071920 | BA17: 40' | BB17: OOLU2038497840 | BE17: 0 | BF17: 0 | BM17: 0 | BN17: 0 | BO17: 20 | CG17: JE IM OU | CJ17: CSNU7139997 | CN17: M01 | CO17: 1102-0039190EN | CP17: CAAU7526547 | CQ17: 1197.24 | CR17: =IFERROR(CQ17/(SUMIFS(CQ:CQ,CP:CP,CP17)),100%) -> 0.10575787 | CS17: =CR17*$CS$2 -> 264.39467
B18: M19 | C18: 1195010103 | F18: 34798 | G18: JOHNSON ELECTRIC NORTH AMERICA INC. | H18: Tax ID JEG120120DD4 BOULEVARD MORELOS NO. 1109 MEGA PARQUE INDUSTRIAL AEROPUERTO DE CALERA C.P. 98519 CALERA ZACATECAS MX | I18: XEXX010101000 | J18: JEN | K18: Q06 | L18: PC-INTERNAL-SWO-IM-MX | M18: FLOW | N18: 1 | O18: 1 | P18: CPCSSSP2001/EP | Q18: B | R18: DIRECT.OTHER METAL/PLASTIC PARTS(CATALOGUE).SPRING | S18: SPRING 8130167 | T18: TT45ASA | U18: 50950081247 | W18: 64000 | X18: SEA | Y18: CIP | Z18: CIP | AA18: MANZANILLO | AB18: HONG KONG | AC18: MANZANILLO | AD18: 46083 | AE18: 46139 | AF18: 46090 | AG18: NOR-J19 | AH18: 6123032 | AI18: 46083 | AJ18: 46083 | AK18: 64000 | AL18: 34798 | AM18: 101513753664 | AN18: 46083 | AO18: 46083.638 | AP18: USD | AQ18: 0.00526 | AR18: 336.64 | AS18: USD | AT18: 336.64 | AU18: JOHN JH SHI | AV18: OOCL-SEA-GEN | AW18: XIN OU ZHOU V.077E | AX18: 46093 | AY18: 46142 | AZ18: FBIU5071920 | BA18: 40' | BB18: OOLU2038497840 | BE18: 0 | BF18: 0 | BM18: 0 | BN18: 0 | BO18: 20 | CG18: JE IM OU | CJ18: CSNU7460163 | CN18: M45 | CO18: 1301-12B0010EN | CP18: CAAU7526547 | CQ18: 296.29152 | CR18: =IFERROR(CQ18/(SUMIFS(CQ:CQ,CP:CP,CP18)),100%) -> 0.02617283 | CS18: =CR18*$CS$2 -> 65.432076
B19: MCS | C19: 1275406531 | F19: 34798 | G19: JOHNSON ELECTRIC NORTH AMERICA INC. | H19: Tax ID JEG120120DD4. BOULEVARD MORELOS NO. 1109 MEGA PARQUE INDUSTRIAL AEROPUERTO DE CALERA C.P. 98519 CALERA ZACATECAS MX | I19: XEXX010101000 | J19: JEN | K19: Y99 | L19: C&S-INTERNAL-SWO-IM-MX | M19: FLOW | N19: 1 | O19: 1 | P19: 0070-1100018 | Q19: A | R19: DIRECT.RAW PLASTIC.POM | S19: ACETAL RESIN (POM) | T19: TT45ASA | U19: 50950080782 | W19: 500 | X19: SEA | Y19: CIP | Z19: CIP | AA19: MANZANILLO | AB19: HONG KONG | AC19: MANZANILLO | AD19: 46083 | AE19: 46146 | AF19: 46090 | AG19: NOR-MXC | AH19: 6122375 | AI19: 46083 | AJ19: 46083 | AK19: 500 | AL19: 34798 | AM19: 101513753431 | AN19: 46083 | AO19: 46083.351 | AP19: USD | AQ19: 3.70823 | AR19: 1854.12 | AS19: USD | AT19: 1854.12 | AU19: JOHN JH SHI | AV19: OOCL-SEA-GEN | AW19: XIN OU ZHOU V.077E | AX19: 46093 | AY19: 46142 | AZ19: FBIU5071920 | BA19: 40' | BB19: OOLU2038497840 | BE19: 0 | BF19: 0 | BM19: 0 | BN19: 0 | BO19: =AR19/AQ19 -> 500.00135 | CG19: JE IM OU | CJ19: CSNU7568097 | CN19: M45 | CO19: 1163-12B0002EN0093 | CP19: CAAU7526547 | CQ19: 42.22 | CR19: =IFERROR(CQ19/(SUMIFS(CQ:CQ,CP:CP,CP19)),100%) -> 0.0037294921 | CS19: =CR19*$CS$2 -> 9.3237304
B20: MCS | C20: 1275409290 | F20: 34798 | G20: JOHNSON ELECTRIC NORTH AMERICA INC. | H20: Tax ID JEG120120DD4. BOULEVARD MORELOS NO. 1109 MEGA PARQUE INDUSTRIAL AEROPUERTO DE CALERA C.P. 98519 CALERA ZACATECAS MX | I20: XEXX010101000 | J20: JEN | K20: Y99 | L20: C&S-INTERNAL-SWO-IM-MX | M20: FLOW | N20: 1 | O20: 1 | P20: 0070-5050006 | Q20: A | R20: DIRECT.RAW PLASTIC.PBT | S20: 30%GLASS FIBER REINFORCED PBT | T20: TT45ASA | U20: 50950081100 | W20: 4000 | X20: SEA | Y20: CIP | Z20: CIP | AA20: MANZANILLO | AB20: HONG KONG | AC20: MANZANILLO | AD20: 46083 | AE20: 46139 | AF20: 46090 | AG20: NOR-MXC | AH20: 6122376 | AI20: 46083 | AJ20: 46083 | AK20: 4000 | AL20: 34798 | AM20: 101513753432 | AN20: 46083 | AO20: 46083.351 | AP20: USD | AQ20: 3.04074 | AR20: 12162.96 | AS20: USD | AT20: 12162.96 | AU20: JOHN JH SHI | AV20: OOCL-SEA-GEN | AW20: XIN OU ZHOU V.077E | AX20: 46093 | AY20: 46142 | AZ20: FBIU5071920 | BA20: 40' | BB20: OOLU2038497840 | BE20: 0 | BF20: 0 | BM20: 0 | BN20: 0 | BO20: =AR20/AQ20 -> 4000 | CG20: JE IM OU | CJ20: FBIU5071920 | CN20: M45 | CO20: AYSP61AS871EN | CP20: CAAU7526547 | CQ20: 946.4002 | CR20: =IFERROR(CQ20/(SUMIFS(CQ:CQ,CP:CP,CP20)),100%) -> 0.083600003 | CS20: =CR20*$CS$2 -> 209.00001
B21: M45 | C21: 1615004657 | F21: 34798 | G21: JOHNSON ELECTRIC NORTH AMERICA INC. | H21: Tax ID JEG120120DD4 BOULEVARD MORELOS NO. 1109 MEGA PARQUE INDUSTRIAL AEROPUERTO DE CALERA C.P. 98519 CALERA ZACATECAS MX | I21: XEXX010101000 | J21: JEN | K21: IPG0099 | L21: S1-INTERNAL-SWO-IM-MX | M21: FLOW | N21: 1 | O21: 1 | P21: 1406-12B0001EN | Q21: B | R21: DIRECT.FASTENING PARTS.OTHERS | S21: LOCK RING(EAR CLAMP) | T21: TT45ASA | U21: 50950080037 | W21: 60000 | X21: SEA | Y21: CIP | Z21: CIP | AA21: MANZANILLO | AB21: HONG KONG | AC21: MANZANILLO | AD21: 46083 | AE21: 46139 | AF21: 46090 | AG21: NOR-MXI | AH21: 6123040 | AI21: 46083 | AJ21: 46083 | AK21: 60000 | AL21: 34798 | AM21: 101513753667 | AN21: 46083 | AO21: 46083.638 | AP21: USD | AQ21: 0.13126 | AR21: 7875.6 | AS21: USD | AT21: 7875.6 | AU21: JOHN JH SHI | AV21: OOCL-SEA-GEN | AW21: XIN OU ZHOU V.077E | AX21: 46093 | AY21: 46142 | AZ21: FBIU5071920 | BA21: 40' | BB21: OOLU2038497840 | BE21: 0 | BF21: 0 | BM21: 0 | BN21: 0 | BO21: 50 | CG21: JE IM OU | CJ21: FFAU1272834 | CN21: M45 | CO21: AYSP61AS981EN | CP21: CAAU7526547 | CQ21: 2365.8006 | CR21: =IFERROR(CQ21/(SUMIFS(CQ:CQ,CP:CP,CP21)),100%) -> 0.20898235 | CS21: =CR21*$CS$2 -> 522.45587
B22: M45 | C22: 1615004696 | F22: 34798 | G22: JOHNSON ELECTRIC NORTH AMERICA INC. | H22: Tax ID JEG120120DD4 BOULEVARD MORELOS NO. 1109 MEGA PARQUE INDUSTRIAL AEROPUERTO DE CALERA C.P. 98519 CALERA ZACATECAS MX | I22: XEXX010101000 | J22: JEN | K22: IPG0099 | L22: S1-INTERNAL-SWO-IM-MX | M22: FLOW | N22: 1 | O22: 1 | P22: 1318-11A0060EN | Q22: B | R22: DIRECT.RUBBER SEAL / RUBBER PARTS.MOLDED RUBBER PART | S22: RUBBER SLEEVE | T22: TT45ASA | U22: 50950080933 | W22: 120000 | X22: SEA | Y22: CIP | Z22: CIP | AA22: MANZANILLO | AB22: HONG KONG | AC22: MANZANILLO | AD22: 46083 | AE22: 46139 | AF22: 46090 | AG22: NOR-MXI | AH22: 6123039 | AI22: 46083 | AJ22: 46083 | AK22: 120000 | AL22: 34798 | AM22: 101513753666 | AN22: 46083 | AO22: 46083.638 | AP22: USD | AQ22: 0.04459 | AR22: 5350.8 | AS22: USD | AT22: 5350.8 | AU22: JOHN JH SHI | AV22: OOCL-SEA-GEN | AW22: XIN OU ZHOU V.077E | AX22: 46093 | AY22: 46142 | AZ22: FBIU5071920 | BA22: 40' | BB22: OOLU2038497840 | BE22: 0 | BF22: 0 | BM22: 0 | BN22: 0 | BO22: 50 | CG22: JE IM OU | CJ22: FFAU3131007 | CN22: M45 | CO22: AYSP61BS362EN | CP22: CAAU7526547 | CQ22: 764.0962 | CR22: =IFERROR(CQ22/(SUMIFS(CQ:CQ,CP:CP,CP22)),100%) -> 0.067496229 | CS22: =CR22*$CS$2 -> 168.74057
B23: M45 | C23: 1625002019 | F23: 34798 | G23: JOHNSON ELECTRIC NORTH AMERICA INC. | H23: Tax ID JEG120120DD4 BOULEVARD MORELOS NO. 1109 MEGA PARQUE INDUSTRIAL AEROPUERTO DE CALERA C.P. 98519 CALERA ZACATECAS MX | I23: XEXX010101000 | J23: JEN | K23: IPG0099 | L23: S2-INTERNAL-SWO-IM-MX | M23: FLOW | N23: 1 | O23: 1 | P23: 1205-V0C0003EN | Q23: A | R23: DIRECT.CONNECTOR / TERMINAL.TERMINAL | S23: AMPLIVAR_TERMINAL | T23: TT45ASA | U23: 50950075206 | W23: 60000 | X23: SEA | Y23: CIP | Z23: CIP | AA23: MANZANILLO | AB23: HONG KONG | AC23: MANZANILLO | AD23: 46083 | AE23: 46146 | AF23: 46090 | AG23: NOR-MXI | AH23: 6123042 | AI23: 46083 | AJ23: 46083 | AK23: 60000 | AL23: 34798 | AM23: 101513753668 | AN23: 46083 | AO23: 46083.638 | AP23: USD | AQ23: 0.01259 | AR23: 755.4 | AS23: USD | AT23: 755.4 | AU23: JOHN JH SHI | AV23: OOCL-SEA-GEN | AW23: XIN OU ZHOU V.077E | AX23: 46093 | AY23: 46142 | AZ23: FBIU5071920 | BA23: 40' | BB23: OOLU2038497840 | BE23: 0 | BF23: 0 | BM23: 0 | BN23: 0 | BO23: 0.1 | CG23: JE IM OU | CJ23: FFAU5676599 | CN23: M01 | CO23: 1102-0039190EN | CP23: CAAU7526547 | CQ23: 1197.24 | CR23: =IFERROR(CQ23/(SUMIFS(CQ:CQ,CP:CP,CP23)),100%) -> 0.10575787 | CS23: =CR23*$CS$2 -> 264.39467
B24: M45 | C24: 1625002096 | F24: 34798 | G24: JOHNSON ELECTRIC NORTH AMERICA INC. | H24: Tax ID JEG120120DD4 BOULEVARD MORELOS NO. 1109 MEGA PARQUE INDUSTRIAL AEROPUERTO DE CALERA C.P. 98519 CALERA ZACATECAS MX | I24: XEXX010101000 | J24: JEN | K24: IPG0099 | L24: S2-INTERNAL-SWO-IM-MX | M24: FLOW | N24: 1 | O24: 1 | P24: 1623-10C0022-MCEN | Q24: A | R24: DIRECT.CATALOG PASSIVE ELECTRONIC.FUSE | S24: FUSE | T24: TT45ASA | U24: 50950081473 | W24: 40000 | X24: AIR | Y24: CIP | Z24: CIP | AA24: MANZANILLO | AB24: HONG KONG | AC24: MANZANILLO | AD24: 46083 | AE24: 46139 | AF24: 46090 | AG24: NOR-MXI | AH24: 6122652 | AI24: 46083 | AJ24: 46083 | AK24: 40000 | AL24: 34798 | AM24: 101513753572 | AN24: 46083 | AO24: 46083.44 | AP24: USD | AQ24: 0.04788 | AR24: 1915.2 | AS24: USD | AT24: 1915.2 | AU24: DICK ZJ WU | AV24: AIR | AW24: K4255 | AX24: 46084 | AY24: 46095 | BA24: AIR | BB24: 5439187460 | BE24: 0 | BF24: 0 | BM24: 0 | BN24: 0 | BO24: 50 | CG24: JE IM OU | CJ24: FFAU5865735 | CN24: M01 | CO24: 1999-1010399E1 | CP24: CAIU8394197 | CQ24: 417.88 | CR24: =IFERROR(CQ24/(SUMIFS(CQ:CQ,CP:CP,CP24)),100%) -> 0.028035526 | CS24: =CR24*$CS$2 -> 70.088816
B25: M45 | C25: 1625002098 | F25: 34798 | G25: JOHNSON ELECTRIC NORTH AMERICA INC. | H25: Tax ID JEG120120DD4 BOULEVARD MORELOS NO. 1109 MEGA PARQUE INDUSTRIAL AEROPUERTO DE CALERA C.P. 98519 CALERA ZACATECAS MX | I25: XEXX010101000 | J25: JEN | K25: IPG0099 | L25: S2-INTERNAL-SWO-IM-MX | M25: FLOW | N25: 1 | O25: 1 | P25: 0059-V040320EN | Q25: A | R25: DIRECT.RAW MAGNET WIRE.AL WIRE FINE SIZE (OD <050mm) | S25: 1-EAIW_AL_MAGNET_WIRE_0.32MM | T25: TT45ASA | U25: 50950081532 | W25: 1575.97 | X25: SEA | Y25: CIP | Z25: CIP | AA25: MANZANILLO | AB25: HONG KONG | AC25: MANZANILLO | AD25: 46083 | AE25: 46139 | AF25: 46090 | AG25: NOR-MXI | AH25: 6123043 | AI25: 46083 | AJ25: 46083 | AK25: 1575.97 | AL25: 34798 | AM25: 101513753669 | AN25: 46083 | AO25: 46083.638 | AP25: USD | AQ25: 6.56052 | AR25: 10339.18 | AS25: USD | AT25: 10339.18 | AU25: JOHN JH SHI | AV25: OOCL-SEA-GEN | AW25: XIN OU ZHOU V.077E | AX25: 46093 | AY25: 46142 | AZ25: FBIU5071920 | BA25: 40' | BB25: OOLU2038497840 | BO25: =AR25/AQ25 -> 1575.9696 | CG25: JE IM OU | CJ25: GAOU7040650 | CN25: M19 | CO25: 1275-5YY0783EN | CP25: CAIU8394197 | CQ25: 991.564 | CR25: =IFERROR(CQ25/(SUMIFS(CQ:CQ,CP:CP,CP25)),100%) -> 0.066523927 | CS25: =CR25*$CS$2 -> 166.30982
B26: M45 | C26: 1625002098 | F26: 34798 | G26: JOHNSON ELECTRIC NORTH AMERICA INC. | H26: Tax ID JEG120120DD4 BOULEVARD MORELOS NO. 1109 MEGA PARQUE INDUSTRIAL AEROPUERTO DE CALERA C.P. 98519 CALERA ZACATECAS MX | I26: XEXX010101000 | J26: JEN | K26: IPG0099 | L26: S2-INTERNAL-SWO-IM-MX | M26: FLOW | N26: 2 | O26: 1 | P26: 0059-V040320EN | Q26: A | R26: DIRECT.RAW MAGNET WIRE.AL WIRE FINE SIZE (OD <050mm) | S26: 1-EAIW_AL_MAGNET_WIRE_0.32MM | T26: TT45ASA | U26: 50950081532 | W26: 1641.13 | X26: SEA | Y26: CIP | Z26: CIP | AA26: MANZANILLO | AB26: HONG KONG | AC26: MANZANILLO | AD26: 46083 | AE26: 46160 | AF26: 46090 | AG26: NOR-MXI | AH26: 6123043 | AI26: 46083 | AJ26: 46083 | AK26: 1641.13 | AL26: 34798 | AM26: 101513753669 | AN26: 46083 | AO26: 46083.638 | AP26: USD | AQ26: 6.56052 | AR26: 10766.67 | AS26: USD | AT26: 10766.67 | AU26: JOHN JH SHI | AV26: OOCL-SEA-GEN | AW26: XIN OU ZHOU V.077E | AX26: 46093 | AY26: 46142 | AZ26: FBIU5071920 | BA26: 40' | BB26: OOLU2038497840 | BO26: =AR26/AQ26 -> 1641.1306 | CG26: JE IM OU | CJ26: JXLU4392928 | CN26: M19 | CO26: 1275-5YY0685EN | CP26: CAIU8394197 | CQ26: 104.008 | CR26: =IFERROR(CQ26/(SUMIFS(CQ:CQ,CP:CP,CP26)),100%) -> 0.0069778861 | CS26: =CR26*$CS$2 -> 17.444715
B27: M45 | C27: 1275391670 | F27: 34798 | G27: JOHNSON ELECTRIC NORTH AMERICA INC. | H27: Tax ID JEG120120DD4 BOULEVARD MORELOS NO. 1109 MEGA PARQUE INDUSTRIAL AEROPUERTO DE CALERA C.P. 98519 CALERA ZACATECAS MX | I27: XEXX010101000 | J27: JEN | K27: W03 | L27: C&S-INTERNAL-SWO-IM-MX | M27: FLOW | N27: 1 | O27: 1 | P27: 1202-12B0005EN | Q27: B | R27: RGB.YY.BUSHING | S27: BUSHING | T27: TT45ASA | U27: 50950078779 | W27: 76800 | X27: SEA | Y27: CIP | Z27: CIP | AA27: MANZANILLO | AB27: HONG KONG | AC27: MANZANILLO | AD27: 46083 | AE27: 46139 | AF27: 46090 | AG27: FGD-P2RGB | AH27: 6122727 | AI27: 46083 | AJ27: 46084 | AK27: 76800 | AL27: 34798 | AM27: 101513754343 | AN27: 46084 | AO27: 46084.403 | AP27: USD | AQ27: 0.08846 | AR27: 6793.73 | AS27: USD | AT27: 6793.73 | AU27: JOHN JH SHI | AV27: OOCL-SEA-GEN | AW27: XIN OU ZHOU V.077E | AX27: 46093 | AY27: 46142 | AZ27: FBIU5071920 | BA27: 40' | BB27: OOLU2038497840 | BC27: 3200 | BD27: KG | BE27: 5.4578 | BH27: 395 | BI27: 295 | BJ27: 120 | BK27: 8 | BL27: KG | BM27: 51.6624 | BN27: 37.8624 | BO27: 154.9872 | BP27: MM | BQ27: 800 | BR27: 300 | BS27: 608 | BT27: 3 | BU27: 0 | BV27: 3 | BW27: 24 | BX27: 0 | BY27: 24 | BZ27: 76800 | CA27: 0 | CB27: 76800 | CC27: 113.5872 | CD27: C-PAL-507001 | CE27: C-BOX-474009 | CG27: JE IM OU | CJ27: JXLU6016257 | CN27: M45 | CO27: 1346-12C0011EN | CP27: CAIU8394197 | CQ27: 157.5094 | CR27: =IFERROR(CQ27/(SUMIFS(CQ:CQ,CP:CP,CP27)),100%) -> 0.01056729 | CS27: =CR27*$CS$2 -> 26.418224
B28: M19 | C28: 1275402056 | F28: 34798 | G28: JOHNSON ELECTRIC NORTH AMERICA INC. | H28: Tax ID JEG120120DD4 BOULEVARD MORELOS NO. 1109 MEGA PARQUE INDUSTRIAL AEROPUERTO DE CALERA C.P. 98519 CALERA ZACATECAS MX | I28: XEXX010101000 | J28: JEN | K28: Y05 | L28: C&S-INTERNAL-SWO-IM-MX | M28: FLOW | N28: 1 | O28: 1 | P28: 1307-5YY0150EN | Q28: A | R28: NEW.NEW.NEW | S28: Magnet 8300338 GRADE: 5H | T28: TT45ASA | U28: 50950080272 | W28: 40320 | X28: SEA | Y28: CIP | Z28: CIP | AA28: MANZANILLO | AB28: HONG KONG | AC28: MANZANILLO | AD28: 46077 | AE28: 46146 | AF28: 46097 | AG28: NOR-MXC | AH28: 6125143 | AI28: 46084 | AJ28: 46084 | AK28: 40320 | AL28: 34798 | AM28: 101513754572 | AN28: 46084 | AO28: 46084.722 | AP28: USD | AQ28: 0.08923 | AR28: 3597.75 | AS28: USD | AT28: 3597.75 | AU28: JOHN JH SHI | AV28: OOCL-SEA-GEN | AW28: XIN OU ZHOU V.077E | AX28: 46093 | AY28: 46142 | AZ28: FBIU5071920 | BA28: 40' | BB28: OOLU2038497840 | BO28: 1500 | CG28: JE IM OU | CJ28: MEDU4556686 | CN28: M45 | CO28: 1346-12C0011EN | CP28: CAIU8394197 | CQ28: 157.5094 | CR28: =IFERROR(CQ28/(SUMIFS(CQ:CQ,CP:CP,CP28)),100%) -> 0.01056729 | CS28: =CR28*$CS$2 -> 26.418224
B29: M23 | C29: 1195009982 | F29: 34798 | G29: JOHNSON ELECTRIC NORTH AMERICA INC. | H29: BOULEVARD MORELOS NO. 1109 MEGA PARQUE INDUSTRIAL AEROPUERTO DE CALERA C.P. 98519 CALERA ZACATECAS Tax ID JEG120120DD4 MX | I29: XEXX010101000 | J29: JEN | K29: Q07 | L29: PC-INTERNAL-SWO-HSG-MX | M29: FLOW | N29: 1 | O29: 1 | P29: 0081-5000001EN | Q29: C | R29: DC.CFM.CFM | S29: SILICONE GAP FILLER | T29: TT45ASA | U29: 50950079964 | W29: 2880 | X29: SEA | Y29: CIP | Z29: CIP | AA29: MANZANILLO | AB29: HONG KONG | AC29: MANZANILLO | AD29: 46076 | AE29: 46132 | AF29: 46093 | AG29: FGD-PC | AH29: 6124987 | AI29: 46084 | AJ29: 46085 | AK29: 2880 | AL29: 34798 | AM29: 101513754711 | AN29: 46085 | AO29: 46085.421 | AP29: USD | AQ29: 10.16214 | AR29: 29266.92 | AS29: USD | AT29: 29266.92 | AU29: JOHN JH SHI | AV29: OOCL-SEA-GEN | AW29: XIN OU ZHOU V.077E | AX29: 46093 | AY29: 46142 | AZ29: FBIU5071920 | BA29: 40' | BB29: OOLU2038497840 | BC29: 40 | BD29: KG | BE29: 42.086 | BF29: 40 | BG29: MM | BH29: 340 | BI29: 340 | BJ29: 384 | BK29: 6 | BL29: KG | BM29: 277.516 | BN29: 240 | BO29: 3330.192 | BP29: MM | BQ29: 1070 | BR29: 750 | BS29: 545 | BT29: 12 | BU29: 0 | BV29: 12 | BW29: 72 | BX29: 0 | BY29: 72 | BZ29: 2880 | CA29: 0 | CB29: 2880 | CC29: 2880 | CD29: C-PAL-233059 | CE29: C-BOX-233201 | CG29: JE IM OU | CJ29: MEDU4622772 | CN29: M19 | CO29: 1330-5YY0182EN | CP29: CAIU8394197 | CQ29: 1405.0848 | CR29: =IFERROR(CQ29/(SUMIFS(CQ:CQ,CP:CP,CP29)),100%) -> 0.094266995 | CS29: =CR29*$CS$2 -> 235.66749
B30: M23 | C30: 1195010053 | F30: 34798 | G30: JOHNSON ELECTRIC NORTH AMERICA INC. | H30: BOULEVARD MORELOS NO. 1109 MEGA PARQUE INDUSTRIAL AEROPUERTO DE CALERA C.P. 98519 CALERA ZACATECAS Tax ID JEG120120DD4 MX | I30: XEXX010101000 | J30: JEN | K30: Q07 | L30: PC-INTERNAL-SWO-HSG-MX | M30: FLOW | N30: 1 | O30: 1 | P30: 0081-5000001EN | Q30: C | R30: DC.CFM.CFM | S30: SILICONE GAP FILLER | T30: TT45ASA | U30: 50950080686 | W30: 2880 | X30: SEA | Y30: CIP | Z30: CIP | AA30: MANZANILLO | AB30: HONG KONG | AC30: MANZANILLO | AD30: 46090 | AE30: 46146 | AF30: 46093 | AG30: FGD-PC | AH30: 6124988 | AI30: 46084 | AJ30: 46085 | AK30: 2880 | AL30: 34798 | AM30: 101513754712 | AN30: 46085 | AO30: 46085.421 | AP30: USD | AQ30: 10.16214 | AR30: 29266.92 | AS30: USD | AT30: 29266.92 | AU30: JOHN JH SHI | AV30: OOCL-SEA-GEN | AW30: XIN OU ZHOU V.077E | AX30: 46093 | AY30: 46142 | AZ30: FBIU5071920 | BA30: 40' | BB30: OOLU2038497840 | BC30: 40 | BD30: KG | BE30: 42.086 | BF30: 40 | BG30: MM | BH30: 340 | BI30: 340 | BJ30: 384 | BK30: 6 | BL30: KG | BM30: 277.516 | BN30: 240 | BO30: 3330.192 | BP30: MM | BQ30: 1070 | BR30: 750 | BS30: 545 | BT30: 12 | BU30: 0 | BV30: 12 | BW30: 72 | BX30: 0 | BY30: 72 | BZ30: 2880 | CA30: 0 | CB30: 2880 | CC30: 2880 | CD30: C-PAL-233059 | CE30: C-BOX-233201 | CG30: JE IM OU | CJ30: MEDU5320611 | CN30: M19 | CO30: 1330-5YY0183EN | CP30: CAIU8394197 | CQ30: 1546.1856 | CR30: =IFERROR(CQ30/(SUMIFS(CQ:CQ,CP:CP,CP30)),100%) -> 0.10373343 | CS30: =CR30*$CS$2 -> 259.33358
B31: MCS | C31: 1275409411 | F31: 34798 | G31: JOHNSON ELECTRIC NORTH AMERICA INC. | H31: Tax ID JEG120120DD4. BOULEVARD MORELOS NO. 1109 MEGA PARQUE INDUSTRIAL AEROPUERTO DE CALERA C.P. 98519 CALERA ZACATECAS MX | I31: XEXX010101000 | J31: JEN | K31: Y99 | L31: C&S-INTERNAL-SWO-IM-MX | M31: FLOW | N31: 1 | O31: 1 | P31: 0070-G130008EN | Q31: A | R31: NEW.NEW.NEW | S31: PPS + 40% GF | T31: TT45ASA | U31: 50950081224 | W31: 1000 | X31: SEA | Y31: CIP | Z31: CIP | AA31: MANZANILLO | AB31: HONG KONG | AC31: MANZANILLO | AD31: 46083 | AE31: 46153 | AF31: 46090 | AG31: NOR-MXC | AH31: 6125991 | AI31: 46085 | AJ31: 46085 | AK31: 1000 | AL31: 34798 | AM31: 101513754706 | AN31: 46085 | AO31: 46085.387 | AP31: USD | AQ31: 6.2475 | AR31: 6247.5 | AS31: USD | AT31: 6247.5 | AU31: JOHN JH SHI | AV31: OOCL-SEA-GEN | AW31: XIN OU ZHOU V.077E | AX31: 46093 | AY31: 46142 | AZ31: FBIU5071920 | BA31: 40' | BB31: OOLU2038497840 | BO31: =AR31/AQ31 -> 1000 | CG31: JE IM OU | CJ31: MEDU7325850 | CN31: M19 | CO31: 1330-5YY0176EN | CP31: CAIU8394197 | CQ31: 273.7536 | CR31: =IFERROR(CQ31/(SUMIFS(CQ:CQ,CP:CP,CP31)),100%) -> 0.018366101 | CS31: =CR31*$CS$2 -> 45.915253
B32: M01 | C32: 1015082405 | D32: QIONG PENG | F32: 34798 | G32: JOHNSON ELECTRIC NORTH AMERICA INC. | H32: Tax ID JEG120120DD4 BOULEVARD MORELOS NO. 1109 MEGA PARQUE INDUSTRIAL AEROPUERTO DE CALERA C.P. 98519 CALERA ZACATECAS MX | I32: XEXX010101000 | J32: JEN | K32: A99 | L32: BI-INTERNAL-SWO-HSG-MX | M32: FLOW | N32: 3 | O32: 1 | P32: 1200-1030955EN | Q32: B | R32: EC.N.NONE | S32: END CAP ASS'Y | T32: TT45ASA | U32: 50950080811 | W32: 34560 | X32: SEA | Y32: CIP | Z32: CIP | AA32: MANZANILLO | AB32: YANTIAN | AC32: MANZANILLO | AD32: 46083 | AE32: 46139 | AF32: 46090 | AG32: FGD-BI | AH32: 6130069 | AI32: 46087 | AJ32: 46088 | AK32: 34560 | AL32: 34798 | AM32: 101513756354 | AN32: 46088 | AO32: 46088.585 | AP32: USD | AQ32: 0.23995 | AR32: 8292.67 | AS32: USD | AT32: 8292.67 | AU32: JOHN JH SHI | AV32: MSC-SEA-GEN | AW32: MANZANILLO EXPRESS V.2611E | AX32: 46092 | AY32: 46141 | AZ32: MSNU9003952 | BA32: 40HQ | BB32: MEDUWH352603 | BC32: 240 | BD32: KG | BE32: 2.861 | BF32: 1.584 | BG32: MM | BH32: 340 | BI32: 250 | BJ32: 230 | BK32: 48 | BL32: KG | BM32: 158.328 | BN32: 76.032 | BO32: 474.984 | BP32: MM | BQ32: 1066 | BR32: 1066 | BS32: 1080 | BT32: 3 | BU32: 0 | BV32: 3 | BW32: 144 | BX32: 0 | BY32: 144 | BZ32: 34560 | CA32: 0 | CB32: 34560 | CC32: 228.096 | CD32: C-PAL-233041 | CE32: C-BOX-233127 | CG32: JE IM OU | CJ32: MSCU5287590 | CN32: M19 | CO32: 1330-5YY0112EN | CP32: CAIU8394197 | CQ32: 888.63408 | CR32: =IFERROR(CQ32/(SUMIFS(CQ:CQ,CP:CP,CP32)),100%) -> 0.059618369 | CS32: =CR32*$CS$2 -> 149.04592
B33: M46 | C33: 1235035118 | D33: ELLA CY XIAO | F33: 34798 | G33: JOHNSON ELECTRIC NORTH AMERICA INC. | H33: Tax ID JEG120120DD4 BOULEVARD MORELOS NO. 1109 MEGA PARQUE INDUSTRIAL AEROPUERTO DE CALERA C.P. 98519 CALERA ZACATECAS MX | I33: XEXX010101000 | J33: JEN | K33: B99 | L33: PM-INTERNAL-SWO-HSG-MX | M33: FLOW | N33: 1 | O33: 1 | P33: 1200-1061164EN | Q33: C | R33: EC.N.NONE | S33: END CAP ASSY | T33: TT45ASA | U33: 50950081293 | W33: 9600 | X33: SEA | Y33: CIP | Z33: CIP | AA33: MANZANILLO | AB33: YANTIAN | AC33: MANZANILLO | AD33: 46083 | AE33: 46139 | AF33: 46090 | AG33: FGD-PM | AH33: 6130070 | AI33: 46087 | AJ33: 46088 | AK33: 9600 | AL33: 34798 | AM33: 101513756355 | AN33: 46088 | AO33: 46088.585 | AP33: USD | AQ33: 0.70009 | AR33: 6720.87 | AS33: USD | AT33: 6720.87 | AU33: JOHN JH SHI | AV33: MSC-SEA-GEN | AW33: MANZANILLO EXPRESS V.2611E | AX33: 46092 | AY33: 46141 | AZ33: MSNU9003952 | BA33: 40HQ | BB33: MEDUWH352603 | BC33: 240 | BD33: KG | BE33: 5.9942 | BF33: 4.3632 | BG33: MM | BH33: 395 | BI33: 295 | BJ33: 170 | BK33: 40 | BL33: KG | BM33: 264.768 | BN33: 174.528 | BO33: 264.768 | BP33: MM | BQ33: 1200 | BR33: 800 | BS33: 1010 | BT33: 1 | BU33: 0 | BV33: 1 | BW33: 40 | BX33: 0 | BY33: 40 | BZ33: 9600 | CA33: 0 | CB33: 9600 | CC33: 174.528 | CD33: C-PAL-171001 | CE33: C-BOX-233113 | CG33: JE IM OU | CJ33: MSDU6089696 | CN33: M19 | CO33: 1330-5YY0177EN | CP33: CAIU8394197 | CQ33: 1014.594 | CR33: =IFERROR(CQ33/(SUMIFS(CQ:CQ,CP:CP,CP33)),100%) -> 0.068069008 | CS33: =CR33*$CS$2 -> 170.17252
B34: M23 | C34: 1235035461 | D34: HONGLI CAO | F34: 34798 | G34: JOHNSON ELECTRIC NORTH AMERICA INC. | H34: Tax ID JEG120120DD4 BOULEVARD MORELOS NO. 1109 MEGA PARQUE INDUSTRIAL AEROPUERTO DE CALERA C.P. 98519 CALERA ZACATECAS MX | I34: XEXX010101000 | J34: JEN | K34: B99 | L34: PM-INTERNAL-SWO-HSG-MX | M34: FLOW | N34: 1 | O34: 2 | P34: 1293-1060012EN | Q34: A | R34: NONE.N.NONE | S34: TERMINAL HOLDER ASSY | T34: TT45ASA | U34: 50950081546 | W34: 12800 | X34: SEA | Y34: CIP | Z34: CIP | AA34: MANZANILLO | AB34: YANTIAN | AC34: MANZANILLO | AD34: 46103 | AE34: 46139 | AF34: 46090 | AG34: FGD-PM | AH34: 6130071 | AI34: 46087 | AJ34: 46088 | AK34: 12800 | AL34: 34798 | AM34: 101513756352 | AN34: 46088 | AO34: 46088.585 | AP34: USD | AQ34: 0.56743 | AR34: 7263.11 | AS34: USD | AT34: 7263.11 | AU34: JOHN JH SHI | AV34: MSC-SEA-GEN | AW34: MANZANILLO EXPRESS V.2611E | AX34: 46092 | AY34: 46141 | AZ34: MSNU9003952 | BA34: 40HQ | BB34: MEDUWH352603 | BC34: 200 | BD34: KG | BE34: 3.9521 | BF34: 2.7251 | BG34: MM | BH34: 395 | BI34: 295 | BJ34: 200 | BK34: 32 | BL34: KG | BM34: 151.4672 | BN34: 87.2032 | BO34: 302.9344 | BP34: MM | BQ34: 1200 | BR34: 800 | BS34: 960 | BT34: 2 | BU34: 0 | BV34: 2 | BW34: 64 | BX34: 0 | BY34: 64 | BZ34: 12800 | CA34: 0 | CB34: 12800 | CC34: 174.4064 | CD34: C-PAL-136001 | CE34: C-BOX-594150 | CG34: JE IM OU | CJ34: MSMU2474387 | CN34: M19 | CO34: 1330-5YY0251EN | CP34: CAIU8394197 | CQ34: 217.67016 | CR34: =IFERROR(CQ34/(SUMIFS(CQ:CQ,CP:CP,CP34)),100%) -> 0.014603469 | CS34: =CR34*$CS$2 -> 36.508672
B35: M23 | C35: 1235035462 | D35: HONGLI CAO | F35: 34798 | G35: JOHNSON ELECTRIC NORTH AMERICA INC. | H35: Tax ID JEG120120DD4 BOULEVARD MORELOS NO. 1109 MEGA PARQUE INDUSTRIAL AEROPUERTO DE CALERA C.P. 98519 CALERA ZACATECAS MX | I35: XEXX010101000 | J35: JEN | K35: B99 | L35: PM-INTERNAL-SWO-HSG-MX | M35: FLOW | N35: 1 | O35: 1 | P35: 1293-1060012EN | Q35: A | R35: NONE.N.NONE | S35: TERMINAL HOLDER ASSY | T35: TT45ASA | U35: 50950081549 | W35: 19200 | X35: SEA | Y35: CIP | Z35: CIP | AA35: MANZANILLO | AB35: YANTIAN | AC35: MANZANILLO | AD35: 46098 | AE35: 46125 | AF35: 46090 | AG35: FGD-PM | AH35: 6130072 | AI35: 46087 | AJ35: 46088 | AK35: 19200 | AL35: 34798 | AM35: 101513756353 | AN35: 46088 | AO35: 46088.585 | AP35: USD | AQ35: 0.56743 | AR35: 10894.66 | AS35: USD | AT35: 10894.66 | AU35: JOHN JH SHI | AV35: MSC-SEA-GEN | AW35: MANZANILLO EXPRESS V.2611E | AX35: 46092 | AY35: 46141 | AZ35: MSNU9003952 | BA35: 40HQ | BB35: MEDUWH352603 | BC35: 200 | BD35: KG | BE35: 3.9521 | BF35: 2.7251 | BG35: MM | BH35: 395 | BI35: 295 | BJ35: 200 | BK35: 32 | BL35: KG | BM35: 151.4672 | BN35: 87.2032 | BO35: 454.4016 | BP35: MM | BQ35: 1200 | BR35: 800 | BS35: 960 | BT35: 3 | BU35: 0 | BV35: 3 | BW35: 96 | BX35: 0 | BY35: 96 | BZ35: 19200 | CA35: 0 | CB35: 19200 | CC35: 261.6096 | CD35: C-PAL-136001 | CE35: C-BOX-594150 | CG35: JE IM OU | CJ35: MSMU5349558 | CN35: M45 | CO35: 1339-12C0007EN | CP35: CAIU8394197 | CQ35: 2548.9796 | CR35: =IFERROR(CQ35/(SUMIFS(CQ:CQ,CP:CP,CP35)),100%) -> 0.17101078 | CS35: =CR35*$CS$2 -> 427.52695
B36: M19 | C36: 1275395940 | F36: 34798 | G36: JOHNSON ELECTRIC NORTH AMERICA INC. | H36: BOULEVARD MORELOS NO. 1109 MEGA PARQUE INDUSTRIAL AEROPUERTO DE CALERA C.P. 98519 CALERA ZACATECAS Tax ID JEG120120DD4 MX | I36: XEXX010101000 | J36: JEN | K36: W03 | L36: C&S-INTERNAL-SWO-HSG-MX | M36: FLOW | N36: 1 | O36: 3 | P36: 1220-5YY0030EN | Q36: G | R36: CEM.YY.TERMINAL HOLDER | S36: TERMINAL HOLDER 8260573 | T36: TT45ASA | U36: 50950079191 | W36: 2700 | X36: SEA | Y36: CIP | Z36: CIP | AA36: MANZANILLO | AB36: YANTIAN | AC36: MANZANILLO | AD36: 46076 | AE36: 46132 | AF36: 46090 | AG36: FGD-CS | AH36: 6130073 | AI36: 46087 | AJ36: 46088 | AK36: 2700 | AL36: 34798 | AM36: 101513756367 | AN36: 46088 | AO36: 46088.585 | AP36: USD | AQ36: 1.95098 | AR36: 5267.64 | AS36: USD | AT36: 5267.64 | AU36: JOHN JH SHI | AV36: MSC-SEA-GEN | AW36: MANZANILLO EXPRESS V.2611E | AX36: 46092 | AY36: 46141 | AZ36: MSNU9003952 | BA36: 40HQ | BB36: MEDUWH352603 | BC36: 27 | BD36: KG | BE36: 2.656 | BF36: 1.623 | BG36: MM | BH36: 395 | BI36: 295 | BJ36: 190 | BK36: 50 | BL36: KG | BM36: 159.8 | BN36: 81.15 | BO36: 319.5997 | BP36: MM | BQ36: 1200 | BR36: 1000 | BS36: 1110 | BT36: 2 | BU36: 0 | BV36: 2 | BW36: 100 | BX36: 0 | BY36: 100 | BZ36: 2700 | CA36: 0 | CB36: 2700 | CC36: 162.2997 | CD36: C-PAL-294062 | CE36: C-BOX-001051 | CG36: JE IM OU | CJ36: MSMU6025580 | CN36: M45 | CO36: 1339-12C0008EN | CP36: CAIU8394197 | CQ36: 3192.2725 | CR36: =IFERROR(CQ36/(SUMIFS(CQ:CQ,CP:CP,CP36)),100%) -> 0.21416924 | CS36: =CR36*$CS$2 -> 535.42309
B37: M19 | C37: 1275401968 | F37: 34798 | G37: JOHNSON ELECTRIC NORTH AMERICA INC. | H37: BOULEVARD MORELOS NO. 1109 MEGA PARQUE INDUSTRIAL AEROPUERTO DE CALERA C.P. 98519 CALERA ZACATECAS Tax ID JEG120120DD4 MX | I37: XEXX010101000 | J37: JEN | K37: W01 | L37: C&S-INTERNAL-SWO-HSG-MX | M37: FLOW | N37: 1 | O37: 1 | P37: 1101-5YY0361EN | Q37: B | R37: BB.P0.SHAFT | S37: SHAFT 8000847 | T37: TT45ASA | U37: 50950080140 | W37: 23040 | X37: SEA | Y37: CIP | Z37: CIP | AA37: MANZANILLO | AB37: YANTIAN | AC37: MANZANILLO | AD37: 46083 | AE37: 46139 | AF37: 46090 | AG37: FGD-CS | AH37: 6130074 | AI37: 46087 | AJ37: 46088 | AK37: 23040 | AL37: 34798 | AM37: 101513756366 | AN37: 46088 | AO37: 46088.585 | AP37: USD | AQ37: 0.07477 | AR37: 1722.7 | AS37: USD | AT37: 1722.7 | AU37: JOHN JH SHI | AV37: MSC-SEA-GEN | AW37: MANZANILLO EXPRESS V.2611E | AX37: 46092 | AY37: 46141 | AZ37: MSNU9003952 | BA37: 40HQ | BB37: MEDUWH352603 | BC37: 320 | BD37: KG | BE37: 6.0304 | BF37: 5.7304 | BG37: MM | BH37: 295 | BI37: 195 | BJ37: 100 | BK37: 64 | BL37: KG | BM37: 415.9456 | BN37: 366.7456 | BO37: 494.1865 | BP37: MM | BQ37: 1200 | BR37: 800 | BS37: 573 | BT37: 1 | BU37: 1 | BV37: 2 | BW37: 72 | BX37: 0 | BY37: 72 | BZ37: 20480 | CA37: 2560 | CB37: 23040 | CC37: 412.5865 | CD37: C-PAL-360001 | CE37: 1504-1YY0040 | CG37: JE IM OU | CJ37: MSMU8888430 | CN37: M45 | CO37: AYSP61AS871EN | CP37: CAIU8394197 | CQ37: 946.4002 | CR37: =IFERROR(CQ37/(SUMIFS(CQ:CQ,CP:CP,CP37)),100%) -> 0.063493893 | CS37: =CR37*$CS$2 -> 158.73473
B38: M19 | C38: 1275402000 | F38: 34798 | G38: JOHNSON ELECTRIC NORTH AMERICA INC. | H38: BOULEVARD MORELOS NO. 1109 MEGA PARQUE INDUSTRIAL AEROPUERTO DE CALERA C.P. 98519 CALERA ZACATECAS Tax ID JEG120120DD4 MX | I38: XEXX010101000 | J38: JEN | K38: W01 | L38: C&S-INTERNAL-SWO-HSG-MX | M38: FLOW | N38: 1 | O38: 1 | P38: 1101-5YY0299EN | Q38: C | R38: BB.P0.SHAFT | S38: SHAFT 8000764 | T38: TT45ASA | U38: 50950080162 | W38: 5760 | X38: SEA | Y38: CIP | Z38: CIP | AA38: MANZANILLO | AB38: YANTIAN | AC38: MANZANILLO | AD38: 46090 | AE38: 46125 | AF38: 46090 | AG38: FGD-CS | AH38: 6130075 | AI38: 46087 | AJ38: 46088 | AK38: 5760 | AL38: 34798 | AM38: 101513756359 | AN38: 46088 | AO38: 46088.585 | AP38: USD | AQ38: 0.19124 | AR38: 1101.54 | AS38: USD | AT38: 1101.54 | AU38: JOHN JH SHI | AV38: MSC-SEA-GEN | AW38: MANZANILLO EXPRESS V.2611E | AX38: 46092 | AY38: 46141 | AZ38: MSNU9003952 | BA38: 40HQ | BB38: MEDUWH352603 | BC38: 320 | BD38: KG | BE38: 7.5755 | BF38: 7.2755 | BG38: MM | BH38: 295 | BI38: 195 | BJ38: 100 | BK38: 64 | BL38: KG | BM38: 166.35936 | BN38: 130.95936 | BO38: 166.35936 | BP38: MM | BQ38: 1200 | BR38: 800 | BS38: 573 | BT38: 0 | BU38: 1 | BV38: 1 | BW38: 18 | BX38: 0 | BY38: 18 | BZ38: 0 | CA38: 5760 | CB38: 5760 | CC38: 130.95936 | CD38: C-PAL-360001 | CE38: 1504-1YY0040 | CG38: JE IM OU | CJ38: MSNU7011814 | CN38: M45 | CO38: AYSP61BS362EN | CP38: CAIU8394197 | CQ38: 382.0481 | CR38: =IFERROR(CQ38/(SUMIFS(CQ:CQ,CP:CP,CP38)),100%) -> 0.025631568 | CS38: =CR38*$CS$2 -> 64.07892
B39: M19 | C39: 1275402030 | F39: 34798 | G39: JOHNSON ELECTRIC NORTH AMERICA INC. | H39: BOULEVARD MORELOS NO. 1109 MEGA PARQUE INDUSTRIAL AEROPUERTO DE CALERA C.P. 98519 CALERA ZACATECAS Tax ID JEG120120DD4 MX | I39: XEXX010101000 | J39: JEN | K39: Y01 | L39: C&S-INTERNAL-SWO-HSG-MX | M39: FLOW | N39: 1 | O39: 1 | P39: 1140-5YY0004EN | Q39: C | R39: PM.11.SLEEVE | S39: SLEEVE 8140186 | T39: TT45ASA | U39: 50950080200 | W39: 35200 | X39: SEA | Y39: CIP | Z39: CIP | AA39: MANZANILLO | AB39: YANTIAN | AC39: MANZANILLO | AD39: 46083 | AE39: 46132 | AF39: 46090 | AG39: FGD-CS | AH39: 6130076 | AI39: 46087 | AJ39: 46088 | AK39: 35200 | AL39: 34798 | AM39: 101513756358 | AN39: 46088 | AO39: 46088.585 | AP39: USD | AQ39: 0.11616 | AR39: 4088.83 | AS39: USD | AT39: 4088.83 | AU39: JOHN JH SHI | AV39: MSC-SEA-GEN | AW39: MANZANILLO EXPRESS V.2611E | AX39: 46092 | AY39: 46141 | AZ39: MSNU9003952 | BA39: 40HQ | BB39: MEDUWH352603 | BC39: 880 | BD39: KG | BE39: 13.594 | BF39: 11.994 | BG39: MM | BH39: 395 | BI39: 295 | BJ39: 230 | BK39: 40 | BL39: KG | BM39: 574.7584 | BN39: 479.7584 | BO39: 574.7584 | BP39: MM | BQ39: 1200 | BR39: 1000 | BS39: 1075 | BT39: 1 | BU39: 0 | BV39: 1 | BW39: 40 | BX39: 0 | BY39: 40 | BZ39: 35200 | CA39: 0 | CB39: 35200 | CC39: 479.7584 | CD39: C-PAL-512001 | CE39: C-BOX-001219 | CG39: JE IM OU | CJ39: MSNU9003952 | CN39: M46 | CO39: 1301-1060387EN | CP39: CAIU8394197 | CQ39: 661.28032 | CR39: =IFERROR(CQ39/(SUMIFS(CQ:CQ,CP:CP,CP39)),100%) -> 0.044365229 | CS39: =CR39*$CS$2 -> 110.91307
B40: M19 | C40: 1275402035 | F40: 34798 | G40: JOHNSON ELECTRIC NORTH AMERICA INC. | H40: BOULEVARD MORELOS NO. 1109 MEGA PARQUE INDUSTRIAL AEROPUERTO DE CALERA C.P. 98519 CALERA ZACATECAS Tax ID JEG120120DD4 MX | I40: XEXX010101000 | J40: JEN | K40: W03 | L40: C&S-INTERNAL-SWO-HSG-MX | M40: FLOW | N40: 1 | O40: 1 | P40: 1106-5YY0012-T2EN | Q40: G | R40: CE.YY.COLLECTOR LINK | S40: COLLECTOR LINK | T40: TT45ASA | U40: 50950080208 | W40: 15120 | X40: SEA | Y40: CIP | Z40: CIP | AA40: MANZANILLO | AB40: YANTIAN | AC40: MANZANILLO | AD40: 46083 | AE40: 46139 | AF40: 46090 | AG40: FGD-CS | AH40: 6130077 | AI40: 46087 | AJ40: 46088 | AK40: 15120 | AL40: 34798 | AM40: 101513756360 | AN40: 46088 | AO40: 46088.585 | AP40: USD | AQ40: 0.14565 | AR40: 2202.24 | AS40: USD | AT40: 2202.24 | AU40: JOHN JH SHI | AV40: MSC-SEA-GEN | AW40: MANZANILLO EXPRESS V.2611E | AX40: 46092 | AY40: 46141 | AZ40: MSNU9003952 | BA40: 40HQ | BB40: MEDUWH352603 | BC40: 420 | BD40: KG | BE40: 2.1333 | BF40: 1.4133 | BG40: MM | BH40: 395 | BI40: 295 | BJ40: 220 | BK40: 6 | BL40: KG | BM40: 20.7998 | BN40: 8.4798 | BO40: 124.7988 | BP40: MM | BQ40: 800 | BR40: 300 | BS40: 830 | BT40: 6 | BU40: 0 | BV40: 6 | BW40: 36 | BX40: 0 | BY40: 36 | BZ40: 15120 | CA40: 0 | CB40: 15120 | CC40: 50.8788 | CD40: C-PAL-146006 | CE40: C-BOX-001184 | CG40: JE IM OU | CJ40: OOCU6524515 | CN40: M01 | CO40: 1999-1031492EN | CP40: CCLU7673540 | CQ40: 518.2 | CR40: =IFERROR(CQ40/(SUMIFS(CQ:CQ,CP:CP,CP40)),100%) -> 0.041360496 | CS40: =CR40*$CS$2 -> 103.40124
B41: M19 | C41: 1275402083 | F41: 34798 | G41: JOHNSON ELECTRIC NORTH AMERICA INC. | H41: BOULEVARD MORELOS NO. 1109 MEGA PARQUE INDUSTRIAL AEROPUERTO DE CALERA C.P. 98519 CALERA ZACATECAS Tax ID JEG120120DD4 MX | I41: XEXX010101000 | J41: JEN | K41: Y01 | L41: C&S-INTERNAL-SWO-HSG-MX | M41: FLOW | N41: 1 | O41: 1 | P41: 1252-5YY0073EN | Q41: A | R41: SB.YY.CARBON BRUSH | S41: CARBON BRUSH 8330162 | T41: TT45ASA | U41: 50950080350 | W41: 24000 | X41: SEA | Y41: CIP | Z41: CIP | AA41: MANZANILLO | AB41: YANTIAN | AC41: MANZANILLO | AD41: 46083 | AE41: 46139 | AF41: 46090 | AG41: FGD-CS | AH41: 6130078 | AI41: 46087 | AJ41: 46088 | AK41: 24000 | AL41: 34798 | AM41: 101513756361 | AN41: 46088 | AO41: 46088.585 | AP41: USD | AQ41: 0.1051 | AR41: 2522.4 | AS41: USD | AT41: 2522.4 | AU41: JOHN JH SHI | AV41: MSC-SEA-GEN | AW41: MANZANILLO EXPRESS V.2611E | AX41: 46092 | AY41: 46141 | AZ41: MSNU9003952 | BA41: 40HQ | BB41: MEDUWH352603 | BC41: 2400 | BD41: KG | BE41: 8.7984 | BF41: 7.4774 | BG41: MM | BH41: 395 | BI41: 295 | BJ41: 210 | BK41: 6 | BL41: KG | BM41: 60.7904 | BN41: 44.8644 | BO41: 103.9844 | BP41: MM | BQ41: 800 | BR41: 300 | BS41: 790 | BT41: 1 | BU41: 1 | BV41: 2 | BW41: 10 | BX41: 0 | BY41: 10 | BZ41: 14400 | CA41: 9600 | CB41: 24000 | CC41: 74.7744 | CD41: C-PAL-294025 | CE41: C-BOX-594025 | CG41: JE IM OU | CJ41: OOCU6799960 | CN41: M01 | CO41: 1999-1031491EN | CP41: CCLU7673540 | CQ41: 518.2 | CR41: =IFERROR(CQ41/(SUMIFS(CQ:CQ,CP:CP,CP41)),100%) -> 0.041360496 | CS41: =CR41*$CS$2 -> 103.40124
B42: M01 | C42: 1275402789 | F42: 34798 | G42: JOHNSON ELECTRIC NORTH AMERICA INC. | H42: Tax ID JEG120120DD4 BOULEVARD MORELOS NO. 1109 MEGA PARQUE INDUSTRIAL AEROPUERTO DE CALERA C.P. 98519 CALERA ZACATECAS MX | I42: XEXX010101000 | J42: JEN | K42: Y04 | L42: C&S-INTERNAL-SWO-HSG-MX | M42: FLOW | N42: 1 | O42: 1 | P42: 1200-3030001EN | Q42: G | R42: CE.300.END CAP | S42: END CAP ASS'Y | T42: TT45ASA | U42: 50950080450 | W42: 12800 | X42: SEA | Y42: CIP | Z42: CIP | AA42: MANZANILLO | AB42: YANTIAN | AC42: MANZANILLO | AD42: 46081 | AE42: 46132 | AF42: 46090 | AG42: FGD-CS | AH42: 6130079 | AI42: 46087 | AJ42: 46088 | AK42: 12800 | AL42: 34798 | AM42: 101513756365 | AN42: 46088 | AO42: 46088.585 | AP42: USD | AQ42: 0.11813 | AR42: 1512.07 | AS42: USD | AT42: 1512.07 | AU42: JOHN JH SHI | AV42: MSC-SEA-GEN | AW42: MANZANILLO EXPRESS V.2611E | AX42: 46092 | AY42: 46141 | AZ42: MSNU9003952 | BA42: 40HQ | BB42: MEDUWH352603 | BC42: 320 | BD42: KG | BE42: 4.5108 | BF42: 3.6038 | BG42: MM | BH42: 395 | BI42: 295 | BJ42: 270 | BK42: 30 | BL42: KG | BM42: 162.324 | BN42: 108.114 | BO42: 234.4336 | BP42: MM | BQ42: 1200 | BR42: 1000 | BS42: 918 | BT42: 1 | BU42: 1 | BV42: 2 | BW42: 40 | BX42: 0 | BY42: 40 | BZ42: 9600 | CA42: 3200 | CB42: 12800 | CC42: 144.1536 | CD42: C-PAL-522001 | CE42: C-BOX-001212 | CG42: JE IM OU | CJ42: OOCU6912465 | CN42: M19 | CO42: 1275-5YY0561EN | CP42: CCLU7673540 | CQ42: 798.756 | CR42: =IFERROR(CQ42/(SUMIFS(CQ:CQ,CP:CP,CP42)),100%) -> 0.06375327 | CS42: =CR42*$CS$2 -> 159.38318
B43: M46 | C43: 1275402944 | F43: 34798 | G43: JOHNSON ELECTRIC NORTH AMERICA INC. | H43: Tax ID JEG120120DD4 BOULEVARD MORELOS NO. 1109 MEGA PARQUE INDUSTRIAL AEROPUERTO DE CALERA C.P. 98519 CALERA ZACATECAS MX | I43: XEXX010101000 | J43: JEN | K43: Y01 | L43: C&S-INTERNAL-SWO-HSG-MX | M43: FLOW | N43: 1 | O43: 1 | P43: 1415-EQN0004EN | Q43: D | R43: SB.YY.GEAR | S43: DRIVE GEAR | T43: TT45ASA | U43: 50950080641 | W43: 10032 | X43: SEA | Y43: CIP | Z43: CIP | AA43: MANZANILLO | AB43: YANTIAN | AC43: MANZANILLO | AD43: 46083 | AE43: 46139 | AF43: 46090 | AG43: FGD-CS | AH43: 6130080 | AI43: 46087 | AJ43: 46088 | AK43: 10032 | AL43: 34798 | AM43: 101513756382 | AN43: 46088 | AO43: 46088.585 | AP43: USD | AQ43: 0.40085 | AR43: 4021.32 | AS43: USD | AT43: 4021.32 | AU43: JOHN JH SHI | AV43: MSC-SEA-GEN | AW43: MANZANILLO EXPRESS V.2611E | AX43: 46092 | AY43: 46141 | AZ43: MSNU9003952 | BA43: 40HQ | BB43: MEDUWH352603 | BC43: 3344 | BD43: KG | BE43: 236.0321 | BF43: 216.0321 | BG43: MM | BH43: 1050 | BI43: 480 | BJ43: 460 | BK43: 1 | BL43: KG | BM43: 236.0322 | BN43: 216.0321 | BO43: 708.09659 | BP43: MM | BQ43: 1050 | BR43: 480 | BS43: 480 | BT43: 3 | BU43: 0 | BV43: 3 | BW43: 3 | BX43: 0 | BY43: 3 | BZ43: 10032 | CA43: 0 | CB43: 10032 | CC43: 648.09629 | CD43: C-PAL-WOODCASE | CE43: C-BOX-001444 | CG43: JE IM OU | CJ43: OOCU8204341 | CN43: M19 | CO43: 1275-5YY0573EN | CP43: CCLU7673540 | CQ43: 528.472 | CR43: =IFERROR(CQ43/(SUMIFS(CQ:CQ,CP:CP,CP43)),100%) -> 0.042180363 | CS43: =CR43*$CS$2 -> 105.45091
B44: M46 | C44: 1275402946 | F44: 34798 | G44: JOHNSON ELECTRIC NORTH AMERICA INC. | H44: Tax ID JEG120120DD4 BOULEVARD MORELOS NO. 1109 MEGA PARQUE INDUSTRIAL AEROPUERTO DE CALERA C.P. 98519 CALERA ZACATECAS MX | I44: XEXX010101000 | J44: JEN | K44: Y01 | L44: C&S-INTERNAL-SWO-HSG-MX | M44: FLOW | N44: 1 | O44: 1 | P44: 1415-EQN0007EN | Q44: E | R44: SB.YY.GEAR | S44: HELICAL GEAR | T44: TT45ASA | U44: 50950080642 | W44: 8820 | X44: SEA | Y44: CIP | Z44: CIP | AA44: MANZANILLO | AB44: YANTIAN | AC44: MANZANILLO | AD44: 46086 | AE44: 46139 | AF44: 46090 | AG44: FGD-CS | AH44: 6130081 | AI44: 46087 | AJ44: 46088 | AK44: 8820 | AL44: 34798 | AM44: 101513756383 | AN44: 46088 | AO44: 46088.585 | AP44: USD | AQ44: 0.69983 | AR44: 6172.5 | AS44: USD | AT44: 6172.5 | AU44: JOHN JH SHI | AV44: MSC-SEA-GEN | AW44: MANZANILLO EXPRESS V.2611E | AX44: 46092 | AY44: 46141 | AZ44: MSNU9003952 | BA44: 40HQ | BB44: MEDUWH352603 | BC44: 1764 | BD44: KG | BE44: 177.2049 | BF44: 157.2049 | BG44: MM | BH44: 1050 | BI44: 480 | BJ44: 460 | BK44: 1 | BL44: KG | BM44: 177.205 | BN44: 157.2049 | BO44: 886.02479 | BP44: MM | BQ44: 1050 | BR44: 480 | BS44: 480 | BT44: 5 | BU44: 0 | BV44: 5 | BW44: 5 | BX44: 0 | BY44: 5 | BZ44: 8820 | CA44: 0 | CB44: 8820 | CC44: 786.02429 | CD44: C-PAL-WOODCASE | CE44: C-BOX-001444 | CG44: JE IM OU | CJ44: OOCU9018737 | CN44: M45 | CO44: 1301-12C0022EN | CP44: CCLU7673540 | CQ44: 1231.232 | CR44: =IFERROR(CQ44/(SUMIFS(CQ:CQ,CP:CP,CP44)),100%) -> 0.098271645 | CS44: =CR44*$CS$2 -> 245.67911
B45: M46 | C45: 1275402947 | F45: 34798 | G45: JOHNSON ELECTRIC NORTH AMERICA INC. | H45: Tax ID JEG120120DD4 BOULEVARD MORELOS NO. 1109 MEGA PARQUE INDUSTRIAL AEROPUERTO DE CALERA C.P. 98519 CALERA ZACATECAS MX | I45: XEXX010101000 | J45: JEN | K45: Y01 | L45: C&S-INTERNAL-SWO-HSG-MX | M45: FLOW | N45: 1 | O45: 1 | P45: 1415-EQN0005EN | Q45: B | R45: PM.YY.GEAR | S45: PLANET GEAR | T45: TT45ASA | U45: 50950080644 | W45: 21600 | X45: SEA | Y45: CIP | Z45: CIP | AA45: MANZANILLO | AB45: YANTIAN | AC45: MANZANILLO | AD45: 46083 | AE45: 46139 | AF45: 46090 | AG45: FGD-CS | AH45: 6130082 | AI45: 46087 | AJ45: 46088 | AK45: 21600 | AL45: 34798 | AM45: 101513756384 | AN45: 46088 | AO45: 46088.585 | AP45: USD | AQ45: 0.19273 | AR45: 4162.96 | AS45: USD | AT45: 4162.96 | AU45: JOHN JH SHI | AV45: MSC-SEA-GEN | AW45: MANZANILLO EXPRESS V.2611E | AX45: 46092 | AY45: 46141 | AZ45: MSNU9003952 | BA45: 40HQ | BB45: MEDUWH352603 | BC45: 900 | BD45: KG | BE45: 16.9505 | BF45: 16.5605 | BG45: MM | BH45: 368 | BI45: 257 | BJ45: 136 | BK45: 6 | BL45: KG | BM45: 109.703 | BN45: 99.363 | BO45: 438.8108 | BP45: MM | BQ45: 800 | BR45: 300 | BS45: 608 | BT45: 4 | BU45: 0 | BV45: 4 | BW45: 24 | BX45: 0 | BY45: 24 | BZ45: 21600 | CA45: 0 | CB45: 21600 | CC45: 397.4508 | CD45: C-PAL-507001 | CE45: C-BOX-594165 | CG45: JE IM OU | CJ45: OOCU9364658 | CN45: M45 | CO45: 1346-12C0011EN | CP45: CCLU7673540 | CQ45: 315.0188 | CR45: =IFERROR(CQ45/(SUMIFS(CQ:CQ,CP:CP,CP45)),100%) -> 0.025143446 | CS45: =CR45*$CS$2 -> 62.858616
B46: M01 | C46: 1275406532 | F46: 34798 | G46: JOHNSON ELECTRIC NORTH AMERICA INC. | H46: Tax ID JEG120120DD4 BOULEVARD MORELOS NO. 1109 MEGA PARQUE INDUSTRIAL AEROPUERTO DE CALERA C.P. 98519 CALERA ZACATECAS MX | I46: XEXX010101000 | J46: JEN | K46: W03 | L46: C&S-INTERNAL-SWO-HSG-MX | M46: FLOW | N46: 5 | O46: 1 | P46: 1308-0033550EN | Q46: D | R46: CE.300.MAGNET SPRING | S46: MAGNET SPRING(33550-30800EP) | T46: TT45ASA | U46: 50950080786 | W46: 160000 | X46: SEA | Y46: CIP | Z46: CIP | AA46: MANZANILLO | AB46: YANTIAN | AC46: MANZANILLO | AD46: 46083 | AE46: 46139 | AF46: 46090 | AG46: FGD-CS | AH46: 6130083 | AI46: 46087 | AJ46: 46088 | AK46: 160000 | AL46: 34798 | AM46: 101513756369 | AN46: 46088 | AO46: 46088.585 | AP46: USD | AQ46: 0.00279 | AR46: 446.4 | AS46: USD | AT46: 446.4 | AU46: JOHN JH SHI | AV46: MSC-SEA-GEN | AW46: MANZANILLO EXPRESS V.2611E | AX46: 46092 | AY46: 46141 | AZ46: MSNU9003952 | BA46: 40HQ | BB46: MEDUWH352603 | BC46: 8000 | BD46: KG | BE46: 5.8522 | BF46: 5.1232 | BG46: MM | BH46: 395 | BI46: 295 | BJ46: 120 | BK46: 8 | BL46: KG | BM46: 54.8176 | BN46: 40.9856 | BO46: 141.044 | BP46: MM | BQ46: 800 | BR46: 300 | BS46: 698 | BT46: 2 | BU46: 1 | BV46: 3 | BW46: 20 | BX46: 0 | BY46: 20 | BZ46: 128000 | CA46: 32000 | CB46: 160000 | CC46: 102.464 | CD46: C-PAL-398001 | CE46: 1504-1MB0011 | CG46: JE IM OU | CJ46: OOLU8995146 | CN46: M19 | CO46: 1330-5YY0182EN | CP46: CCLU7673540 | CQ46: 351.2712 | CR46: =IFERROR(CQ46/(SUMIFS(CQ:CQ,CP:CP,CP46)),100%) -> 0.028036957 | CS46: =CR46*$CS$2 -> 70.092393
B47: M01 | C47: 1275406537 | F47: 34798 | G47: JOHNSON ELECTRIC NORTH AMERICA INC. | H47: Tax ID JEG120120DD4 BOULEVARD MORELOS NO. 1109 MEGA PARQUE INDUSTRIAL AEROPUERTO DE CALERA C.P. 98519 CALERA ZACATECAS MX | I47: XEXX010101000 | J47: JEN | K47: Y01 | L47: C&S-INTERNAL-SWO-HSG-MX | M47: FLOW | N47: 5 | O47: 1 | P47: 1202-1030350EN | Q47: A | R47: PM.300.BUSHING | S47: BUSHING(1202-1030020-76EN) | T47: TT45ASA | U47: 50950080791 | W47: 192000 | X47: SEA | Y47: CIP | Z47: CIP | AA47: MANZANILLO | AB47: YANTIAN | AC47: MANZANILLO | AD47: 46080 | AE47: 46125 | AF47: 46090 | AG47: FGD-CS | AH47: 6130084 | AI47: 46087 | AJ47: 46088 | AK47: 192000 | AL47: 34798 | AM47: 101513756372 | AN47: 46088 | AO47: 46088.585 | AP47: USD | AQ47: 0.00991 | AR47: 1902.72 | AS47: USD | AT47: 1902.72 | AU47: JOHN JH SHI | AV47: MSC-SEA-GEN | AW47: MANZANILLO EXPRESS V.2611E | AX47: 46092 | AY47: 46141 | AZ47: MSNU9003952 | BA47: 40HQ | BB47: MEDUWH352603 | BC47: 12000 | BD47: KG | BE47: 10.8048 | BF47: 10.4148 | BG47: MM | BH47: 368 | BI47: 257 | BJ47: 136 | BK47: 6 | BL47: KG | BM47: 72.8288 | BN47: 62.4888 | BO47: 196.8768 | BP47: MM | BQ47: 800 | BR47: 300 | BS47: 608 | BT47: 2 | BU47: 1 | BV47: 3 | BW47: 16 | BX47: 0 | BY47: 16 | BZ47: 144000 | CA47: 48000 | CB47: 192000 | CC47: 166.6368 | CD47: C-PAL-507001 | CE47: C-BOX-594165 | CG47: JE IM OU | CJ47: OOLU9103769 | CN47: M45 | CO47: 1404-12C0002EN | CP47: CCLU7673540 | CQ47: 2636.6756 | CR47: =IFERROR(CQ47/(SUMIFS(CQ:CQ,CP:CP,CP47)),100%) -> 0.21044811 | CS47: =CR47*$CS$2 -> 526.12028
... B57: MCS | C57: 1275409314 | F57: 34798 | G57: JOHNSON ELECTRIC NORTH AMERICA INC. | H57: Tax ID JEG120120DD4 BOULEVARD MORELOS NO. 1109 MEGA PARQUE INDUSTRIAL AEROPUERTO DE CALERA C.P. 98519 CALERA ZACATECAS MX | I57: XEXX010101000 | J57: JEN | K57: W03 | L57: C&S-INTERNAL-SWO-HSG-MX | M57: FLOW | N57: 1 | O57: 1 | P57: 1209-5YY0497EN | Q57: A | R57: CE.YY.TERMINAL | S57: TERMINAL 8351296(1209-5YY0497-T2EN) | T57: TT45ASA | U57: 50950081110 | W57: 7200 | X57: SEA | Y57: CIP | Z57: CIP | AA57: MANZANILLO | AB57: YANTIAN | AC57: MANZANILLO | AD57: 46083 | AE57: 46139 | AF57: 46090 | AG57: FGD-CS | AH57: 6130094 | AI57: 46087 | AJ57: 46088 | AK57: 7200 | AL57: 34798 | AM57: 101513756379 | AN57: 46088 | AO57: 46088.585 | AP57: USD | AQ57: 0.05433 | AR57: 391.18 | AS57: USD | AT57: 391.18 | AU57: JOHN JH SHI | AV57: MSC-SEA-GEN | AW57: MANZANILLO EXPRESS V.2611E | AX57: 46092 | AY57: 46141 | AZ57: MSNU9003952 | BA57: 40HQ | BB57: MEDUWH352603 | BC57: 900 | BD57: KG | BE57: 2.9651 | BF57: 1.2951 | BG57: MM | BH57: 395 | BI57: 295 | BJ57: 150 | BK57: 8 | BL57: KG | BM57: 31.7208 | BN57: 10.3608 | BO57: 31.7208 | BP57: MM | BQ57: 800 | BR57: 300 | BS57: 760 | BT57: 1 | BU57: 0 | BV57: 1 | BW57: 8 | BX57: 0 | BY57: 8 | BZ57: 7200 | CA57: 0 | CB57: 7200 | CC57: 10.3608 | CD57: C-PAL-146015 | CE57: C-BOX-474030 | CG57: JE IM OU | CJ57: TIIU2575610 | CN57: M45 | CO57: 1210-10C0133EN | CP57: CCLU7843605 | CQ57: 283.06 | CR57: =IFERROR(CQ57/(SUMIFS(CQ:CQ,CP:CP,CP57)),100%) -> 0.025602158 | CS57: =CR57*$CS$2 -> 64.005394
B58: M19 | C58: 1275409403 | D58: NOT APPLICABLE | F58: 34798 | G58: JOHNSON ELECTRIC NORTH AMERICA INC. | H58: BOULEVARD MORELOS NO. 1109 MEGA PARQUE INDUSTRIAL AEROPUERTO DE CALERA C.P. 98519 CALERA ZACATECAS Tax ID JEG120120DD4 MX | I58: XEXX010101000 | J58: JEN | K58: W03 | L58: C&S-INTERNAL-SWO-HSG-MX | M58: FLOW | N58: 1 | O58: 1 | P58: 1322-5YY0003EP | Q58: E | R58: CE.YY.COVER | S58: BEARING PLATE 8191162 / 8190442 | T58: TT45ASA | U58: 50950081225 | V58: 8191162 | W58: 12000 | X58: SEA | Y58: CIP | Z58: CIP | AA58: MANZANILLO | AB58: YANTIAN | AC58: MANZANILLO | AD58: 46083 | AE58: 46139 | AF58: 46090 | AG58: FGD-CS | AH58: 6130095 | AI58: 46087 | AJ58: 46088 | AK58: 12000 | AL58: 34798 | AM58: 101513756356 | AN58: 46088 | AO58: 46088.585 | AP58: USD | AQ58: 0.01905 | AR58: 228.6 | AS58: USD | AT58: 228.6 | AU58: JOHN JH SHI | AV58: MSC-SEA-GEN | AW58: MANZANILLO EXPRESS V.2611E | AX58: 46092 | AY58: 46141 | AZ58: MSNU9003952 | BA58: 40HQ | BB58: MEDUWH352603 | BC58: 3000 | BD58: KG | BE58: 7.996 | BF58: 7.11 | BG58: MM | BH58: 395 | BI58: 295 | BJ58: 210 | BK58: 32 | BL58: KG | BM58: 56.984 | BN58: 28.44 | BO58: 56.984 | BP58: MM | BQ58: 1200 | BR58: 800 | BS58: 1006 | BT58: 0 | BU58: 1 | BV58: 1 | BW58: 4 | BX58: 0 | BY58: 4 | BZ58: 0 | CA58: 12000 | CB58: 12000 | CC58: 28.44 | CD58: C-PAL-048001 | CE58: 1504-1YY0133 | CG58: JE IM OU | CJ58: TRHU4923520 | CN58: M19 | CO58: 1330-5YY0182EN | CP58: CCLU7843605 | CQ58: 1053.8136 | CR58: =IFERROR(CQ58/(SUMIFS(CQ:CQ,CP:CP,CP58)),100%) -> 0.095315134 | CS58: =CR58*$CS$2 -> 238.28784
B59: M46 | C59: 1275409746 | F59: 34798 | G59: JOHNSON ELECTRIC NORTH AMERICA INC. | H59: Tax ID JEG120120DD4 BOULEVARD MORELOS NO. 1109 MEGA PARQUE INDUSTRIAL AEROPUERTO DE CALERA C.P. 98519 CALERA ZACATECAS MX | I59: XEXX010101000 | J59: JEN | K59: W01 | L59: C&S-INTERNAL-SWO-HSG-MX | M59: FLOW | N59: 1 | O59: 1 | P59: 1101-EQN0004EN | Q59: C | R59: BB.YY.SHAFT | S59: SHAFT | T59: TT45ASA | U59: 50950081291 | W59: 16000 | X59: SEA | Y59: CIP | Z59: CIP | AA59: MANZANILLO | AB59: YANTIAN | AC59: MANZANILLO | AD59: 46083 | AE59: 46139 | AF59: 46090 | AG59: FGD-CS | AH59: 6130096 | AI59: 46087 | AJ59: 46088 | AK59: 16000 | AL59: 34798 | AM59: 101513756374 | AN59: 46088 | AO59: 46088.585 | AP59: USD | AQ59: 0.11368 | AR59: 1818.88 | AS59: USD | AT59: 1818.88 | AU59: JOHN JH SHI | AV59: MSC-SEA-GEN | AW59: MANZANILLO EXPRESS V.2611E | AX59: 46092 | AY59: 46141 | AZ59: MSNU9003952 | BA59: 40HQ | BB59: MEDUWH352603 | BC59: 2000 | BD59: KG | BE59: 10.0184 | BF59: 9.6904 | BG59: MM | BH59: 296 | BI59: 195 | BJ59: 145 | BK59: 12 | BL59: KG | BM59: 88.1472 | BN59: 77.5232 | BO59: 88.1472 | BP59: MM | BQ59: 800 | BR59: 300 | BS59: 608 | BT59: 0 | BU59: 1 | BV59: 1 | BW59: 8 | BX59: 0 | BY59: 8 | BZ59: 0 | CA59: 16000 | CB59: 16000 | CC59: 77.5232 | CD59: C-PAL-507001 | CE59: C-BOX-001008 | CG59: JE IM OU | CJ59: TRHU5512159 | CN59: M19 | CO59: 1330-5YY0183EN | CP59: CCLU7843605 | CQ59: 773.0928 | CR59: =IFERROR(CQ59/(SUMIFS(CQ:CQ,CP:CP,CP59)),100%) -> 0.069924552 | CS59: =CR59*$CS$2 -> 174.81138
B60: M23 | C60: 1275411877 | F60: 34798 | G60: JOHNSON ELECTRIC NORTH AMERICA INC. | H60: Tax ID JEG120120DD4 BOULEVARD MORELOS NO. 1109 MEGA PARQUE INDUSTRIAL AEROPUERTO DE CALERA C.P. 98519 CALERA ZACATECAS MX | I60: XEXX010101000 | J60: JEN | K60: Y01 | L60: C&S-INTERNAL-SWO-HSG-MX | M60: FLOW | N60: 1 | O60: 1 | P60: 1415-1060749EN | Q60: B | R60: SB.700.BUSHING | S60: PINION | T60: TT45ASA | U60: 50950081533 | W60: 25600 | X60: SEA | Y60: CIP | Z60: CIP | AA60: MANZANILLO | AB60: YANTIAN | AC60: MANZANILLO | AD60: 46087 | AE60: 46132 | AF60: 46090 | AG60: FGD-CS | AH60: 6130097 | AI60: 46087 | AJ60: 46088 | AK60: 25600 | AL60: 34798 | AM60: 101513756363 | AN60: 46088 | AO60: 46088.585 | AP60: USD | AQ60: 0.07612 | AR60: 1948.67 | AS60: USD | AT60: 1948.67 | AU60: JOHN JH SHI | AV60: MSC-SEA-GEN | AW60: MANZANILLO EXPRESS V.2611E | AX60: 46092 | AY60: 46141 | AZ60: MSNU9003952 | BA60: 40HQ | BB60: MEDUWH352603 | BC60: 1600 | BD60: KG | BE60: 13.2516 | BF60: 11.1016 | BG60: MM | BH60: 395 | BI60: 295 | BJ60: 100 | BK60: 12 | BL60: KG | BM60: 167.0192 | BN60: 133.2192 | BO60: 228.0256 | BP60: MM | BQ60: 800 | BR60: 300 | BS60: 758 | BT60: 1 | BU60: 1 | BV60: 2 | BW60: 16 | BX60: 0 | BY60: 16 | BZ60: 19200 | CA60: 6400 | CB60: 25600 | CC60: 177.6256 | CD60: C-PAL-294039 | CE60: C-BOX-474127 | CG60: JE IM OU | CJ60: WHSU2218868 | CN60: M19 | CO60: 1330-5YY0183EN | CP60: CCLU7843605 | CQ60: 515.3952 | CR60: =IFERROR(CQ60/(SUMIFS(CQ:CQ,CP:CP,CP60)),100%) -> 0.046616368 | CS60: =CR60*$CS$2 -> 116.54092
B61: M46 | C61: 1275412196 | F61: 34798 | G61: JOHNSON ELECTRIC NORTH AMERICA INC. | H61: Tax ID JEG120120DD4 BOULEVARD MORELOS NO. 1109 MEGA PARQUE INDUSTRIAL AEROPUERTO DE CALERA C.P. 98519 CALERA ZACATECAS MX | I61: XEXX010101000 | J61: JEN | K61: W01 | L61: C&S-INTERNAL-SWO-HSG-MX | M61: FLOW | N61: 1 | O61: 1 | P61: 1101-EQN0001EN | Q61: B | R61: BB.YY.SHAFT | S61: SHAFT | T61: TT45ASA | U61: 50950081572 | W61: 18000 | X61: SEA | Y61: CIP | Z61: CIP | AA61: MANZANILLO | AB61: YANTIAN | AC61: MANZANILLO | AD61: 46097 | AE61: 46153 | AF61: 46090 | AG61: FGD-CS | AH61: 6130098 | AI61: 46087 | AJ61: 46088 | AK61: 18000 | AL61: 34798 | AM61: 101513756373 | AN61: 46088 | AO61: 46088.585 | AP61: USD | AQ61: 0.01242 | AR61: 223.56 | AS61: USD | AT61: 223.56 | AU61: JOHN JH SHI | AV61: MSC-SEA-GEN | AW61: MANZANILLO EXPRESS V.2611E | AX61: 46092 | AY61: 46141 | AZ61: MSNU9003952 | BA61: 40HQ | BB61: MEDUWH352603 | BC61: 6000 | BD61: KG | BE61: 9.097 | BF61: 8.769 | BG61: MM | BH61: 296 | BI61: 195 | BJ61: 145 | BK61: 12 | BL61: KG | BM61: 35.291 | BN61: 26.307 | BO61: 35.291 | BP61: MM | BQ61: 800 | BR61: 300 | BS61: 608 | BT61: 0 | BU61: 1 | BV61: 1 | BW61: 3 | BX61: 0 | BY61: 3 | BZ61: 0 | CA61: 18000 | CB61: 18000 | CC61: 26.307 | CD61: C-PAL-507001 | CE61: C-BOX-001008 | CG61: JE IM OU | CJ61: WHSU5613188 | CN61: M19 | CO61: 1330-5YY0112EN | CP61: CCLU7843605 | CQ61: 2073.4795 | CR61: =IFERROR(CQ61/(SUMIFS(CQ:CQ,CP:CP,CP61)),100%) -> 0.18754169 | CS61: =CR61*$CS$2 -> 468.85421
B62: M46 | C62: 1275412198 | F62: 34798 | G62: JOHNSON ELECTRIC NORTH AMERICA INC. | H62: Tax ID JEG120120DD4 BOULEVARD MORELOS NO. 1109 MEGA PARQUE INDUSTRIAL AEROPUERTO DE CALERA C.P. 98519 CALERA ZACATECAS MX | I62: XEXX010101000 | J62: JEN | K62: W01 | L62: C&S-INTERNAL-SWO-HSG-MX | M62: FLOW | N62: 1 | O62: 1 | P62: 1101-EQN0004EN | Q62: C | R62: BB.YY.SHAFT | S62: SHAFT | T62: TT45ASA | U62: 50950081575 | W62: 16000 | X62: SEA | Y62: CIP | Z62: CIP | AA62: MANZANILLO | AB62: YANTIAN | AC62: MANZANILLO | AD62: 46090 | AE62: 46146 | AF62: 46090 | AG62: FGD-CS | AH62: 6130099 | AI62: 46087 | AJ62: 46088 | AK62: 16000 | AL62: 34798 | AM62: 101513756375 | AN62: 46088 | AO62: 46088.585 | AP62: USD | AQ62: 0.11368 | AR62: 1818.88 | AS62: USD | AT62: 1818.88 | AU62: JOHN JH SHI | AV62: MSC-SEA-GEN | AW62: MANZANILLO EXPRESS V.2611E | AX62: 46092 | AY62: 46141 | AZ62: MSNU9003952 | BA62: 40HQ | BB62: MEDUWH352603 | BC62: 2000 | BD62: KG | BE62: 10.0184 | BF62: 9.6904 | BG62: MM | BH62: 296 | BI62: 195 | BJ62: 145 | BK62: 12 | BL62: KG | BM62: 88.1472 | BN62: 77.5232 | BO62: 88.1472 | BP62: MM | BQ62: 800 | BR62: 300 | BS62: 608 | BT62: 0 | BU62: 1 | BV62: 1 | BW62: 8 | BX62: 0 | BY62: 8 | BZ62: 0 | CA62: 16000 | CB62: 16000 | CC62: 77.5232 | CD62: C-PAL-507001 | CE62: C-BOX-001008 | CG62: JE IM OU | CJ62: WHSU5760194 | CN62: M19 | CO62: 1330-5YY0168EN | CP62: CCLU7843605 | CQ62: 1284.96 | CR62: =IFERROR(CQ62/(SUMIFS(CQ:CQ,CP:CP,CP62)),100%) -> 0.11622182 | CS62: =CR62*$CS$2 -> 290.55455
B63: M23 | C63: 1275412966 | F63: 34798 | G63: JOHNSON ELECTRIC NORTH AMERICA INC. | H63: Tax ID JEG120120DD4 BOULEVARD MORELOS NO. 1109 MEGA PARQUE INDUSTRIAL AEROPUERTO DE CALERA C.P. 98519 CALERA ZACATECAS MX | I63: XEXX010101000 | J63: JEN | K63: W01 | L63: C&S-INTERNAL-SWO-HSG-MX | M63: FLOW | N63: 1 | O63: 1 | P63: 1101-1060600EN | Q63: C | R63: BB.600.SHAFT | S63: SHAFT | T63: TT45ASA | U63: 50950081622 | W63: 30000 | X63: SEA | Y63: CIP | Z63: CIP | AA63: MANZANILLO | AB63: YANTIAN | AC63: MANZANILLO | AD63: 46083 | AE63: 46139 | AF63: 46090 | AG63: FGD-CS | AH63: 6130100 | AI63: 46087 | AJ63: 46088 | AK63: 30000 | AL63: 34798 | AM63: 101513756362 | AN63: 46088 | AO63: 46088.585 | AP63: USD | AQ63: 0.041 | AR63: 1230 | AS63: USD | AT63: 1230 | AU63: JOHN JH SHI | AV63: MSC-SEA-GEN | AW63: MANZANILLO EXPRESS V.2611E | AX63: 46092 | AY63: 46141 | AZ63: MSNU9003952 | BA63: 40HQ | BB63: MEDUWH352603 | BC63: 1000 | BD63: KG | BE63: 7.854 | BF63: 7.526 | BG63: MM | BH63: 296 | BI63: 195 | BJ63: 145 | BK63: 12 | BL63: KG | BM63: 102.248 | BN63: 90.312 | BO63: 259.62 | BP63: MM | BQ63: 800 | BR63: 300 | BS63: 608 | BT63: 2 | BU63: 1 | BV63: 3 | BW63: 30 | BX63: 0 | BY63: 30 | BZ63: 24000 | CA63: 6000 | CB63: 30000 | CC63: 225.78 | CD63: C-PAL-507001 | CE63: C-BOX-001008 | CG63: JE IM OU | CJ63: WHSU6740607 | CN63: M01 | CO63: 1301-1030479EN | CP63: CCLU7843605 | CQ63: 737.44 | CR63: =IFERROR(CQ63/(SUMIFS(CQ:CQ,CP:CP,CP63)),100%) -> 0.066699834 | CS63: =CR63*$CS$2 -> 166.74959
B64: M23 | C64: 3275162412 | F64: 34798 | G64: JOHNSON ELECTRIC NORTH AMERICA INC. | H64: Tax ID JEG120120DD4 BOULEVARD MORELOS NO. 1109 MEGA PARQUE INDUSTRIAL AEROPUERTO DE CALERA C.P. 98519 CALERA ZACATECAS MX | I64: XEXX010101000 | J64: JEN | K64: Y01 | L64: C&S-INTERNAL-RUSH-HSG-MX | M64: FLOW | N64: 1 | O64: 1 | P64: 1415-1060749EN | Q64: B | R64: SB.700.BUSHING | S64: PINION | T64: TT45ASA | U64: 50950081542 | W64: 25600 | X64: SEA | Y64: CIP | Z64: CIP | AA64: MANZANILLO | AB64: YANTIAN | AC64: MANZANILLO | AD64: 46080 | AE64: 46111 | AF64: 46090 | AG64: FGD-CS | AH64: 6130101 | AI64: 46087 | AJ64: 46088 | AK64: 25600 | AL64: 34798 | AM64: 101513756364 | AN64: 46088 | AO64: 46088.585 | AP64: USD | AQ64: 0.07612 | AR64: 1948.67 | AS64: USD | AT64: 1948.67 | AU64: JOHN JH SHI | AV64: MSC-SEA-GEN | AW64: MANZANILLO EXPRESS V.2611E | AX64: 46092 | AY64: 46141 | AZ64: MSNU9003952 | BA64: 40HQ | BB64: MEDUWH352603 | BC64: 1600 | BD64: KG | BE64: 13.2516 | BF64: 11.1016 | BG64: MM | BH64: 395 | BI64: 295 | BJ64: 100 | BK64: 12 | BL64: KG | BM64: 167.0192 | BN64: 133.2192 | BO64: 228.0256 | BP64: MM | BQ64: 800 | BR64: 300 | BS64: 758 | BT64: 1 | BU64: 1 | BV64: 2 | BW64: 16 | BX64: 0 | BY64: 16 | BZ64: 19200 | CA64: 6400 | CB64: 25600 | CC64: 177.6256 | CD64: C-PAL-294039 | CE64: C-BOX-474127 | CG64: JE IM OU | CJ64: ZCSU7928505 | CN64: M01 | CO64: 1301-1030479EN | CP64: CCLU7843605 | CQ64: 368.72 | CR64: =IFERROR(CQ64/(SUMIFS(CQ:CQ,CP:CP,CP64)),100%) -> 0.033349917 | CS64: =CR64*$CS$2 -> 83.374793
B65: M23 | C65: 3275162414 | F65: 34798 | G65: JOHNSON ELECTRIC NORTH AMERICA INC. | H65: Tax ID JEG120120DD4 BOULEVARD MORELOS NO. 1109 MEGA PARQUE INDUSTRIAL AEROPUERTO DE CALERA C.P. 98519 CALERA ZACATECAS MX | I65: XEXX010101000 | J65: JE | K65: Y04 | L65: C&S-INTERNAL-RUSH-HJM-MX | M65: EXPORT | N65: 1 | O65: 1 | P65: 1318-1YY0567EN | Q65: A | R65: CR.YY.O-RING | S65: O-RING | T65: TT45ASA | U65: 50950081584 | W65: 3000 | X65: AIR | Y65: CIP | Z65: CIP | AA65: MANZANILLO | AB65: HONG KONG | AC65: MANZANILLO | AD65: 46080 | AE65: 46083 | AF65: 46082 | AG65: FGD-JCE | AH65: 6119042 | AI65: 46080 | AJ65: 46083 | AK65: 3000 | AL65: 34798 | AM65: 101513753470 | AN65: 46083 | AO65: 46083.385 | AP65: USD | AQ65: 0.12189 | AR65: 365.67 | AS65: USD | AT65: 365.67 | AU65: DICK ZJ WU | AV65: DHL COURIER-AIR-GEN | AW65: K4241 | AX65: 46084 | AY65: 46090 | BA65: AIR | BB65: 1644074541 | BC65: 1200 | BD65: KG | BE65: 2.8952 | BF65: 2.0952 | BG65: MM | BH65: 395 | BI65: 295 | BJ65: 210 | BK65: 32 | BL65: KG | BM65: 37.638 | BN65: 5.238 | BO65: 37.638 | BP65: MM | BQ65: 1200 | BR65: 800 | BS65: 1000 | BT65: 0 | BU65: 1 | BV65: 1 | BW65: 2 | BX65: 1 | BY65: 3 | BZ65: 0 | CA65: 3000 | CB65: 3000 | CC65: 5.238 | CD65: C-PAL-11803 | CE65: C-BOX-594074 | CG65: JE IM OU | CN65: M01 | CO65: 1301-1030476EN | CP65: CCLU7843605 | CQ65: 1474.88 | CR65: =IFERROR(CQ65/(SUMIFS(CQ:CQ,CP:CP,CP65)),100%) -> 0.13339967 | CS65: =CR65*$CS$2 -> 333.49917
B66: M23 | C66: 3275162555 | F66: 34798 | G66: JOHNSON ELECTRIC NORTH AMERICA INC. | H66: Tax ID JEG120120DD4 BOULEVARD MORELOS NO. 1109 MEGA PARQUE INDUSTRIAL AEROPUERTO DE CALERA C.P. 98519 CALERA ZACATECAS MX | I66: XEXX010101000 | J66: JE | K66: Y04 | L66: C&S-INTERNAL-RUSH-HJM-MX | M66: EXPORT | N66: 1 | O66: 1 | P66: 1318-1E90169EN | Q66: A | R66: CR.YY.O-RING | S66: O-RING | T66: TT45ASA | U66: 50950081895 | W66: 8000 | X66: AIR | Y66: CIP | Z66: CIP | AA66: MANZANILLO | AB66: HONG KONG | AC66: MANZANILLO | AD66: 46080 | AE66: 46104 | AF66: 46082 | AG66: FGD-JCE | AH66: 6119043 | AI66: 46080 | AJ66: 46083 | AK66: 8000 | AL66: 34798 | AM66: 101513753469 | AN66: 46083 | AO66: 46083.385 | AP66: USD | AQ66: 0.03107 | AR66: 248.56 | AS66: USD | AT66: 248.56 | AU66: DICK ZJ WU | AV66: DHL COURIER-AIR-GEN | AW66: 3S500 | AX66: 46084 | AY66: 46090 | BA66: AIR | BB66: 1644074541 | BC66: 8000 | BD66: KG | BE66: 3.808 | BF66: 3.008 | BG66: MM | BH66: 395 | BI66: 295 | BJ66: 210 | BK66: 6 | BL66: KG | BM66: 11.808 | BN66: 3.008 | BO66: 11.808 | BP66: MM | BQ66: 800 | BR66: 300 | BS66: 790 | BT66: 0 | BU66: 1 | BV66: 1 | BW66: 1 | BX66: 0 | BY66: 1 | BZ66: 0 | CA66: 8000 | CB66: 8000 | CC66: 3.008 | CD66: C-PAL-294025 | CE66: C-BOX-594074 | CG66: JE IM OU | CN66: M45 | CO66: 1205-10C0010EN | CP66: CSGU2004557 | CQ66: 0.1 | CR66: =IFERROR(CQ66/(SUMIFS(CQ:CQ,CP:CP,CP66)),100%) -> 1.3826453e-05 | CS66: =CR66*$CS$2 -> 0.034566133
B67: M01 | C67: 1015081121 | D67: QIONG PENG | F67: 34798 | G67: JOHNSON ELECTRIC NORTH AMERICA INC. | H67: Tax ID JEG120120DD4 BOULEVARD MORELOS NO. 1109 MEGA PARQUE INDUSTRIAL AEROPUERTO DE CALERA C.P. 98519 CALERA ZACATECAS MX | I67: XEXX010101000 | J67: JE | K67: A99 | L67: BI-INTERNAL-SWO-HJM-MX | M67: FLOW | N67: 1 | O67: 3 | P67: 1200-1030990EN0002 | Q67: A | R67: EC.N.NONE | S67: END CAP ASS'Y WITH PACKAGING | T67: TT45ASA | U67: 50950080607 | W67: 46080 | X67: SEA | Y67: CIP | Z67: CIP | AA67: MANZANILLO | AB67: SHEKOU | AC67: MANZANILLO | AD67: 46074 | AE67: 46132 | AF67: 46090 | AG67: FG-BI-14E | AH67: 6123114 | AI67: 46083 | AJ67: 46084 | AK67: 46080 | AL67: 34798 | AM67: 101513754415 | AN67: 46084 | AO67: 46084.447 | AP67: USD | AQ67: 0.18359 | AR67: 8459.84 | AS67: USD | AT67: 8459.84 | AU67: JOHN JH SHI | AV67: SHIPCO TRANSPORT-SEA-GEN | AW67: WAN HAI A16 V.E010 | AX67: 46089 | AY67: 46138 | AZ67: TGBU7107819 | BA67: 40HQ | BB67: 22145133 | BC67: 240 | BD67: KG | BE67: 2.5634 | BF67: 1.2864 | BG67: MM | BH67: 340 | BI67: 250 | BJ67: 230 | BK67: 48 | BL67: KG | BM67: 144.0432 | BN67: 61.7472 | BO67: 576.1728 | BP67: MM | BQ67: 1066 | BR67: 1066 | BS67: 1080 | BT67: 4 | BU67: 0 | BV67: 4 | BW67: 192 | BX67: 0 | BY67: 192 | BZ67: 46080 | CA67: 0 | CB67: 46080 | CC67: 246.9888 | CD67: C-PAL-233041 | CE67: C-BOX-233127 | CG67: JE IM OU | CN67: M45 | CO67: 1205-10C0010EN | CP67: CSGU2004557 | CQ67: 0.1 | CR67: =IFERROR(CQ67/(SUMIFS(CQ:CQ,CP:CP,CP67)),100%) -> 1.3826453e-05 | CS67: =CR67*$CS$2 -> 0.034566133
B68: M19 | C68: 1195009717 | F68: 34798 | G68: JOHNSON ELECTRIC NORTH AMERICA INC. | H68: Tax ID JEG120120DD4 BOULEVARD MORELOS NO. 1109 MEGA PARQUE INDUSTRIAL AEROPUERTO DE CALERA C.P. 98519 CALERA ZACATECAS MX | I68: XEXX010101000 | J68: JE | K68: Q03 | L68: PC-INTERNAL-SWO-HJM-MX | M68: FLOW | N68: 1 | O68: 1 | P68: 1275-5YY0783EN | Q68: G | R68: DC.CFM.CFM | S68: COMPLETE WIRE HARNESS | T68: TT45ASA | U68: 50950076748 | W68: 8064 | X68: SEA | Y68: CIP | Z68: CIP | AA68: MANZANILLO | AB68: SHEKOU | AC68: MANZANILLO | AD68: 46083 | AE68: 46139 | AF68: 46090 | AG68: FG-PC-13E | AH68: 6123115 | AI68: 46083 | AJ68: 46084 | AK68: 8064 | AL68: 34798 | AM68: 101513754405 | AN68: 46084 | AO68: 46084.447 | AP68: USD | AQ68: 2.19133 | AR68: 17670.88 | AS68: USD | AT68: 17670.88 | AU68: JOHN JH SHI | AV68: SHIPCO TRANSPORT-SEA-GEN | AW68: WAN HAI A16 V.E010 | AX68: 46089 | AY68: 46138 | AZ68: TGBU7107819 | BA68: 40HQ | BB68: 22145133 | BC68: 28 | BD68: KG | BE68: 4.1198 | BF68: 2.2568 | BG68: MM | BH68: 795 | BI68: 395 | BJ68: 145 | BK68: 18 | BL68: KG | BM68: 99.1564 | BN68: 40.6224 | BO68: 1586.5024 | BP68: MM | BQ68: 1200 | BR68: 800 | BS68: 1030 | BT68: 16 | BU68: 0 | BV68: 16 | BW68: 288 | BX68: 0 | BY68: 288 | BZ68: 8064 | CA68: 0 | CB68: 8064 | CC68: 649.9584 | CD68: C-PAL-158001 | CE68: C-BOX-233190 | CG68: JE IM OU | CN68: M46 | CO68: 1123-1060052EN | CP68: CSGU2004557 | CQ68: 637.71168 | CR68: =IFERROR(CQ68/(SUMIFS(CQ:CQ,CP:CP,CP68)),100%) -> 0.088172906 | CS68: =CR68*$CS$2 -> 220.43227
B69: M01 | C69: 1275349495 | F69: 34798 | G69: JOHNSON ELECTRIC NORTH AMERICA INC. | H69: Tax ID JEG120120DD4 BOULEVARD MORELOS NO. 1109 MEGA PARQUE INDUSTRIAL AEROPUERTO DE CALERA C.P. 98519 CALERA ZACATECAS MX | I69: XEXX010101000 | J69: JE | K69: Y07 | L69: C&S-INTERNAL-SWO-HJM-MX | M69: FLOW | N69: 1 | O69: 2 | P69: 1438-1010107EN | Q69: F | R69: PCBA.100.PCBA | S69: PCB ASS'Y(1438-1010107-MTEN) | T69: TT45ASA | U69: 50950072176 | W69: 8640 | X69: SEA | Y69: CIP | Z69: CIP | AA69: MANZANILLO | AB69: SHEKOU | AC69: MANZANILLO | AD69: 46076 | AE69: 46076 | AF69: 46090 | AG69: FGD-JCE | AH69: 6123116 | AI69: 46083 | AJ69: 46084 | AK69: 8640 | AL69: 34798 | AM69: 101513754414 | AN69: 46084 | AO69: 46084.447 | AP69: USD | AQ69: 1.38604 | AR69: 11975.38 | AS69: USD | AT69: 11975.38 | AU69: JOHN JH SHI | AV69: SHIPCO TRANSPORT-SEA-GEN | AW69: WAN HAI A16 V.E010 | AX69: 46089 | AY69: 46138 | AZ69: TGBU7107819 | BA69: 40HQ | BB69: 22145133 | BC69: 108 | BD69: KG | BE69: 2.8953 | BF69: 1.8403 | BG69: MM | BH69: 495 | BI69: 295 | BJ69: 180 | BK69: 40 | BL69: KG | BM69: 142.812 | BN69: 73.612 | BO69: 285.6256 | BP69: MM | BQ69: 1200 | BR69: 1000 | BS69: 1060 | BT69: 2 | BU69: 0 | BV69: 2 | BW69: 80 | BX69: 0 | BY69: 80 | BZ69: 8640 | CA69: 0 | CB69: 8640 | CC69: 147.2256 | CD69: C-PAL-294061 | CE69: C-BOX-001384 | CG69: JE IM OU | CN69: M19 | CO69: 1220-5YY0030EN | CP69: CSGU2004557 | CQ69: 639.1994 | CR69: =IFERROR(CQ69/(SUMIFS(CQ:CQ,CP:CP,CP69)),100%) -> 0.088378605 | CS69: =CR69*$CS$2 -> 220.94651
B70: M01 | C70: 1275349991 | F70: 34798 | G70: JOHNSON ELECTRIC NORTH AMERICA INC. | H70: Tax ID JEG120120DD4 BOULEVARD MORELOS NO. 1109 MEGA PARQUE INDUSTRIAL AEROPUERTO DE CALERA C.P. 98519 CALERA ZACATECAS MX | I70: XEXX010101000 | J70: JE | K70: Y07 | L70: C&S-INTERNAL-SWO-HJM-MX | M70: FLOW | N70: 1 | O70: 5 | P70: 1438-1010133EN | Q70: D | R70: PCBA.100.PCBA | S70: (LEADWIRE)CONN & PCB ASSY (AUTOMOTIVE GRADE) | T70: TT45ASA | U70: 50950072254 | W70: 8640 | X70: SEA | Y70: CIP | Z70: CIP | AA70: MANZANILLO | AB70: SHEKOU | AC70: MANZANILLO | AD70: 46076 | AE70: 46111 | AF70: 46090 | AG70: FGD-JCE | AH70: 6123117 | AI70: 46083 | AJ70: 46084 | AK70: 8640 | AL70: 34798 | AM70: 101513754413 | AN70: 46084 | AO70: 46084.447 | AP70: USD | AQ70: 1.44828 | AR70: 12513.15 | AS70: USD | AT70: 12513.15 | AU70: JOHN JH SHI | AV70: SHIPCO TRANSPORT-SEA-GEN | AW70: WAN HAI A16 V.E010 | AX70: 46089 | AY70: 46138 | AZ70: TGBU7107819 | BA70: 40HQ | BB70: 22145133 | BC70: 72 | BD70: KG | BE70: 2.5281 | BF70: 1.3421 | BG70: MM | BH70: 495 | BI70: 295 | BJ70: 180 | BK70: 40 | BL70: KG | BM70: 128.124 | BN70: 53.684 | BO70: 384.3696 | BP70: MM | BQ70: 1200 | BR70: 1000 | BS70: 1058 | BT70: 3 | BU70: 0 | BV70: 3 | BW70: 120 | BX70: 0 | BY70: 120 | BZ70: 8640 | CA70: 0 | CB70: 8640 | CC70: 161.0496 | CD70: C-PAL-387001 | CE70: C-BOX-2330011 | CG70: JE IM OU | CN70: M19 | CO70: 1220-5YY0030EN | CP70: CSGU2004557 | CQ70: 479.39955 | CR70: =IFERROR(CQ70/(SUMIFS(CQ:CQ,CP:CP,CP70)),100%) -> 0.066283954 | CS70: =CR70*$CS$2 -> 165.70988
B71: M45 | C71: 1275396288 | F71: 34798 | G71: JOHNSON ELECTRIC NORTH AMERICA INC. | H71: Tax ID JEG120120DD4 BOULEVARD MORELOS NO. 1109 MEGA PARQUE INDUSTRIAL AEROPUERTO DE CALERA C.P. 98519 CALERA ZACATECAS MX | I71: XEXX010101000 | J71: JE | K71: Y04 | L71: C&S-INTERNAL-SWO-HJM-MX | M71: FLOW | N71: 1 | O71: 1 | P71: 1100-12C0005EN | Q71: C | R71: CB.12.ROTOR ASSY | S71: OVERMOLD ROTOR | T71: TT45ASA | U71: 50950079596 | W71: 14400 | X71: SEA | Y71: CIP | Z71: CIP | AA71: MANZANILLO | AB71: SHEKOU | AC71: MANZANILLO | AD71: 46083 | AE71: 46153 | AF71: 46090 | AG71: FGD-JCE | AH71: 6123118 | AI71: 46083 | AJ71: 46084 | AK71: 14400 | AL71: 34798 | AM71: 101513754407 | AN71: 46084 | AO71: 46084.447 | AP71: USD | AQ71: 0.30101 | AR71: 4334.54 | AS71: USD | AT71: 4334.54 | AU71: JOHN JH SHI | AV71: SHIPCO TRANSPORT-SEA-GEN | AW71: WAN HAI A16 V.E010 | AX71: 46089 | AY71: 46138 | AZ71: TGBU7107819 | BA71: 40HQ | BB71: 22145133 | BC71: 288 | BD71: KG | BE71: 13.2311 | BF71: 11.8161 | BG71: MM | BH71: 395 | BI71: 295 | BJ71: 160 | BK71: 60 | BL71: KG | BM71: 688.5532 | BN71: 590.8032 | BO71: 688.5532 | BP71: MM | BQ71: 1200 | BR71: 1000 | BS71: 1120 | BT71: 0 | BU71: 1 | BV71: 1 | BW71: 50 | BX71: 0 | BY71: 50 | BZ71: 0 | CA71: 14400 | CB71: 14400 | CC71: 590.8032 | CD71: C-PAL-146020 | CE71: C-BOX-001372 | CG71: JE IM OU | CN71: M46 | CO71: 1415-EQN0005EN | CP71: CSGU2004557 | CQ71: 438.8108 | CR71: =IFERROR(CQ71/(SUMIFS(CQ:CQ,CP:CP,CP71)),100%) -> 0.060671969 | CS71: =CR71*$CS$2 -> 151.67992
B72: M45 | C72: 1275396288 | F72: 34798 | G72: JOHNSON ELECTRIC NORTH AMERICA INC. | H72: Tax ID JEG120120DD4 BOULEVARD MORELOS NO. 1109 MEGA PARQUE INDUSTRIAL AEROPUERTO DE CALERA C.P. 98519 CALERA ZACATECAS MX | I72: XEXX010101000 | J72: JE | K72: Y04 | L72: C&S-INTERNAL-SWO-HJM-MX | M72: FLOW | N72: 1 | O72: 2 | P72: 1100-12C0005EN | Q72: C | R72: CB.12.ROTOR ASSY | S72: OVERMOLD ROTOR | T72: TT45ASA | U72: 50950079596 | W72: 17280 | X72: SEA | Y72: CIP | Z72: CIP | AA72: MANZANILLO | AB72: SHEKOU | AC72: MANZANILLO | AD72: 46083 | AE72: 46153 | AF72: 46090 | AG72: FGD-JCE | AH72: 6123118 | AI72: 46083 | AJ72: 46084 | AK72: 17280 | AL72: 34798 | AM72: 101513754407 | AN72: 46084 | AO72: 46084.447 | AP72: USD | AQ72: 0.30101 | AR72: 5201.45 | AS72: USD | AT72: 5201.45 | AU72: JOHN JH SHI | AV72: SHIPCO TRANSPORT-SEA-GEN | AW72: WAN HAI A16 V.E010 | AX72: 46089 | AY72: 46138 | AZ72: TGBU7107819 | BA72: 40HQ | BB72: 22145133 | BC72: 288 | BD72: KG | BE72: 13.2311 | BF72: 11.8161 | BG72: MM | BH72: 395 | BI72: 295 | BJ72: 160 | BK72: 60 | BL72: KG | BM72: 820.86384 | BN72: 708.96384 | BO72: 820.86384 | BP72: MM | BQ72: 1200 | BR72: 1000 | BS72: 1120 | BT72: 1 | BU72: 0 | BV72: 1 | BW72: 60 | BX72: 0 | BY72: 60 | BZ72: 17280 | CA72: 0 | CB72: 17280 | CC72: 708.96384 | CD72: C-PAL-146020 | CE72: C-BOX-001372 | CG72: JE IM OU | CN72: M19 | CO72: 1252-5YY0073EN | CP72: CSGU2004557 | CQ72: 103.9844 | CR72: =IFERROR(CQ72/(SUMIFS(CQ:CQ,CP:CP,CP72)),100%) -> 0.014377354 | CS72: =CR72*$CS$2 -> 35.943386
B73: M19 | C73: 1275402071 | F73: 34798 | G73: JOHNSON ELECTRIC NORTH AMERICA INC. | H73: Tax ID JEG120120DD4 BOULEVARD MORELOS NO. 1109 MEGA PARQUE INDUSTRIAL AEROPUERTO DE CALERA C.P. 98519 CALERA ZACATECAS MX | I73: XEXX010101000 | J73: JE | K73: Y03 | L73: C&S-INTERNAL-SWO-HJM-MX | M73: EXPORT | N73: 1 | O73: 7 | P73: 1330-5YY0182EN | Q73: C | R73: BZ.YY.HEAT SINK | S73: HEAT SINK 8191891(PLATING C4) | T73: TT45ASA | U73: 50950080247 | W73: 3840 | X73: SEA | Y73: CIP | Z73: CIP | AA73: MANZANILLO | AB73: SHEKOU | AC73: MANZANILLO | AD73: 46077 | AE73: 46111 | AF73: 46090 | AG73: FGD-JCE | AH73: 6122970 | AI73: 46083 | AJ73: 46084 | AK73: 3840 | AL73: 34798 | AM73: 101513754322 | AN73: 46084 | AO73: 46084.391 | AP73: USD | AQ73: 1.96204 | AR73: 7534.24 | AS73: USD | AT73: 7534.24 | AU73: JOHN JH SHI | AV73: SHIPCO TRANSPORT-SEA-GEN | AW73: WAN HAI A16 V.E010 | AX73: 46089 | AY73: 46138 | AZ73: FFAU1272834 | BA73: 40HQ | BB73: 22145132 | BC73: 16 | BD73: KG | BE73: 4.9545 | BF73: 3.7555 | BG73: MM | BH73: 495 | BI73: 395 | BJ73: 190 | BK73: 30 | BL73: KG | BM73: 175.635 | BN73: 112.665 | BO73: 1405.0848 | BP73: MM | BQ73: 1200 | BR73: 1000 | BS73: 1120 | BT73: 8 | BU73: 0 | BV73: 8 | BW73: 240 | BX73: 0 | BY73: 240 | BZ73: 3840 | CA73: 0 | CB73: 3840 | CC73: 901.3248 | CD73: C-PAL-146020 | CE73: C-BOX-001328 | CG73: JE IM OU | CN73: M19 | CO73: 1204-5YY0009-56EN | CP73: CSGU2004557 | CQ73: 73.17 | CR73: =IFERROR(CQ73/(SUMIFS(CQ:CQ,CP:CP,CP73)),100%) -> 0.010116816 | CS73: =CR73*$CS$2 -> 25.292039
B74: M19 | C74: 1275402073 | F74: 34798 | G74: JOHNSON ELECTRIC NORTH AMERICA INC. | H74: Tax ID JEG120120DD4 BOULEVARD MORELOS NO. 1109 MEGA PARQUE INDUSTRIAL AEROPUERTO DE CALERA C.P. 98519 CALERA ZACATECAS MX | I74: XEXX010101000 | J74: JE | K74: Y03 | L74: C&S-INTERNAL-SWO-HJM-MX | M74: FLOW | N74: 1 | O74: 2 | P74: 1330-5YY0183EN | Q74: B | R74: BZ.YY.HEAT SINK | S74: HEAT SINK 8191892(PLATING C4) | T74: TT45ASA | U74: 50950080248 | W74: 1440 | X74: SEA | Y74: CIP | Z74: CIP | AA74: MANZANILLO | AB74: SHEKOU | AC74: MANZANILLO | AD74: 46077 | AE74: 46111 | AF74: 46090 | AG74: FGD-JCE | AH74: 6122971 | AI74: 46083 | AJ74: 46084 | AK74: 1440 | AL74: 34798 | AM74: 101513754323 | AN74: 46084 | AO74: 46084.391 | AP74: USD | AQ74: 1.20448 | AR74: 1734.45 | AS74: USD | AT74: 1734.45 | AU74: JOHN JH SHI | AV74: SHIPCO TRANSPORT-SEA-GEN | AW74: WAN HAI A16 V.E010 | AX74: 46089 | AY74: 46138 | AZ74: FFAU1272834 | BA74: 40HQ | BB74: 22145132 | BC74: 48 | BD74: KG | BE74: 7.6899 | BF74: 6.2299 | BG74: MM | BH74: 495 | BI74: 395 | BJ74: 190 | BK74: 30 | BL74: KG | BM74: 257.6976 | BN74: 186.8976 | BO74: 257.6976 | BP74: MM | BQ74: 1200 | BR74: 1000 | BS74: 1120 | BT74: 1 | BU74: 0 | BV74: 1 | BW74: 30 | BX74: 0 | BY74: 30 | BZ74: 1440 | CA74: 0 | CB74: 1440 | CC74: 186.8976 | CD74: C-PAL-146020 | CE74: C-BOX-001329 | CG74: JE IM OU | CN74: M19 | CO74: 1101-5YY0361EN | CP74: CSGU2004557 | CQ74: 494.1865 | CR74: =IFERROR(CQ74/(SUMIFS(CQ:CQ,CP:CP,CP74)),100%) -> 0.068328464 | CS74: =CR74*$CS$2 -> 170.82116
B75: M19 | C75: 1275402099 | E75: Mexico PC Planner Assigned | F75: 34798 | G75: JOHNSON ELECTRIC NORTH AMERICA INC. | H75: Tax ID JEG120120DD4 BOULEVARD MORELOS NO. 1109 MEGA PARQUE INDUSTRIAL AEROPUERTO DE CALERA C.P. 98519 CALERA ZACATECAS MX | I75: XEXX010101000 | J75: JE | K75: Y03 | L75: C&S-INTERNAL-SWO-HJM-MX | M75: FLOW | N75: 1 | O75: 2 | P75: 1330-5YY0176EN | Q75: A | R75: BZ.YY.HEAT SINK | S75: HEAT SINK 8191849 (1330-5YY0176-C4EN) | T75: TT45ASA | U75: 50950080293 | W75: 2880 | X75: SEA | Y75: CIP | Z75: CIP | AA75: MANZANILLO | AB75: SHEKOU | AC75: MANZANILLO | AD75: 46077 | AE75: 46132 | AF75: 46090 | AG75: FGD-JCE | AH75: 6122972 | AI75: 46083 | AJ75: 46084 | AK75: 2880 | AL75: 34798 | AM75: 101513754320 | AN75: 46084 | AO75: 46084.391 | AP75: USD | AQ75: 1.15734 | AR75: 3333.14 | AS75: USD | AT75: 3333.14 | AU75: JOHN JH SHI | AV75: SHIPCO TRANSPORT-SEA-GEN | AW75: WAN HAI A16 V.E010 | AX75: 46089 | AY75: 46138 | AZ75: FFAU1272834 | BA75: 40HQ | BB75: 22145132 | BC75: 48 | BD75: KG | BE75: 8.2251 | BF75: 6.7651 | BG75: MM | BH75: 495 | BI75: 395 | BJ75: 190 | BK75: 30 | BL75: KG | BM75: 273.753 | BN75: 202.953 | BO75: 547.5072 | BP75: MM | BQ75: 1200 | BR75: 1000 | BS75: 1120 | BT75: 2 | BU75: 0 | BV75: 2 | BW75: 60 | BX75: 0 | BY75: 60 | BZ75: 2880 | CA75: 0 | CB75: 2880 | CC75: 405.9072 | CD75: C-PAL-146020 | CE75: C-BOX-001329 | CG75: JE IM OU | CN75: M19 | CO75: 1106-5YY0032EN | CP75: CSGU2004557 | CQ75: 198.3756 | CR75: =IFERROR(CQ75/(SUMIFS(CQ:CQ,CP:CP,CP75)),100%) -> 0.027428309 | CS75: =CR75*$CS$2 -> 68.570773
B76: M19 | C76: 1275402130 | F76: 34798 | G76: JOHNSON ELECTRIC NORTH AMERICA INC. | H76: Tax ID JEG120120DD4 BOULEVARD MORELOS NO. 1109 MEGA PARQUE INDUSTRIAL AEROPUERTO DE CALERA C.P. 98519 CALERA ZACATECAS MX | I76: XEXX010101000 | J76: JE | K76: Y03 | L76: C&S-INTERNAL-SWO-HJM-MX | M76: FLOW | N76: 1 | O76: 1 | P76: 1330-5YY0167EN | Q76: G | R76: BZ.YY.HEAT SINK | S76: HEAT SINK 8191836(1330-5YY0167-C4EN) | T76: TT45ASA | U76: 50950080324 | W76: 6720 | X76: SEA | Y76: CIP | Z76: CIP | AA76: MANZANILLO | AB76: SHEKOU | AC76: MANZANILLO | AD76: 46083 | AE76: 46132 | AF76: 46090 | AG76: FGD-JCE | AH76: 6122973 | AI76: 46083 | AJ76: 46084 | AK76: 6720 | AL76: 34798 | AM76: 101513754321 | AN76: 46084 | AO76: 46084.391 | AP76: USD | AQ76: 1.89248 | AR76: 12717.46 | AS76: USD | AT76: 12717.46 | AU76: JOHN JH SHI | AV76: SHIPCO TRANSPORT-SEA-GEN | AW76: WAN HAI A16 V.E010 | AX76: 46089 | AY76: 46138 | AZ76: FFAU1272834 | BA76: 40HQ | BB76: 22145132 | BC76: 16 | BD76: KG | BE76: 4.9409 | BF76: 3.7419 | BG76: MM | BH76: 495 | BI76: 395 | BJ76: 190 | BK76: 30 | BL76: KG | BM76: 175.227 | BN76: 112.257 | BO76: 2453.1864 | BP76: MM | BQ76: 1200 | BR76: 1000 | BS76: 1120 | BT76: 14 | BU76: 0 | BV76: 14 | BW76: 420 | BX76: 0 | BY76: 420 | BZ76: 6720 | CA76: 0 | CB76: 6720 | CC76: 1571.6064 | CD76: C-PAL-146020 | CE76: C-BOX-001328 | CG76: JE IM OU | CN76: M19 | CO76: 1140-5YY0004EN | CP76: CSGU2004557 | CQ76: 302.8792 | CR76: =IFERROR(CQ76/(SUMIFS(CQ:CQ,CP:CP,CP76)),100%) -> 0.04187745 | CS76: =CR76*$CS$2 -> 104.69363
B77: M01 | C77: 1275406540 | F77: 34798 | G77: JOHNSON ELECTRIC NORTH AMERICA INC. | H77: Tax ID JEG120120DD4 BOULEVARD MORELOS NO. 1109 MEGA PARQUE INDUSTRIAL AEROPUERTO DE CALERA C.P. 98519 CALERA ZACATECAS MX | I77: XEXX010101000 | J77: JE | K77: Y04 | L77: C&S-INTERNAL-SWO-HJM-MX | M77: FLOW | N77: 4 | O77: 1 | P77: 1277-1030069EN | Q77: E | R77: CE.300.CONNECTOR | S77: CONNECTOR | T77: TT45ASA | U77: 50950080792 | W77: 9600 | X77: SEA | Y77: CIP | Z77: CIP | AA77: MANZANILLO | AB77: SHEKOU | AC77: MANZANILLO | AD77: 46081 | AE77: 46132 | AF77: 46090 | AG77: FGD-JCE | AH77: 6123119 | AI77: 46083 | AJ77: 46084 | AK77: 9600 | AL77: 34798 | AM77: 101513754406 | AN77: 46084 | AO77: 46084.447 | AP77: USD | AQ77: 0.11833 | AR77: 1135.97 | AS77: USD | AT77: 1135.97 | AU77: JOHN JH SHI | AV77: SHIPCO TRANSPORT-SEA-GEN | AW77: WAN HAI A16 V.E010 | AX77: 46089 | AY77: 46138 | AZ77: TGBU7107819 | BA77: 40HQ | BB77: 22145133 | BC77: 320 | BD77: KG | BE77: 4.186 | BF77: 3.616 | BG77: MM | BH77: 395 | BI77: 295 | BJ77: 255 | BK77: 30 | BL77: KG | BM77: 152.58 | BN77: 108.48 | BO77: 152.58 | BP77: MM | BQ77: 1200 | BR77: 1000 | BS77: 918 | BT77: 1 | BU77: 0 | BV77: 1 | BW77: 30 | BX77: 0 | BY77: 30 | BZ77: 9600 | CA77: 0 | CB77: 9600 | CC77: 108.48 | CD77: C-PAL-522001 | CE77: C-BOX-233107 | CG77: JE IM OU | CN77: M19 | CO77: 1106-5YY0033EN | CP77: CSGU2004557 | CQ77: 164.1536 | CR77: =IFERROR(CQ77/(SUMIFS(CQ:CQ,CP:CP,CP77)),100%) -> 0.02269662 | CS77: =CR77*$CS$2 -> 56.741551
B78: M45 | C78: 1275406977 | F78: 34798 | G78: JOHNSON ELECTRIC NORTH AMERICA INC. | H78: Tax ID JEG120120DD4 BOULEVARD MORELOS NO. 1109 MEGA PARQUE INDUSTRIAL AEROPUERTO DE CALERA C.P. 98519 CALERA ZACATECAS MX | I78: XEXX010101000 | J78: JE | K78: Y04 | L78: C&S-INTERNAL-SWO-HJM-MX | M78: FLOW | N78: 1 | O78: 1 | P78: 1459-12C0018EN | Q78: A | R78: CB.200.COVER | S78: COVER | T78: TT45ASA | U78: 50950080931 | W78: 60480 | X78: SEA | Y78: CIP | Z78: CIP | AA78: MANZANILLO | AB78: SHEKOU | AC78: MANZANILLO | AD78: 46083 | AE78: 46153 | AF78: 46090 | AG78: FGD-JCE | AH78: 6123120 | AI78: 46083 | AJ78: 46084 | AK78: 60480 | AL78: 34798 | AM78: 101513754408 | AN78: 46084 | AO78: 46084.447 | AP78: USD | AQ78: 0.11709 | AR78: 7081.56 | AS78: USD | AT78: 7081.56 | AU78: JOHN JH SHI | AV78: SHIPCO TRANSPORT-SEA-GEN | AW78: WAN HAI A16 V.E010 | AX78: 46089 | AY78: 46138 | AZ78: TGBU7107819 | BA78: 40HQ | BB78: 22145133 | BC78: 280 | BD78: KG | BE78: 8.6921 | BF78: 7.1621 | BG78: MM | BH78: 595 | BI78: 495 | BJ78: 310 | BK78: 12 | BL78: KG | BM78: 131.3052 | BN78: 85.9452 | BO78: 2363.4979 | BP78: MM | BQ78: 1200 | BR78: 1000 | BS78: 1088 | BT78: 18 | BU78: 0 | BV78: 18 | BW78: 216 | BX78: 0 | BY78: 216 | BZ78: 60480 | CA78: 0 | CB78: 60480 | CC78: 1547.0179 | CD78: C-PAL-393001 | CE78: C-BOX-001402 | CG78: JE IM OU | CN78: M19 | CO78: 1106-5YY0031EN | CP78: CSGU2004557 | CQ78: 169.0112 | CR78: =IFERROR(CQ78/(SUMIFS(CQ:CQ,CP:CP,CP78)),100%) -> 0.023368254 | CS78: =CR78*$CS$2 -> 58.420636
B79: M19 | C79: 1275406998 | F79: 34798 | G79: JOHNSON ELECTRIC NORTH AMERICA INC. | H79: Tax ID JEG120120DD4 BOULEVARD MORELOS NO. 1109 MEGA PARQUE INDUSTRIAL AEROPUERTO DE CALERA C.P. 98519 CALERA ZACATECAS MX | I79: XEXX010101000 | J79: JE | K79: W04 | L79: C&S-INTERNAL-SWO-HJM-MX | M79: FLOW | N79: 1 | O79: 2 | P79: 1301-5YY0305EN0093 | Q79: C | R79: AA.YY.REAR HOUSING | S79: HOUSING 8030642 | T79: TT45ASA | U79: 50950080992 | W79: 4860 | X79: SEA | Y79: CIP | Z79: CIP | AA79: MANZANILLO | AB79: SHEKOU | AC79: MANZANILLO | AD79: 46081 | AE79: 46139 | AF79: 46090 | AG79: FGD-JCE | AH79: 6122974 | AI79: 46083 | AJ79: 46084 | AK79: 4860 | AL79: 34798 | AM79: 101513754318 | AN79: 46084 | AO79: 46084.391 | AP79: USD | AQ79: 1.37858 | AR79: 6699.9 | AS79: USD | AT79: 6699.9 | AU79: JOHN JH SHI | AV79: SHIPCO TRANSPORT-SEA-GEN | AW79: WAN HAI A16 V.E010 | AX79: 46089 | AY79: 46138 | AZ79: FFAU1272834 | BA79: 40HQ | BB79: 22145132 | BC79: 27 | BD79: KG | BE79: 14.8654 | BF79: 13.6374 | BG79: MM | BH79: 495 | BI79: 395 | BJ79: 170 | BK79: 30 | BL79: KG | BM79: 472.962 | BN79: 409.122 | BO79: 2837.7774 | BP79: MM | BQ79: 1200 | BR79: 1000 | BS79: 1000 | BT79: 6 | BU79: 0 | BV79: 6 | BW79: 180 | BX79: 0 | BY79: 180 | BZ79: 4860 | CA79: 0 | CB79: 4860 | CC79: 2454.7374 | CD79: C-PAL-518001 | CE79: C-BOX-001319 | CG79: JE IM OU | CN79: M19 | CO79: 1101-5YY0313EN | CP79: CSGU2004557 | CQ79: 287.38816 | CR79: =IFERROR(CQ79/(SUMIFS(CQ:CQ,CP:CP,CP79)),100%) -> 0.039735589 | CS79: =CR79*$CS$2 -> 99.338973
B80: M19 | C80: 1275407010 | F80: 34798 | G80: JOHNSON ELECTRIC NORTH AMERICA INC. | H80: Tax ID JEG120120DD4 BOULEVARD MORELOS NO. 1109 MEGA PARQUE INDUSTRIAL AEROPUERTO DE CALERA C.P. 98519 CALERA ZACATECAS MX | I80: XEXX010101000 | J80: JE | K80: W04 | L80: C&S-INTERNAL-SWO-HJM-MX | M80: FLOW | N80: 1 | O80: 1 | P80: 1301-5YY0306EN0093 | Q80: F | R80: AA.YY.REAR HOUSING | S80: HOUSING 8030645 | T80: TT45ASA | U80: 50950081005 | W80: 13068 | X80: SEA | Y80: CIP | Z80: CIP | AA80: MANZANILLO | AB80: SHEKOU | AC80: MANZANILLO | AD80: 46081 | AE80: 46139 | AF80: 46090 | AG80: FGD-JCE | AH80: 6122975 | AI80: 46083 | AJ80: 46084 | AK80: 13068 | AL80: 34798 | AM80: 101513754319 | AN80: 46084 | AO80: 46084.391 | AP80: USD | AQ80: 1.00054 | AR80: 13075.04 | AS80: USD | AT80: 13075.04 | AU80: JOHN JH SHI | AV80: SHIPCO TRANSPORT-SEA-GEN | AW80: WAN HAI A16 V.E010 | AX80: 46089 | AY80: 46138 | AZ80: FFAU1272834 | BA80: 40HQ | BB80: 22145132 | BC80: 33 | BD80: KG | BE80: 12.9557 | BF80: 12.0057 | BG80: MM | BH80: 495 | BI80: 395 | BJ80: 150 | BK80: 36 | BL80: KG | BM80: 493.4052 | BN80: 432.2052 | BO80: 5427.4691 | BP80: MM | BQ80: 1200 | BR80: 1000 | BS80: 1053 | BT80: 11 | BU80: 0 | BV80: 11 | BW80: 396 | BX80: 0 | BY80: 396 | BZ80: 13068 | CA80: 0 | CB80: 13068 | CC80: 4754.2691 | CD80: C-PAL-511001 | CE80: C-BOX-001343 | CG80: JE IM OU | CN80: M19 | CO80: 1250-5YY0031EN | CP80: CSGU2004557 | CQ80: 143.82 | CR80: =IFERROR(CQ80/(SUMIFS(CQ:CQ,CP:CP,CP80)),100%) -> 0.019885205 | CS80: =CR80*$CS$2 -> 49.713012
B81: M23 | C81: 1275377265 | F81: 34798 | G81: JOHNSON ELECTRIC NORTH AMERICA INC. | H81: Tax ID JEG120120DD4 BOULEVARD MORELOS NO. 1109 MEGA PARQUE INDUSTRIAL AEROPUERTO DE CALERA C.P. 98519 CALERA ZACATECAS MX | I81: XEXX010101000 | J81: JE | K81: W03 | L81: C&S-INTERNAL-SWO-HJM-MX | M81: FLOW | N81: 1 | O81: 6 | P81: 1346-1120062EN | Q81: C | R81: CE.12.BOBBIN | S81: BOBBIN(REAR) | T81: TT45ASA | U81: 50950076165 | W81: 6000 | X81: SEA | Y81: CIP | Z81: CIP | AA81: MANZANILLO | AB81: YANTIAN | AC81: MANZANILLO | AD81: 46080 | AE81: 46125 | AF81: 46091 | AG81: FGD-JCE | AH81: 6124744 | AI81: 46084 | AJ81: 46085 | AK81: 6000 | AL81: 34798 | AM81: 101513754751 | AN81: 46085 | AO81: 46085.452 | AP81: USD | AQ81: 0.26237 | AR81: 1574.22 | AS81: USD | AT81: 1574.22 | AU81: JOHN JH SHI | AV81: SHIPCO TRANSPORT-SEA-GEN | AW81: ZIM MOUNT BLANC V.12E | AX81: 46091 | AY81: 46140 | AZ81: JXLU4392928 | BA81: 40' | BB81: 22145170 | BC81: 200 | BD81: KG | BE81: 4.389 | BF81: 2.268 | BG81: MM | BH81: 395 | BI81: 295 | BJ81: 320 | BK81: 15 | BL81: KG | BM81: 92.835 | BN81: 34.02 | BO81: 185.67 | BP81: MM | BQ81: 1200 | BR81: 1000 | BS81: 1120 | BT81: 2 | BU81: 0 | BV81: 2 | BW81: 30 | BX81: 0 | BY81: 30 | BZ81: 6000 | CA81: 0 | CB81: 6000 | CC81: 68.04 | CD81: C-PAL-349002 | CE81: C-BOX-474271 | CG81: JE IM OU | CN81: M19 | CO81: 1326-5YY0082EN | CP81: CSGU2004557 | CQ81: 66.9472 | CR81: =IFERROR(CQ81/(SUMIFS(CQ:CQ,CP:CP,CP81)),100%) -> 0.0092564232 | CS81: =CR81*$CS$2 -> 23.141058
B82: M23 | C82: 1275377292 | F82: 34798 | G82: JOHNSON ELECTRIC NORTH AMERICA INC. | H82: Tax ID JEG120120DD4 BOULEVARD MORELOS NO. 1109 MEGA PARQUE INDUSTRIAL AEROPUERTO DE CALERA C.P. 98519 CALERA ZACATECAS MX | I82: XEXX010101000 | J82: JE | K82: Y04 | L82: C&S-INTERNAL-SWO-HJM-MX | M82: FLOW | N82: 1 | O82: 10 | P82: 1301-1120169EN | Q82: D | R82: CB.11.HOUSING | S82: HOUSING(BARE PART) | T82: TT45ASA | U82: 50950076250 | W82: 1200 | X82: SEA | Y82: CIP | Z82: CIP | AA82: MANZANILLO | AB82: YANTIAN | AC82: MANZANILLO | AD82: 46083 | AE82: 46118 | AF82: 46091 | AG82: FGD-JCE | AH82: 6124745 | AI82: 46084 | AJ82: 46085 | AK82: 1200 | AL82: 34798 | AM82: 101513754750 | AN82: 46085 | AO82: 46085.452 | AP82: USD | AQ82: 1.03729 | AR82: 1244.75 | AS82: USD | AT82: 1244.75 | AU82: JOHN JH SHI | AV82: SHIPCO TRANSPORT-SEA-GEN | AW82: ZIM MOUNT BLANC V.12E | AX82: 46091 | AY82: 46140 | AZ82: JXLU4392928 | BA82: 40' | BB82: 22145170 | BC82: 40 | BD82: KG | BE82: 4.4851 | BF82: 3.3351 | BG82: MM | BH82: 495 | BI82: 395 | BJ82: 1800 | BK82: 30 | BL82: KG | BM82: 161.5536 | BN82: 100.0536 | BO82: 161.5536 | BP82: MM | BQ82: 1200 | BR82: 1000 | BS82: 1058 | BT82: 1 | BU82: 0 | BV82: 1 | BW82: 30 | BX82: 0 | BY82: 30 | BZ82: 1200 | CA82: 0 | CB82: 1200 | CC82: 100.0536 | CD82: C-PAL-387001 | CE82: C-BOX-474272 | CG82: JE IM OU | CN82: M23 | CO82: 1415-1060749EN | CP82: CSGU2004557 | CQ82: 228.0256 | CR82: =IFERROR(CQ82/(SUMIFS(CQ:CQ,CP:CP,CP82)),100%) -> 0.031527853 | CS82: =CR82*$CS$2 -> 78.819631
B83: M23 | C83: 1275377292 | F83: 34798 | G83: JOHNSON ELECTRIC NORTH AMERICA INC. | H83: Tax ID JEG120120DD4 BOULEVARD MORELOS NO. 1109 MEGA PARQUE INDUSTRIAL AEROPUERTO DE CALERA C.P. 98519 CALERA ZACATECAS MX | I83: XEXX010101000 | J83: JE | K83: Y04 | L83: C&S-INTERNAL-SWO-HJM-MX | M83: FLOW | N83: 1 | O83: 11 | P83: 1301-1120169EN | Q83: D | R83: CB.11.HOUSING | S83: HOUSING(BARE PART) | T83: TT45ASA | U83: 50950076250 | W83: 4800 | X83: SEA | Y83: CIP | Z83: CIP | AA83: MANZANILLO | AB83: YANTIAN | AC83: MANZANILLO | AD83: 46083 | AE83: 46118 | AF83: 46091 | AG83: FGD-JCE | AH83: 6124745 | AI83: 46084 | AJ83: 46085 | AK83: 4800 | AL83: 34798 | AM83: 101513754750 | AN83: 46085 | AO83: 46085.452 | AP83: USD | AQ83: 1.03729 | AR83: 4979 | AS83: USD | AT83: 4979 | AU83: JOHN JH SHI | AV83: SHIPCO TRANSPORT-SEA-GEN | AW83: ZIM MOUNT BLANC V.12E | AX83: 46091 | AY83: 46140 | AZ83: JXLU4392928 | BA83: 40' | BB83: 22145170 | BC83: 40 | BD83: KG | BE83: 4.4851 | BF83: 3.3351 | BG83: MM | BH83: 495 | BI83: 395 | BJ83: 1800 | BK83: 30 | BL83: KG | BM83: 161.553 | BN83: 100.053 | BO83: 646.2144 | BP83: MM | BQ83: 1200 | BR83: 1000 | BS83: 1058 | BT83: 4 | BU83: 0 | BV83: 4 | BW83: 120 | BX83: 0 | BY83: 120 | BZ83: 4800 | CA83: 0 | CB83: 4800 | CC83: 400.2144 | CD83: C-PAL-387001 | CE83: C-BOX-474272 | CG83: JE IM OU | CN83: M46 | CO83: 1202-1060393EN | CP83: CSGU2004557 | CQ83: 32.9338 | CR83: =IFERROR(CQ83/(SUMIFS(CQ:CQ,CP:CP,CP83)),100%) -> 0.0045535764 | CS83: =CR83*$CS$2 -> 11.383941
B84: M45 | C84: 1275391619 | F84: 34798 | G84: JOHNSON ELECTRIC NORTH AMERICA INC. | H84: Tax ID JEG120120DD4 BOULEVARD MORELOS NO. 1109 MEGA PARQUE INDUSTRIAL AEROPUERTO DE CALERA C.P. 98519 CALERA ZACATECAS MX | I84: XEXX010101000 | J84: JE | K84: Y04 | L84: C&S-INTERNAL-SWO-HJM-MX | M84: FLOW | N84: 1 | O84: 2 | P84: 1301-12C0022EN | Q84: B | R84: CB.600.REAR HOUSING | S84: HOUSING(SEAL OVERMOLD) | T84: TT45ASA | U84: 50950078837 | W84: 35200 | X84: SEA | Y84: CIP | Z84: CIP | AA84: MANZANILLO | AB84: YANTIAN | AC84: MANZANILLO | AD84: 46081 | AE84: 46132 | AF84: 46091 | AG84: FGD-JCE | AH84: 6124746 | AI84: 46084 | AJ84: 46085 | AK84: 35200 | AL84: 34798 | AM84: 101513754760 | AN84: 46085 | AO84: 46085.452 | AP84: USD | AQ84: 0.11867 | AR84: 4177.15 | AS84: USD | AT84: 4177.15 | AU84: JOHN JH SHI | AV84: SHIPCO TRANSPORT-SEA-GEN | AW84: ZIM MOUNT BLANC V.12E | AX84: 46091 | AY84: 46140 | AZ84: JXLU4392928 | BA84: 40' | BB84: 22145170 | BC84: 160 | BD84: KG | BE84: 6.3452 | BF84: 4.7952 | BG84: MM | BH84: 595 | BI84: 495 | BJ84: 190 | BK84: 20 | BL84: KG | BM84: 153.904 | BN84: 95.904 | BO84: 1692.944 | BP84: MM | BQ84: 1200 | BR84: 1000 | BS84: 1110 | BT84: 11 | BU84: 0 | BV84: 11 | BW84: 220 | BX84: 0 | BY84: 220 | BZ84: 35200 | CA84: 0 | CB84: 35200 | CC84: 1054.944 | CD84: C-PAL-294062 | CE84: C-BOX-001437 | CG84: JE IM OU | CN84: M01 | CO84: 1202-1030350EN | CP84: CSGU2004557 | CQ84: 196.8768 | CR84: =IFERROR(CQ84/(SUMIFS(CQ:CQ,CP:CP,CP84)),100%) -> 0.027221078 | CS84: =CR84*$CS$2 -> 68.052696
B85: M45 | C85: 1275391774 | F85: 34798 | G85: JOHNSON ELECTRIC NORTH AMERICA INC. | H85: Tax ID JEG120120DD4 BOULEVARD MORELOS NO. 1109 MEGA PARQUE INDUSTRIAL AEROPUERTO DE CALERA C.P. 98519 CALERA ZACATECAS MX | I85: XEXX010101000 | J85: JE | K85: Y04 | L85: C&S-INTERNAL-SWO-HJM-MX | M85: FLOW | N85: 1 | O85: 1 | P85: 1346-12C0011EN | Q85: E | R85: CB.SP63.BOBBIN | S85: BOBBIN | T85: TT45ASA | U85: 50950078820 | W85: 13200 | X85: SEA | Y85: CIP | Z85: CIP | AA85: MANZANILLO | AB85: YANTIAN | AC85: MANZANILLO | AD85: 46083 | AE85: 46167 | AF85: 46091 | AG85: FGD-JCE | AH85: 6124747 | AI85: 46084 | AJ85: 46085 | AK85: 13200 | AL85: 34798 | AM85: 101513754752 | AN85: 46085 | AO85: 46085.452 | AP85: USD | AQ85: 0.19572 | AR85: 2583.5 | AS85: USD | AT85: 2583.5 | AU85: JOHN JH SHI | AV85: SHIPCO TRANSPORT-SEA-GEN | AW85: ZIM MOUNT BLANC V.12E | AX85: 46091 | AY85: 46140 | AZ85: JXLU4392928 | BA85: 40' | BB85: 22145170 | BC85: 264 | BD85: KG | BE85: 5.2204 | BF85: 3.8304 | BG85: MM | BH85: 595 | BI85: 395 | BJ85: 175 | BK85: 25 | BL85: KG | BM85: 157.51 | BN85: 95.76 | BO85: 315.0188 | BP85: MM | BQ85: 1200 | BR85: 1000 | BS85: 1035 | BT85: 2 | BU85: 0 | BV85: 2 | BW85: 50 | BX85: 0 | BY85: 50 | BZ85: 13200 | CA85: 0 | CB85: 13200 | CC85: 191.5188 | CD85: C-PAL-293001 | CE85: C-BOX-001404 | CG85: JE IM OU | CN85: M01 | CO85: 1101-0037350EN | CP85: CSGU2004557 | CQ85: 351.31 | CR85: =IFERROR(CQ85/(SUMIFS(CQ:CQ,CP:CP,CP85)),100%) -> 0.048573712 | CS85: =CR85*$CS$2 -> 121.43428
B86: M19 | C86: 1275402073 | F86: 34798 | G86: JOHNSON ELECTRIC NORTH AMERICA INC. | H86: Tax ID JEG120120DD4 BOULEVARD MORELOS NO. 1109 MEGA PARQUE INDUSTRIAL AEROPUERTO DE CALERA C.P. 98519 CALERA ZACATECAS MX | I86: XEXX010101000 | J86: JE | K86: Y03 | L86: C&S-INTERNAL-SWO-HJM-MX | M86: FLOW | N86: 1 | O86: 8 | P86: 1330-5YY0183EN | Q86: B | R86: BZ.YY.HEAT SINK | S86: HEAT SINK 8191892(PLATING C4) | T86: TT45ASA | U86: 50950080248 | W86: 5760 | X86: SEA | Y86: CIP | Z86: CIP | AA86: MANZANILLO | AB86: YANTIAN | AC86: MANZANILLO | AD86: 46077 | AE86: 46111 | AF86: 46091 | AG86: FGD-JCE | AH86: 6124748 | AI86: 46084 | AJ86: 46085 | AK86: 5760 | AL86: 34798 | AM86: 101513754757 | AN86: 46085 | AO86: 46085.452 | AP86: USD | AQ86: 1.20448 | AR86: 6937.8 | AS86: USD | AT86: 6937.8 | AU86: JOHN JH SHI | AV86: SHIPCO TRANSPORT-SEA-GEN | AW86: ZIM MOUNT BLANC V.12E | AX86: 46091 | AY86: 46140 | AZ86: JXLU4392928 | BA86: 40' | BB86: 22145170 | BC86: 48 | BD86: KG | BE86: 7.6899 | BF86: 6.2299 | BG86: MM | BH86: 495 | BI86: 395 | BJ86: 190 | BK86: 30 | BL86: KG | BM86: 257.697 | BN86: 186.897 | BO86: 1030.7904 | BP86: MM | BQ86: 1200 | BR86: 1000 | BS86: 1120 | BT86: 4 | BU86: 0 | BV86: 4 | BW86: 120 | BX86: 0 | BY86: 120 | BZ86: 5760 | CA86: 0 | CB86: 5760 | CC86: 747.5904 | CD86: C-PAL-146020 | CE86: C-BOX-001329 | CG86: JE IM OU | CN86: M01 | CO86: 1308-0033550EN | CP86: CSGU2004557 | CQ86: 141.044 | CR86: =IFERROR(CQ86/(SUMIFS(CQ:CQ,CP:CP,CP86)),100%) -> 0.019501382 | CS86: =CR86*$CS$2 -> 48.753456
B87: M19 | C87: 1275402099 | E87: Mexico PC Planner Assigned | F87: 34798 | G87: JOHNSON ELECTRIC NORTH AMERICA INC. | H87: Tax ID JEG120120DD4 BOULEVARD MORELOS NO. 1109 MEGA PARQUE INDUSTRIAL AEROPUERTO DE CALERA C.P. 98519 CALERA ZACATECAS MX | I87: XEXX010101000 | J87: JE | K87: Y03 | L87: C&S-INTERNAL-SWO-HJM-MX | M87: FLOW | N87: 1 | O87: 3 | P87: 1330-5YY0176EN | Q87: A | R87: BZ.YY.HEAT SINK | S87: HEAT SINK 8191849 (1330-5YY0176-C4EN) | T87: TT45ASA | U87: 50950080293 | W87: 1440 | X87: SEA | Y87: CIP | Z87: CIP | AA87: MANZANILLO | AB87: YANTIAN | AC87: MANZANILLO | AD87: 46077 | AE87: 46132 | AF87: 46091 | AG87: FGD-JCE | AH87: 6124749 | AI87: 46084 | AJ87: 46085 | AK87: 1440 | AL87: 34798 | AM87: 101513754761 | AN87: 46085 | AO87: 46085.452 | AP87: USD | AQ87: 1.15734 | AR87: 1666.57 | AS87: USD | AT87: 1666.57 | AU87: JOHN JH SHI | AV87: SHIPCO TRANSPORT-SEA-GEN | AW87: ZIM MOUNT BLANC V.12E | AX87: 46091 | AY87: 46140 | AZ87: JXLU4392928 | BA87: 40' | BB87: 22145170 | BC87: 48 | BD87: KG | BE87: 8.2251 | BF87: 6.7651 | BG87: MM | BH87: 495 | BI87: 395 | BJ87: 190 | BK87: 30 | BL87: KG | BM87: 273.7536 | BN87: 202.9536 | BO87: 273.7536 | BP87: MM | BQ87: 1200 | BR87: 1000 | BS87: 1120 | BT87: 1 | BU87: 0 | BV87: 1 | BW87: 30 | BX87: 0 | BY87: 30 | BZ87: 1440 | CA87: 0 | CB87: 1440 | CC87: 202.9536 | CD87: C-PAL-146020 | CE87: C-BOX-001329 | CG87: JE IM OU | CN87: M01 | CO87: 1110-0035030EN | CP87: CSGU2004557 | CQ87: 13.156 | CR87: =IFERROR(CQ87/(SUMIFS(CQ:CQ,CP:CP,CP87)),100%) -> 0.0018190082 | CS87: =CR87*$CS$2 -> 4.5475204
B88: M19 | C88: 1275402131 | F88: 34798 | G88: JOHNSON ELECTRIC NORTH AMERICA INC. | H88: Tax ID JEG120120DD4 BOULEVARD MORELOS NO. 1109 MEGA PARQUE INDUSTRIAL AEROPUERTO DE CALERA C.P. 98519 CALERA ZACATECAS MX | I88: XEXX010101000 | J88: JE | K88: Y03 | L88: C&S-INTERNAL-SWO-HJM-MX | M88: FLOW | N88: 1 | O88: 1 | P88: 1330-5YY0182EN | Q88: C | R88: BZ.YY.HEAT SINK | S88: HEAT SINK 8191891(PLATING C4) | T88: TT45ASA | U88: 50950080325 | W88: 480 | X88: SEA | Y88: CIP | Z88: CIP | AA88: MANZANILLO | AB88: YANTIAN | AC88: MANZANILLO | AD88: 46081 | AE88: 46118 | AF88: 46091 | AG88: FGD-JCE | AH88: 6124750 | AI88: 46084 | AJ88: 46085 | AK88: 480 | AL88: 34798 | AM88: 101513754756 | AN88: 46085 | AO88: 46085.452 | AP88: USD | AQ88: 1.96204 | AR88: 941.78 | AS88: USD | AT88: 941.78 | AU88: JOHN JH SHI | AV88: SHIPCO TRANSPORT-SEA-GEN | AW88: ZIM MOUNT BLANC V.12E | AX88: 46091 | AY88: 46140 | AZ88: JXLU4392928 | BA88: 40' | BB88: 22145170 | BC88: 16 | BD88: KG | BE88: 4.9545 | BF88: 3.7555 | BG88: MM | BH88: 495 | BI88: 395 | BJ88: 190 | BK88: 30 | BL88: KG | BM88: 175.6356 | BN88: 112.6656 | BO88: 175.6356 | BP88: MM | BQ88: 1200 | BR88: 1000 | BS88: 1120 | BT88: 1 | BU88: 0 | BV88: 1 | BW88: 30 | BX88: 0 | BY88: 30 | BZ88: 480 | CA88: 0 | CB88: 480 | CC88: 112.6656 | CD88: C-PAL-146020 | CE88: C-BOX-001328 | CG88: JE IM OU | CN88: M01 | CO88: 1202-1030170-71EN | CP88: CSGU2004557 | CQ88: 28.522 | CR88: =IFERROR(CQ88/(SUMIFS(CQ:CQ,CP:CP,CP88)),100%) -> 0.0039435809 | CS88: =CR88*$CS$2 -> 9.8589524
B89: M19 | C89: 1275402149 | F89: 34798 | G89: JOHNSON ELECTRIC NORTH AMERICA INC. | H89: Tax ID JEG120120DD4 BOULEVARD MORELOS NO. 1109 MEGA PARQUE INDUSTRIAL AEROPUERTO DE CALERA C.P. 98519 CALERA ZACATECAS MX | I89: XEXX010101000 | J89: JE | K89: Y03 | L89: C&S-INTERNAL-SWO-HJM-MX | M89: FLOW | N89: 1 | O89: 2 | P89: 1330-5YY0168EN | Q89: A | R89: BZ.YY.HEAT SINK | S89: HEAT SHIELD 8191837(1330-5YY0168-C4EN) | T89: TT45ASA | U89: 50950080367 | W89: 5760 | X89: SEA | Y89: CIP | Z89: CIP | AA89: MANZANILLO | AB89: YANTIAN | AC89: MANZANILLO | AD89: 46077 | AE89: 46132 | AF89: 46091 | AG89: FGD-JCE | AH89: 6124751 | AI89: 46084 | AJ89: 46085 | AK89: 5760 | AL89: 34798 | AM89: 101513754755 | AN89: 46085 | AO89: 46085.452 | AP89: USD | AQ89: 1.09377 | AR89: 6300.12 | AS89: USD | AT89: 6300.12 | AU89: JOHN JH SHI | AV89: SHIPCO TRANSPORT-SEA-GEN | AW89: ZIM MOUNT BLANC V.12E | AX89: 46091 | AY89: 46140 | AZ89: JXLU4392928 | BA89: 40' | BB89: 22145170 | BC89: 48 | BD89: KG | BE89: 7.6664 | BF89: 6.2064 | BG89: MM | BH89: 495 | BI89: 395 | BJ89: 190 | BK89: 30 | BL89: KG | BM89: 256.992 | BN89: 186.192 | BO89: 1027.968 | BP89: MM | BQ89: 1200 | BR89: 1000 | BS89: 1120 | BT89: 4 | BU89: 0 | BV89: 4 | BW89: 120 | BX89: 0 | BY89: 120 | BZ89: 5760 | CA89: 0 | CB89: 5760 | CC89: 744.768 | CD89: C-PAL-146020 | CE89: C-BOX-001329 | CG89: JE IM OU | CN89: M19 | CO89: 1101-5YY0353EN | CP89: CSGU2004557 | CQ89: 110.55603 | CR89: =IFERROR(CQ89/(SUMIFS(CQ:CQ,CP:CP,CP89)),100%) -> 0.015285978 | CS89: =CR89*$CS$2 -> 38.214945
B90: M01 | C90: 1275402803 | F90: 34798 | G90: JOHNSON ELECTRIC NORTH AMERICA INC. | H90: Tax ID JEG120120DD4 BOULEVARD MORELOS NO. 1109 MEGA PARQUE INDUSTRIAL AEROPUERTO DE CALERA C.P. 98519 CALERA ZACATECAS MX | I90: XEXX010101000 | J90: JE | K90: Y04 | L90: C&S-INTERNAL-SWO-HJM-MX | M90: FLOW | N90: 1 | O90: 1 | P90: 1277-1030115EN | Q90: A | R90: CE.300.CONNECTOR | S90: CONNECTOR | T90: TT45ASA | U90: 50950080457 | W90: 7000 | X90: SEA | Y90: CIP | Z90: CIP | AA90: MANZANILLO | AB90: YANTIAN | AC90: MANZANILLO | AD90: 46081 | AE90: 46139 | AF90: 46091 | AG90: FGD-JCE | AH90: 6124752 | AI90: 46084 | AJ90: 46085 | AK90: 7000 | AL90: 34798 | AM90: 101513754762 | AN90: 46085 | AO90: 46085.452 | AP90: USD | AQ90: 0.11308 | AR90: 791.56 | AS90: USD | AT90: 791.56 | AU90: JOHN JH SHI | AV90: SHIPCO TRANSPORT-SEA-GEN | AW90: ZIM MOUNT BLANC V.12E | AX90: 46091 | AY90: 46140 | AZ90: JXLU4392928 | BA90: 40' | BB90: 22145170 | BC90: 1400 | BD90: KG | BE90: 10.201 | BF90: 9.331 | BG90: MM | BH90: 595 | BI90: 395 | BJ90: 190 | BK90: 25 | BL90: KG | BM90: 78.005 | BN90: 46.655 | BO90: 78.005 | BP90: MM | BQ90: 1200 | BR90: 1000 | BS90: 1088 | BT90: 0 | BU90: 1 | BV90: 1 | BW90: 5 | BX90: 0 | BY90: 5 | BZ90: 0 | CA90: 7000 | CB90: 7000 | CC90: 46.655 | CD90: C-PAL-393001 | CE90: C-BOX-001312 | CG90: JE IM OU | CN90: MCS | CO90: 1209-5YY0496EN | CP90: CSGU2004557 | CQ90: 84.926 | CR90: =IFERROR(CQ90/(SUMIFS(CQ:CQ,CP:CP,CP90)),100%) -> 0.011742254 | CS90: =CR90*$CS$2 -> 29.355634
B91: M01 | C91: 1275402856 | F91: 34798 | G91: JOHNSON ELECTRIC NORTH AMERICA INC. | H91: Tax ID JEG120120DD4 BOULEVARD MORELOS NO. 1109 MEGA PARQUE INDUSTRIAL AEROPUERTO DE CALERA C.P. 98519 CALERA ZACATECAS MX | I91: XEXX010101000 | J91: JE | K91: Y04 | L91: C&S-INTERNAL-SWO-HJM-MX | M91: FLOW | N91: 1 | O91: 2 | P91: 1201-1030400EN | Q91: F | R91: CE.300.END CAP | S91: END CAP (TERMINAL HOUSING) | T91: TT45ASA | U91: 50950080539 | W91: 28000 | X91: SEA | Y91: CIP | Z91: CIP | AA91: MANZANILLO | AB91: YANTIAN | AC91: MANZANILLO | AD91: 46081 | AE91: 46097 | AF91: 46091 | AG91: FGD-JCE | AH91: 6124753 | AI91: 46084 | AJ91: 46085 | AK91: 28000 | AL91: 34798 | AM91: 101513754758 | AN91: 46085 | AO91: 46085.452 | AP91: USD | AQ91: 0.11025 | AR91: 3087 | AS91: USD | AT91: 3087 | AU91: JOHN JH SHI | AV91: SHIPCO TRANSPORT-SEA-GEN | AW91: ZIM MOUNT BLANC V.12E | AX91: 46091 | AY91: 46140 | AZ91: JXLU4392928 | BA91: 40' | BB91: 22145170 | BC91: 1400 | BD91: KG | BE91: 9.8622 | BF91: 8.9922 | BG91: MM | BH91: 595 | BI91: 395 | BJ91: 190 | BK91: 25 | BL91: KG | BM91: 224.244 | BN91: 179.844 | BO91: 224.244 | BP91: MM | BQ91: 1200 | BR91: 1000 | BS91: 1088 | BT91: 0 | BU91: 1 | BV91: 1 | BW91: 20 | BX91: 0 | BY91: 20 | BZ91: 0 | CA91: 28000 | CB91: 28000 | CC91: 179.844 | CD91: C-PAL-393001 | CE91: C-BOX-001312 | CG91: JE IM OU | CN91: M19 | CO91: 1202-5YY0024-76EN | CP91: CSGU2004557 | CQ91: 116.29415 | CR91: =IFERROR(CQ91/(SUMIFS(CQ:CQ,CP:CP,CP91)),100%) -> 0.016079356 | CS91: =CR91*$CS$2 -> 40.19839
B92: M01 | C92: 1275402859 | F92: 34798 | G92: JOHNSON ELECTRIC NORTH AMERICA INC. | H92: Tax ID JEG120120DD4 BOULEVARD MORELOS NO. 1109 MEGA PARQUE INDUSTRIAL AEROPUERTO DE CALERA C.P. 98519 CALERA ZACATECAS MX | I92: XEXX010101000 | J92: JE | K92: Y04 | L92: C&S-INTERNAL-SWO-HJM-MX | M92: FLOW | N92: 1 | O92: 1 | P92: 1426-1030015EN | Q92: C | R92: CB.300.VALVE | S92: PRESSURE VALVES | T92: TT45ASA | U92: 50950080544 | W92: 24000 | X92: SEA | Y92: CIP | Z92: CIP | AA92: MANZANILLO | AB92: YANTIAN | AC92: MANZANILLO | AD92: 46081 | AE92: 46139 | AF92: 46091 | AG92: FGD-JCE | AH92: 6124754 | AI92: 46084 | AJ92: 46085 | AK92: 24000 | AL92: 34798 | AM92: 101513754763 | AN92: 46085 | AO92: 46085.452 | AP92: USD | AQ92: 0.04286 | AR92: 1028.64 | AS92: USD | AT92: 1028.64 | AU92: JOHN JH SHI | AV92: SHIPCO TRANSPORT-SEA-GEN | AW92: ZIM MOUNT BLANC V.12E | AX92: 46091 | AY92: 46140 | AZ92: JXLU4392928 | BA92: 40' | BB92: 22145170 | BC92: 600 | BD92: KG | BE92: 4.8836 | BF92: 3.9726 | BG92: MM | BH92: 395 | BI92: 295 | BJ92: 270 | BK92: 30 | BL92: KG | BM92: 173.508 | BN92: 119.178 | BO92: 249.344 | BP92: MM | BQ92: 1200 | BR92: 1000 | BS92: 984 | BT92: 1 | BU92: 1 | BV92: 2 | BW92: 40 | BX92: 0 | BY92: 40 | BZ92: 18000 | CA92: 6000 | CB92: 24000 | CC92: 158.904 | CD92: C-PAL-392001 | CE92: C-BOX-594110 | CG92: JE IM OU | CN92: M19 | CO92: 1140-5YY0004EN | CP92: CSGU2004557 | CQ92: 302.8792 | CR92: =IFERROR(CQ92/(SUMIFS(CQ:CQ,CP:CP,CP92)),100%) -> 0.04187745 | CS92: =CR92*$CS$2 -> 104.69363
B93: M45 | C93: 1275406928 | F93: 34798 | G93: JOHNSON ELECTRIC NORTH AMERICA INC. | H93: Tax ID JEG120120DD4 BOULEVARD MORELOS NO. 1109 MEGA PARQUE INDUSTRIAL AEROPUERTO DE CALERA C.P. 98519 CALERA ZACATECAS MX | I93: XEXX010101000 | J93: JE | K93: Y04 | L93: C&S-INTERNAL-SWO-HJM-MX | M93: FLOW | N93: 1 | O93: 1 | P93: 1484-12C0012EN | Q93: A | R93: CB.300.IMPELLER | S93: IMPELLER | T93: TT45ASA | U93: 50950080944 | W93: 60000 | X93: SEA | Y93: CIP | Z93: CIP | AA93: MANZANILLO | AB93: YANTIAN | AC93: MANZANILLO | AD93: 46083 | AE93: 46160 | AF93: 46091 | AG93: FGD-JCE | AH93: 6124755 | AI93: 46084 | AJ93: 46085 | AK93: 60000 | AL93: 34798 | AM93: 101513754753 | AN93: 46085 | AO93: 46085.452 | AP93: USD | AQ93: 0.06123 | AR93: 3673.8 | AS93: USD | AT93: 3673.8 | AU93: JOHN JH SHI | AV93: SHIPCO TRANSPORT-SEA-GEN | AW93: ZIM MOUNT BLANC V.12E | AX93: 46091 | AY93: 46140 | AZ93: JXLU4392928 | BA93: 40' | BB93: 22145170 | BC93: 1200 | BD93: KG | BE93: 7.068 | BF93: 6.198 | BG93: MM | BH93: 595 | BI93: 395 | BJ93: 190 | BK93: 25 | BL93: KG | BM93: 203.7 | BN93: 154.95 | BO93: 407.4 | BP93: MM | BQ93: 1200 | BR93: 1000 | BS93: 1088 | BT93: 2 | BU93: 0 | BV93: 2 | BW93: 50 | BX93: 0 | BY93: 50 | BZ93: 60000 | CA93: 0 | CB93: 60000 | CC93: 309.9 | CD93: C-PAL-393001 | CE93: C-BOX-001312 | CG93: JE IM OU | CN93: MCS | CO93: 1209-5YY0465EN | CP93: CSGU2004557 | CQ93: 88.25536 | CR93: =IFERROR(CQ93/(SUMIFS(CQ:CQ,CP:CP,CP93)),100%) -> 0.012202586 | CS93: =CR93*$CS$2 -> 30.506465
B94: M19 | C94: 1275407010 | F94: 34798 | G94: JOHNSON ELECTRIC NORTH AMERICA INC. | H94: Tax ID JEG120120DD4 BOULEVARD MORELOS NO. 1109 MEGA PARQUE INDUSTRIAL AEROPUERTO DE CALERA C.P. 98519 CALERA ZACATECAS MX | I94: XEXX010101000 | J94: JE | K94: W04 | L94: C&S-INTERNAL-SWO-HJM-MX | M94: FLOW | N94: 1 | O94: 2 | P94: 1301-5YY0306EN0093 | Q94: F | R94: AA.YY.REAR HOUSING | S94: HOUSING 8030645 | T94: TT45ASA | U94: 50950081005 | W94: 8316 | X94: SEA | Y94: CIP | Z94: CIP | AA94: MANZANILLO | AB94: YANTIAN | AC94: MANZANILLO | AD94: 46081 | AE94: 46139 | AF94: 46091 | AG94: FGD-JCE | AH94: 6124756 | AI94: 46084 | AJ94: 46085 | AK94: 8316 | AL94: 34798 | AM94: 101513754754 | AN94: 46085 | AO94: 46085.452 | AP94: USD | AQ94: 1.00054 | AR94: 8320.48 | AS94: USD | AT94: 8320.48 | AU94: JOHN JH SHI | AV94: SHIPCO TRANSPORT-SEA-GEN | AW94: ZIM MOUNT BLANC V.12E | AX94: 46091 | AY94: 46140 | AZ94: JXLU4392928 | BA94: 40' | BB94: 22145170 | BC94: 33 | BD94: KG | BE94: 12.9557 | BF94: 12.0057 | BG94: MM | BH94: 495 | BI94: 395 | BJ94: 150 | BK94: 36 | BL94: KG | BM94: 493.4052 | BN94: 432.2052 | BO94: 3453.844 | BP94: MM | BQ94: 1200 | BR94: 1000 | BS94: 1053 | BT94: 7 | BU94: 0 | BV94: 7 | BW94: 252 | BX94: 0 | BY94: 252 | BZ94: 8316 | CA94: 0 | CB94: 8316 | CC94: 3025.444 | CD94: C-PAL-511001 | CE94: C-BOX-001343 | CG94: JE IM OU | CN94: MCS | CO94: 1209-5YY0494EN | CP94: CSGU2004557 | CQ94: 120.66816 | CR94: =IFERROR(CQ94/(SUMIFS(CQ:CQ,CP:CP,CP94)),100%) -> 0.016684127 | CS94: =CR94*$CS$2 -> 41.710316
B95: M19 | C95: 1275409419 | E95: Mexico PC Planner Assigned | F95: 34798 | G95: JOHNSON ELECTRIC NORTH AMERICA INC. | H95: Tax ID JEG120120DD4 BOULEVARD MORELOS NO. 1109 MEGA PARQUE INDUSTRIAL AEROPUERTO DE CALERA C.P. 98519 CALERA ZACATECAS MX | I95: XEXX010101000 | J95: JE | K95: Y03 | L95: C&S-INTERNAL-SWO-HJM-MX | M95: FLOW | N95: 1 | O95: 1 | P95: 1330-5YY0176EN | Q95: A | R95: BZ.YY.HEAT SINK | S95: HEAT SINK 8191849 (1330-5YY0176-C4EN) | T95: TT45ASA | U95: 50950081257 | W95: 1440 | X95: SEA | Y95: CIP | Z95: CIP | AA95: MANZANILLO | AB95: YANTIAN | AC95: MANZANILLO | AD95: 46081 | AE95: 46139 | AF95: 46091 | AG95: FGD-JCE | AH95: 6124757 | AI95: 46084 | AJ95: 46085 | AK95: 1440 | AL95: 34798 | AM95: 101513754759 | AN95: 46085 | AO95: 46085.452 | AP95: USD | AQ95: 1.15734 | AR95: 1666.57 | AS95: USD | AT95: 1666.57 | AU95: JOHN JH SHI | AV95: SHIPCO TRANSPORT-SEA-GEN | AW95: ZIM MOUNT BLANC V.12E | AX95: 46091 | AY95: 46140 | AZ95: JXLU4392928 | BA95: 40' | BB95: 22145170 | BC95: 48 | BD95: KG | BE95: 8.2251 | BF95: 6.7651 | BG95: MM | BH95: 495 | BI95: 395 | BJ95: 190 | BK95: 30 | BL95: KG | BM95: 273.7536 | BN95: 202.9536 | BO95: 273.7536 | BP95: MM | BQ95: 1200 | BR95: 1000 | BS95: 1120 | BT95: 1 | BU95: 0 | BV95: 1 | BW95: 30 | BX95: 0 | BY95: 30 | BZ95: 1440 | CA95: 0 | CB95: 1440 | CC95: 202.9536 | CD95: C-PAL-146020 | CE95: C-BOX-001329 | CG95: JE IM OU | CN95: M46 | CO95: 1110-EQN0001EN | CP95: CSGU2004557 | CQ95: 9.85 | CR95: =IFERROR(CQ95/(SUMIFS(CQ:CQ,CP:CP,CP95)),100%) -> 0.0013619056 | CS95: =CR95*$CS$2 -> 3.4047641
B96: M01 | C96: 1015081121 | D96: QIONG PENG | F96: 34798 | G96: JOHNSON ELECTRIC NORTH AMERICA INC. | H96: Tax ID JEG120120DD4 BOULEVARD MORELOS NO. 1109 MEGA PARQUE INDUSTRIAL AEROPUERTO DE CALERA C.P. 98519 CALERA ZACATECAS MX | I96: XEXX010101000 | J96: JE | K96: A99 | L96: BI-INTERNAL-SWO-HJM-MX | M96: FLOW | N96: 1 | O96: 4 | P96: 1200-1030990EN0002 | Q96: A | R96: EC.N.NONE | S96: END CAP ASS'Y WITH PACKAGING | T96: TT45ASA | U96: 50950080607 | W96: 11520 | X96: SEA | Y96: CIP | Z96: CIP | AA96: MANZANILLO | AB96: YANTIAN | AC96: MANZANILLO | AD96: 46074 | AE96: 46132 | AF96: 46091 | AG96: FG-BI-14E | AH96: 6126432 | AI96: 46085 | AJ96: 46086 | AK96: 11520 | AL96: 34798 | AM96: 101513755178 | AN96: 46086 | AO96: 46086.409 | AP96: USD | AQ96: 0.18359 | AR96: 2114.96 | AS96: USD | AT96: 2114.96 | AU96: JOHN JH SHI | AV96: SHIPCO TRANSPORT-SEA-GEN | AW96: ZIM MOUNT BLANC V.12E | AX96: 46091 | AY96: 46140 | AZ96: ZCSU7928505 | BA96: 40HQ | BB96: 22145172 | BC96: 240 | BD96: KG | BE96: 2.5634 | BF96: 1.2864 | BG96: MM | BH96: 340 | BI96: 250 | BJ96: 230 | BK96: 48 | BL96: KG | BM96: 144.0432 | BN96: 61.7472 | BO96: 144.0432 | BP96: MM | BQ96: 1066 | BR96: 1066 | BS96: 1080 | BT96: 1 | BU96: 0 | BV96: 1 | BW96: 48 | BX96: 0 | BY96: 48 | BZ96: 11520 | CA96: 0 | CB96: 11520 | CC96: 61.7472 | CD96: C-PAL-233041 | CE96: C-BOX-233127 | CG96: JE IM OU | CN96: M46 | CO96: 1101-EQN0004EN | CP96: CSGU2004557 | CQ96: 48.0736 | CR96: =IFERROR(CQ96/(SUMIFS(CQ:CQ,CP:CP,CP96)),100%) -> 0.0066468737 | CS96: =CR96*$CS$2 -> 16.617184
B97: M01 | C97: 1015082115 | D97: QIONG PENG | F97: 34798 | G97: JOHNSON ELECTRIC NORTH AMERICA INC. | H97: Tax ID JEG120120DD4 BOULEVARD MORELOS NO. 1109 MEGA PARQUE INDUSTRIAL AEROPUERTO DE CALERA C.P. 98519 CALERA ZACATECAS MX | I97: XEXX010101000 | J97: JE | K97: A62 | L97: BI-INTERNAL-SWO-HJM-MX | M97: FLOW | N97: 11 | O97: 1 | P97: 1999-1010399E1 | Q97: E | R97: DC.100.NF143G | S97: NF143G-1010399 | T97: TT45ASA | U97: 50950080751 | W97: 11520 | X97: SEA | Y97: CIP | Z97: CIP | AA97: MANZANILLO | AB97: YANTIAN | AC97: MANZANILLO | AD97: 46084 | AE97: 46132 | AF97: 46092 | AG97: FG-BI-25E | AH97: 6126701 | AI97: 46085 | AJ97: 46086 | AK97: 11520 | AL97: 34798 | AM97: 101513755362 | AN97: 46086 | AO97: 46086.63 | AP97: USD | AQ97: 0.59976 | AR97: 6909.2 | AS97: USD | AT97: 6909.2 | AU97: JOHN JH SHI | AV97: MSC-SEA-GEN | AW97: MANZANILLO EXPRESS V.2611E | AX97: 46092 | AY97: 46141 | AZ97: MSDU6089696 | BA97: 40HQ | BB97: MEDUWH352686 | BC97: 288 | BD97: KG | BE97: 9.822 | BF97: 8.352 | BG97: MM | BH97: 400 | BI97: 300 | BJ97: 160 | BK97: 40 | BL97: KG | BM97: 417.88 | BN97: 334.08 | BO97: 417.88 | BP97: MM | BQ97: 1200 | BR97: 800 | BS97: 970 | BT97: 1 | BU97: 0 | BV97: 1 | BW97: 40 | BX97: 0 | BY97: 40 | BZ97: 11520 | CA97: 0 | CB97: 11520 | CC97: 334.08 | CD97: C-PAL-208002 | CE97: C-BOX-159006 | CG97: JE IM OU | CN97: M46 | CO97: 1127-ETB0002EN | CP97: CSGU2004557 | CQ97: 98.1704 | CR97: =IFERROR(CQ97/(SUMIFS(CQ:CQ,CP:CP,CP97)),100%) -> 0.013573484 | CS97: =CR97*$CS$2 -> 33.933711
B98: M19 | C98: 1195009629 | F98: 34798 | G98: JOHNSON ELECTRIC NORTH AMERICA INC. | H98: Tax ID JEG120120DD4 BOULEVARD MORELOS NO. 1109 MEGA PARQUE INDUSTRIAL AEROPUERTO DE CALERA C.P. 98519 CALERA ZACATECAS MX | I98: XEXX010101000 | J98: JE | K98: Q03 | L98: PC-INTERNAL-SWO-HJM-MX | M98: FLOW | N98: 1 | O98: 1 | P98: 1275-5YY0352EN | Q98: H | R98: DC.CFM.CFM | S98: COMPLETE HARNESS 9180988 | T98: TT45ASA | U98: 50950075777 | W98: 1080 | X98: SEA | Y98: CIP | Z98: CIP | AA98: MANZANILLO | AB98: YANTIAN | AC98: MANZANILLO | AD98: 46083 | AE98: 46111 | AF98: 46091 | AG98: FG-PC-23E | AH98: 6126433 | AI98: 46085 | AJ98: 46086 | AK98: 1080 | AL98: 34798 | AM98: 101513755177 | AN98: 46086 | AO98: 46086.409 | AP98: USD | AQ98: 4.13988 | AR98: 4471.08 | AS98: USD | AT98: 4471.08 | AU98: JOHN JH SHI | AV98: SHIPCO TRANSPORT-SEA-GEN | AW98: ZIM MOUNT BLANC V.12E | AX98: 46091 | AY98: 46140 | AZ98: ZCSU7928505 | BA98: 40HQ | BB98: 22145172 | BC98: 36 | BD98: KG | BE98: 8.787 | BF98: 6.552 | BG98: MM | BH98: 595 | BI98: 395 | BJ98: 290 | BK98: 15 | BL98: KG | BM98: 158.805 | BN98: 98.28 | BO98: 317.61 | BP98: MM | BQ98: 1200 | BR98: 1000 | BS98: 1025 | BT98: 2 | BU98: 0 | BV98: 2 | BW98: 30 | BX98: 0 | BY98: 30 | BZ98: 1080 | CA98: 0 | CB98: 1080 | CC98: 196.56 | CD98: C-PAL-814001 | CE98: C-BOX-233039 | CG98: JE IM OU | CN98: M23 | CO98: 1202-1060185-72EN | CP98: CSGU2004557 | CQ98: 61.7345 | CR98: =IFERROR(CQ98/(SUMIFS(CQ:CQ,CP:CP,CP98)),100%) -> 0.0085356917 | CS98: =CR98*$CS$2 -> 21.339229
B99: M19 | C99: 1195009717 | F99: 34798 | G99: JOHNSON ELECTRIC NORTH AMERICA INC. | H99: Tax ID JEG120120DD4 BOULEVARD MORELOS NO. 1109 MEGA PARQUE INDUSTRIAL AEROPUERTO DE CALERA C.P. 98519 CALERA ZACATECAS MX | I99: XEXX010101000 | J99: JE | K99: Q03 | L99: PC-INTERNAL-SWO-HJM-MX | M99: FLOW | N99: 1 | O99: 2 | P99: 1275-5YY0783EN | Q99: G | R99: DC.CFM.CFM | S99: COMPLETE WIRE HARNESS | T99: TT45ASA | U99: 50950076748 | W99: 504 | X99: SEA | Y99: CIP | Z99: CIP | AA99: MANZANILLO | AB99: YANTIAN | AC99: MANZANILLO | AD99: 46083 | AE99: 46139 | AF99: 46091 | AG99: FG-PC-13E | AH99: 6126434 | AI99: 46085 | AJ99: 46086 | AK99: 504 | AL99: 34798 | AM99: 101513755180 | AN99: 46086 | AO99: 46086.409 | AP99: USD | AQ99: 2.19133 | AR99: 1104.43 | AS99: USD | AT99: 1104.43 | AU99: JOHN JH SHI | AV99: SHIPCO TRANSPORT-SEA-GEN | AW99: ZIM MOUNT BLANC V.12E | AX99: 46091 | AY99: 46140 | AZ99: ZCSU7928505 | BA99: 40HQ | BB99: 22145172 | BC99: 28 | BD99: KG | BE99: 4.1198 | BF99: 2.2568 | BG99: MM | BH99: 795 | BI99: 395 | BJ99: 145 | BK99: 18 | BL99: KG | BM99: 99.1564 | BN99: 40.6224 | BO99: 99.1564 | BP99: MM | BQ99: 1200 | BR99: 800 | BS99: 1030 | BT99: 1 | BU99: 0 | BV99: 1 | BW99: 18 | BX99: 0 | BY99: 18 | BZ99: 504 | CA99: 0 | CB99: 504 | CC99: 40.6224 | CD99: C-PAL-158001 | CE99: C-BOX-233190 | CG99: JE IM OU | CN99: MCS | CO99: 0070-G130008EN | CP99: CSGU2004557 | CQ99: 1000 | CR99: =IFERROR(CQ99/(SUMIFS(CQ:CQ,CP:CP,CP99)),100%) -> 0.13826453 | CS99: =CR99*$CS$2 -> 345.66133
B100: M19 | C100: 1195009942 | E100: Mexico PC Planner Assigned | F100: 34798 | G100: JOHNSON ELECTRIC NORTH AMERICA INC. | H100: Tax ID JEG120120DD4 BOULEVARD MORELOS NO. 1109 MEGA PARQUE INDUSTRIAL AEROPUERTO DE CALERA C.P. 98519 CALERA ZACATECAS MX | I100: XEXX010101000 | J100: JE | K100: Q03 | L100: PC-INTERNAL-SWO-HJM-MX | M100: FLOW | N100: 1 | O100: 1 | P100: 1275-5YY0568EN | Q100: J | R100: DC.CFM.CFM | S100: COMPLETE HARNESS 9181214 | T100: TT45ASA | U100: 50950079558 | W100: 6552 | X100: SEA | Y100: CIP | Z100: CIP | AA100: MANZANILLO | AB100: YANTIAN | AC100: MANZANILLO | AD100: 46083 | AE100: 46139 | AF100: 46091 | AG100: FG-PC-13E | AH100: 6126435 | AI100: 46085 | AJ100: 46086 | AK100: 6552 | AL100: 34798 | AM100: 101513755179 | AN100: 46086 | AO100: 46086.409 | AP100: USD | AQ100: 2.36391 | AR100: 15488.33 | AS100: USD | AT100: 15488.33 | AU100: JOHN JH SHI | AV100: SHIPCO TRANSPORT-SEA-GEN | AW100: ZIM MOUNT BLANC V.12E | AX100: 46091 | AY100: 46140 | AZ100: ZCSU7928505 | BA100: 40HQ | BB100: 22145172 | BC100: 28 | BD100: KG | BE100: 4.6406 | BF100: 2.7776 | BG100: MM | BH100: 795 | BI100: 395 | BJ100: 145 | BK100: 18 | BL100: KG | BM100: 108.5308 | BN100: 49.9968 | BO100: 1410.9004 | BP100: MM | BQ100: 1200 | BR100: 800 | BS100: 1030 | BT100: 13 | BU100: 0 | BV100: 13 | BW100: 234 | BX100: 0 | BY100: 234 | BZ100: 6552 | CA100: 0 | CB100: 6552 | CC100: 649.9584 | CD100: C-PAL-158001 | CE100: C-BOX-233190 | CG100: JE IM OU | CN100: M19 | CO100: 1275-5YY0685EN | CP100: CSGU6547742 | CQ100: 1456.112 | CR100: =IFERROR(CQ100/(SUMIFS(CQ:CQ,CP:CP,CP100)),100%) -> 0.17799391 | CS100: =CR100*$CS$2 -> 444.98479
B101: M01 | C101: 1275347245 | F101: 34798 | G101: JOHNSON ELECTRIC NORTH AMERICA INC. | H101: Tax ID JEG120120DD4 BOULEVARD MORELOS NO. 1109 MEGA PARQUE INDUSTRIAL AEROPUERTO DE CALERA C.P. 98519 CALERA ZACATECAS MX | I101: XEXX010101000 | J101: JE | K101: Y07 | L101: C&S-INTERNAL-SWO-HJM-MX | M101: FLOW | N101: 2 | O101: 1 | P101: 1438-1010107EN | Q101: F | R101: PCBA.100.PCBA | S101: PCB ASS'Y(1438-1010107-MTEN) | T101: TT45ASA | U101: 50950071835 | W101: 30240 | X101: SEA | Y101: CIP | Z101: CIP | AA101: MANZANILLO | AB101: YANTIAN | AC101: MANZANILLO | AD101: 46083 | AE101: 46090 | AF101: 46091 | AG101: FGD-JCE | AH101: 6126436 | AI101: 46085 | AJ101: 46086 | AK101: 30240 | AL101: 34798 | AM101: 101513755176 | AN101: 46086 | AO101: 46086.409 | AP101: USD | AQ101: 1.38604 | AR101: 41913.83 | AS101: USD | AT101: 41913.83 | AU101: JOHN JH SHI | AV101: SHIPCO TRANSPORT-SEA-GEN | AW101: ZIM MOUNT BLANC V.12E | AX101: 46091 | AY101: 46140 | AZ101: ZCSU7928505 | BA101: 40HQ | BB101: 22145172 | BC101: 108 | BD101: KG | BE101: 2.8953 | BF101: 1.8403 | BG101: MM | BH101: 495 | BI101: 295 | BJ101: 180 | BK101: 40 | BL101: KG | BM101: 142.812 | BN101: 73.612 | BO101: 999.6896 | BP101: MM | BQ101: 1200 | BR101: 1000 | BS101: 1060 | BT101: 7 | BU101: 0 | BV101: 7 | BW101: 280 | BX101: 0 | BY101: 280 | BZ101: 30240 | CA101: 0 | CB101: 30240 | CC101: 515.2896 | CD101: C-PAL-294061 | CE101: C-BOX-001384 | CG101: JE IM OU | CN101: M01 | CO101: 1438-1010133EN | CP101: CSGU6547742 | CQ101: 768.7392 | CR101: =IFERROR(CQ101/(SUMIFS(CQ:CQ,CP:CP,CP101)),100%) -> 0.093970037 | CS101: =CR101*$CS$2 -> 234.92509
B102: M45 | C102: 1275370283 | F102: 34798 | G102: JOHNSON ELECTRIC NORTH AMERICA INC. | H102: Tax ID JEG120120DD4 BOULEVARD MORELOS NO. 1109 MEGA PARQUE INDUSTRIAL AEROPUERTO DE CALERA C.P. 98519 CALERA ZACATECAS MX | I102: XEXX010101000 | J102: JE | K102: Y07 | L102: C&S-INTERNAL-SWO-HJM-MX | M102: FLOW | N102: 1 | O102: 1 | P102: 1438-12C0005EN | Q102: B | R102: PCBA.100.PCBA | S102: PCB ASSY | T102: TT45ASA | U102: 50950075102 | W102: 37800 | X102: SEA | Y102: CIP | Z102: CIP | AA102: MANZANILLO | AB102: YANTIAN | AC102: MANZANILLO | AD102: 46087 | AE102: 46195 | AF102: 46091 | AG102: FGD-JCE | AH102: 6126437 | AI102: 46085 | AJ102: 46086 | AK102: 37800 | AL102: 34798 | AM102: 101513755182 | AN102: 46086 | AO102: 46086.409 | AP102: USD | AQ102: 0.63772 | AR102: 24105.81 | AS102: USD | AT102: 24105.81 | AU102: JOHN JH SHI | AV102: SHIPCO TRANSPORT-SEA-GEN | AW102: ZIM MOUNT BLANC V.12E | AX102: 46091 | AY102: 46140 | AZ102: ZCSU7928505 | BA102: 40HQ | BB102: 22145172 | BC102: 350 | BD102: KG | BE102: 3.74 | BF102: 2.03 | BG102: MM | BH102: 400 | BI102: 335 | BJ102: 230 | BK102: 36 | BL102: KG | BM102: 159.64 | BN102: 73.08 | BO102: 478.92 | BP102: MM | BQ102: 1219 | BR102: 1016 | BS102: 1080 | BT102: 3 | BU102: 0 | BV102: 3 | BW102: 108 | BX102: 0 | BY102: 108 | BZ102: 37800 | CA102: 0 | CB102: 37800 | CC102: 219.24 | CD102: C-PAL-043001 | CE102: C-BOX-001407 | CG102: JE IM OU | CN102: M45 | CO102: 1301-12C0022EN | CP102: CSGU6547742 | CQ102: 615.616 | CR102: =IFERROR(CQ102/(SUMIFS(CQ:CQ,CP:CP,CP102)),100%) -> 0.075252385 | CS102: =CR102*$CS$2 -> 188.13096
B103: M01 | C103: 1275384965 | F103: 34798 | G103: JOHNSON ELECTRIC NORTH AMERICA INC. | H103: Tax ID JEG120120DD4 BOULEVARD MORELOS NO. 1109 MEGA PARQUE INDUSTRIAL AEROPUERTO DE CALERA C.P. 98519 CALERA ZACATECAS MX | I103: XEXX010101000 | J103: JE | K103: Y07 | L103: C&S-INTERNAL-SWO-HJM-MX | M103: FLOW | N103: 1 | O103: 1 | P103: 1438-1010133EN | Q103: D | R103: PCBA.100.PCBA | S103: (LEADWIRE)CONN & PCB ASSY (AUTOMOTIVE GRADE) | T103: TT45ASA | U103: 50950077639 | W103: 37440 | X103: SEA | Y103: CIP | Z103: CIP | AA103: MANZANILLO | AB103: YANTIAN | AC103: MANZANILLO | AD103: 46083 | AE103: 46237 | AF103: 46091 | AG103: FGD-JCE | AH103: 6126438 | AI103: 46085 | AJ103: 46086 | AK103: 37440 | AL103: 34798 | AM103: 101513755175 | AN103: 46086 | AO103: 46086.409 | AP103: USD | AQ103: 1.44828 | AR103: 54223.65 | AS103: USD | AT103: 54223.65 | AU103: JOHN JH SHI | AV103: SHIPCO TRANSPORT-SEA-GEN | AW103: ZIM MOUNT BLANC V.12E | AX103: 46091 | AY103: 46140 | AZ103: ZCSU7928505 | BA103: 40HQ | BB103: 22145172 | BC103: 72 | BD103: KG | BE103: 2.5281 | BF103: 1.3421 | BG103: MM | BH103: 495 | BI103: 295 | BJ103: 180 | BK103: 40 | BL103: KG | BM103: 128.124 | BN103: 53.684 | BO103: 1665.6016 | BP103: MM | BQ103: 1200 | BR103: 1000 | BS103: 1058 | BT103: 13 | BU103: 0 | BV103: 13 | BW103: 520 | BX103: 0 | BY103: 520 | BZ103: 37440 | CA103: 0 | CB103: 37440 | CC103: 697.8816 | CD103: C-PAL-387001 | CE103: C-BOX-2330011 | CG103: JE IM OU | CN103: M45 | CO103: 1346-12C0011EN | CP103: CSGU6547742 | CQ103: 157.5094 | CR103: =IFERROR(CQ103/(SUMIFS(CQ:CQ,CP:CP,CP103)),100%) -> 0.019253817 | CS103: =CR103*$CS$2 -> 48.134544
B104: M45 | C104: 1275391774 | F104: 34798 | G104: JOHNSON ELECTRIC NORTH AMERICA INC. | H104: Tax ID JEG120120DD4 BOULEVARD MORELOS NO. 1109 MEGA PARQUE INDUSTRIAL AEROPUERTO DE CALERA C.P. 98519 CALERA ZACATECAS MX | I104: XEXX010101000 | J104: JE | K104: Y04 | L104: C&S-INTERNAL-SWO-HJM-MX | M104: FLOW | N104: 1 | O104: 2 | P104: 1346-12C0011EN | Q104: E | R104: CB.SP63.BOBBIN | S104: BOBBIN | T104: TT45ASA | U104: 50950078820 | W104: 46200 | X104: SEA | Y104: CIP | Z104: CIP | AA104: MANZANILLO | AB104: YANTIAN | AC104: MANZANILLO | AD104: 46083 | AE104: 46167 | AF104: 46092 | AG104: FGD-JCE | AH104: 6126702 | AI104: 46085 | AJ104: 46086 | AK104: 46200 | AL104: 34798 | AM104: 101513755373 | AN104: 46086 | AO104: 46086.63 | AP104: USD | AQ104: 0.19572 | AR104: 9042.25 | AS104: USD | AT104: 9042.25 | AU104: JOHN JH SHI | AV104: MSC-SEA-GEN | AW104: MANZANILLO EXPRESS V.2611E | AX104: 46092 | AY104: 46141 | AZ104: MSDU6089696 | BA104: 40HQ | BB104: MEDUWH352686 | BC104: 264 | BD104: KG | BE104: 5.2204 | BF104: 3.8304 | BG104: MM | BH104: 595 | BI104: 395 | BJ104: 175 | BK104: 25 | BL104: KG | BM104: 157.51 | BN104: 95.76 | BO104: 1102.5658 | BP104: MM | BQ104: 1200 | BR104: 1000 | BS104: 1035 | BT104: 7 | BU104: 0 | BV104: 7 | BW104: 175 | BX104: 0 | BY104: 175 | BZ104: 46200 | CA104: 0 | CB104: 46200 | CC104: 670.3158 | CD104: C-PAL-293001 | CE104: C-BOX-001404 | CG104: JE IM OU | CN104: M19 | CO104: 1330-5YY0182EN | CP104: CSGU6547742 | CQ104: 175.6356 | CR104: =IFERROR(CQ104/(SUMIFS(CQ:CQ,CP:CP,CP104)),100%) -> 0.021469549 | CS104: =CR104*$CS$2 -> 53.673872
B105: M19 | C105: 1275395989 | F105: 34798 | G105: JOHNSON ELECTRIC NORTH AMERICA INC. | H105: Tax ID JEG120120DD4 BOULEVARD MORELOS NO. 1109 MEGA PARQUE INDUSTRIAL AEROPUERTO DE CALERA C.P. 98519 CALERA ZACATECAS MX | I105: XEXX010101000 | J105: JE | K105: Y05 | L105: C&S-INTERNAL-SWO-HJM-MX | M105: FLOW | N105: 1 | O105: 2 | P105: 1307-5YY0151EN | Q105: B | R105: FMP.YY.MAGNET | S105: MAGNET 8300333 | T105: TT45ASA | U105: 50950079468 | W105: 31104 | X105: SEA | Y105: CIP | Z105: CIP | AA105: MANZANILLO | AB105: YANTIAN | AC105: MANZANILLO | AD105: 46081 | AE105: 46111 | AF105: 46092 | AG105: FGD-JCE | AH105: 6126703 | AI105: 46085 | AJ105: 46086 | AK105: 31104 | AL105: 34798 | AM105: 101513755364 | AN105: 46086 | AO105: 46086.63 | AP105: USD | AQ105: 0.06014 | AR105: 1870.59 | AS105: USD | AT105: 1870.59 | AU105: JOHN JH SHI | AV105: MSC-SEA-GEN | AW105: MANZANILLO EXPRESS V.2611E | AX105: 46092 | AY105: 46141 | AZ105: MSDU6089696 | BA105: 40HQ | BB105: MEDUWH352686 | BC105: 576 | BD105: KG | BE105: 8.5413 | BF105: 8.2673 | BG105: MM | BH105: 320 | BI105: 190 | BJ105: 65 | BK105: 54 | BL105: KG | BM105: 488.23171 | BN105: 446.43571 | BO105: 488.23171 | BP105: MM | BQ105: 1200 | BR105: 1000 | BS105: 355 | BT105: 1 | BU105: 0 | BV105: 1 | BW105: 54 | BX105: 0 | BY105: 54 | BZ105: 31104 | CA105: 0 | CB105: 31104 | CC105: 446.43571 | CD105: C-PAL-294041 | CE105: C-BOX-474021 | CG105: JE IM OU | CN105: M19 | CO105: 1330-5YY0183EN | CP105: CSGU6547742 | CQ105: 515.3952 | CR105: =IFERROR(CQ105/(SUMIFS(CQ:CQ,CP:CP,CP105)),100%) -> 0.063001479 | CS105: =CR105*$CS$2 -> 157.5037
B106: M19 | C106: 1275396002 | D106: FLY YF LUO | F106: 34798 | G106: JOHNSON ELECTRIC NORTH AMERICA INC. | H106: Tax ID JEG120120DD4 BOULEVARD MORELOS NO. 1109 MEGA PARQUE INDUSTRIAL AEROPUERTO DE CALERA C.P. 98519 CALERA ZACATECAS MX | I106: XEXX010101000 | J106: JE | K106: Y05 | L106: C&S-INTERNAL-SWO-HJM-MX | M106: FLOW | N106: 1 | O106: 3 | P106: 1307-5YY0182EN | Q106: A | R106: FMP.YY.MAGNET | S106: MAGNET 8300387 | T106: TT45ASA | U106: 50950079499 | W106: 114048 | X106: SEA | Y106: CIP | Z106: CIP | AA106: MANZANILLO | AB106: YANTIAN | AC106: MANZANILLO | AD106: 46077 | AE106: 46104 | AF106: 46092 | AG106: FGD-JCE | AH106: 6126704 | AI106: 46085 | AJ106: 46086 | AK106: 114048 | AL106: 34798 | AM106: 101513755375 | AN106: 46086 | AO106: 46086.63 | AP106: USD | AQ106: 0.05508 | AR106: 6281.76 | AS106: USD | AT106: 6281.76 | AU106: JOHN JH SHI | AV106: MSC-SEA-GEN | AW106: MANZANILLO EXPRESS V.2611E | AX106: 46092 | AY106: 46141 | AZ106: MSDU6089696 | BA106: 40HQ | BB106: MEDUWH352686 | BC106: 594 | BD106: KG | BE106: 8.2227 | BF106: 7.9727 | BG106: MM | BH106: 286 | BI106: 190 | BJ106: 72 | BK106: 48 | BL106: KG | BM106: 419.6896 | BN106: 382.6896 | BO106: 1678.7523 | BP106: MM | BQ106: 1200 | BR106: 800 | BS106: 378 | BT106: 4 | BU106: 0 | BV106: 4 | BW106: 192 | BX106: 0 | BY106: 192 | BZ106: 114048 | CA106: 0 | CB106: 114048 | CC106: 1530.7523 | CD106: C-PAL-294017 | CE106: C-BOX-001401 | CG106: JE IM OU | CN106: M45 | CO106: 1459-12B0011EN | CP106: CSGU6547742 | CQ106: 811.07136 | CR106: =IFERROR(CQ106/(SUMIFS(CQ:CQ,CP:CP,CP106)),100%) -> 0.099144685 | CS106: =CR106*$CS$2 -> 247.86171
B107: M19 | C107: 1275396203 | F107: 34798 | G107: JOHNSON ELECTRIC NORTH AMERICA INC. | H107: Tax ID JEG120120DD4 BOULEVARD MORELOS NO. 1109 MEGA PARQUE INDUSTRIAL AEROPUERTO DE CALERA C.P. 98519 CALERA ZACATECAS MX | I107: XEXX010101000 | J107: JE | K107: Y05 | L107: C&S-INTERNAL-SWO-HJM-MX | M107: FLOW | N107: 1 | O107: 1 | P107: 1307-5YY0154EN | Q107: C | R107: FMP.YY.MAGNET | S107: MAGNET 8300342 | T107: TT45ASA | U107: 50950079443 | W107: 38400 | X107: SEA | Y107: CIP | Z107: CIP | AA107: MANZANILLO | AB107: YANTIAN | AC107: MANZANILLO | AD107: 46081 | AE107: 46125 | AF107: 46092 | AG107: FGD-JCE | AH107: 6126705 | AI107: 46085 | AJ107: 46086 | AK107: 38400 | AL107: 34798 | AM107: 101513755365 | AN107: 46086 | AO107: 46086.63 | AP107: USD | AQ107: 0.0834 | AR107: 3202.56 | AS107: USD | AT107: 3202.56 | AU107: JOHN JH SHI | AV107: MSC-SEA-GEN | AW107: MANZANILLO EXPRESS V.2611E | AX107: 46092 | AY107: 46141 | AZ107: MSDU6089696 | BA107: 40HQ | BB107: MEDUWH352686 | BC107: 240 | BD107: KG | BE107: 8.8945 | BF107: 8.6395 | BG107: MM | BH107: 270 | BI107: 158 | BJ107: 95 | BK107: 80 | BL107: KG | BM107: 736.56 | BN107: 691.16 | BO107: 1473.1232 | BP107: MM | BQ107: 1200 | BR107: 800 | BS107: 540 | BT107: 2 | BU107: 0 | BV107: 2 | BW107: 160 | BX107: 0 | BY107: 160 | BZ107: 38400 | CA107: 0 | CB107: 38400 | CC107: 1382.3232 | CD107: C-PAL-146044 | CE107: C-BOX-001177 | CG107: JE IM OU | CN107: M19 | CO107: 1301-5YY0390EN0093 | CP107: CSGU6547742 | CQ107: 762.5376 | CR107: =IFERROR(CQ107/(SUMIFS(CQ:CQ,CP:CP,CP107)),100%) -> 0.093211959 | CS107: =CR107*$CS$2 -> 233.0299
B108: M45 | C108: 1275400534 | F108: 34798 | G108: JOHNSON ELECTRIC NORTH AMERICA INC. | H108: Tax ID JEG120120DD4 BOULEVARD MORELOS NO. 1109 MEGA PARQUE INDUSTRIAL AEROPUERTO DE CALERA C.P. 98519 CALERA ZACATECAS MX | I108: XEXX010101000 | J108: JE | K108: W03 | L108: C&S-INTERNAL-SWO-HJM-MX | M108: FLOW | N108: 1 | O108: 1 | P108: 1205-12C0015EN | Q108: B | R108: CE.YY.TERMINAL | S108: TERMINAL(OLD PN:1205-12C0009-T1) | T108: TT45ASA | U108: 50950080014 | W108: 48000 | X108: SEA | Y108: CIP | Z108: CIP | AA108: MANZANILLO | AB108: YANTIAN | AC108: MANZANILLO | AD108: 46083 | AE108: 46146 | AF108: 46092 | AG108: FGD-JCE | AH108: 6126706 | AI108: 46085 | AJ108: 46086 | AK108: 48000 | AL108: 34798 | AM108: 101513755370 | AN108: 46086 | AO108: 46086.63 | AP108: USD | AQ108: 0.02447 | AR108: 1174.56 | AS108: USD | AT108: 1174.56 | AU108: JOHN JH SHI | AV108: MSC-SEA-GEN | AW108: MANZANILLO EXPRESS V.2611E | AX108: 46092 | AY108: 46141 | AZ108: MSDU6089696 | BA108: 40HQ | BB108: MEDUWH352686 | BC108: 16000 | BD108: KG | BE108: 8.93385 | BF108: 8 | BG108: MM | BH108: 398 | BI108: 298 | BJ108: 155 | BK108: 6 | BL108: KG | BM108: 34.80155 | BN108: 24 | BO108: 34.80155 | BP108: MM | BQ108: 800 | BR108: 300 | BS108: 608 | BT108: 0 | BU108: 1 | BV108: 1 | BW108: 3 | BX108: 0 | BY108: 3 | BZ108: 0 | CA108: 48000 | CB108: 48000 | CC108: 24 | CD108: C-PAL-507001 | CE108: C-BOX-001105 | CG108: JE IM OU | CN108: M19 | CO108: 1330-5YY0112EN | CP108: CSGU6547742 | CQ108: 296.21136 | CR108: =IFERROR(CQ108/(SUMIFS(CQ:CQ,CP:CP,CP108)),100%) -> 0.036208629 | CS108: =CR108*$CS$2 -> 90.521573
B109: M45 | C109: 1275400536 | F109: 34798 | G109: JOHNSON ELECTRIC NORTH AMERICA INC. | H109: Tax ID JEG120120DD4 BOULEVARD MORELOS NO. 1109 MEGA PARQUE INDUSTRIAL AEROPUERTO DE CALERA C.P. 98519 CALERA ZACATECAS MX | I109: XEXX010101000 | J109: JE | K109: W03 | L109: C&S-INTERNAL-SWO-HJM-MX | M109: FLOW | N109: 1 | O109: 1 | P109: 1205-12B0012EN | Q109: B | R109: CE.YY.TERMINAL | S109: TERMINAL(OLD PN:1205-12B0010-T1) | T109: TT45ASA | U109: 50950080016 | W109: 48000 | X109: SEA | Y109: CIP | Z109: CIP | AA109: MANZANILLO | AB109: YANTIAN | AC109: MANZANILLO | AD109: 46081 | AE109: 46139 | AF109: 46092 | AG109: FGD-JCE | AH109: 6126707 | AI109: 46085 | AJ109: 46086 | AK109: 48000 | AL109: 34798 | AM109: 101513755368 | AN109: 46086 | AO109: 46086.63 | AP109: USD | AQ109: 0.03131 | AR109: 1502.88 | AS109: USD | AT109: 1502.88 | AU109: JOHN JH SHI | AV109: MSC-SEA-GEN | AW109: MANZANILLO EXPRESS V.2611E | AX109: 46092 | AY109: 46141 | AZ109: MSDU6089696 | BA109: 40HQ | BB109: MEDUWH352686 | BC109: 8000 | BD109: KG | BE109: 10.21385 | BF109: 9.28 | BG109: MM | BH109: 398 | BI109: 298 | BJ109: 155 | BK109: 6 | BL109: KG | BM109: 69.2831 | BN109: 55.68 | BO109: 69.2831 | BP109: MM | BQ109: 800 | BR109: 300 | BS109: 608 | BT109: 1 | BU109: 0 | BV109: 1 | BW109: 6 | BX109: 0 | BY109: 6 | BZ109: 48000 | CA109: 0 | CB109: 48000 | CC109: 55.68 | CD109: C-PAL-507001 | CE109: C-BOX-001105 | CG109: JE IM OU | CN109: M19 | CO109: 1330-5YY0167EN | CP109: CSGU6547742 | CQ109: 700.9104 | CR109: =IFERROR(CQ109/(SUMIFS(CQ:CQ,CP:CP,CP109)),100%) -> 0.085678702 | CS109: =CR109*$CS$2 -> 214.19675
B110: M45 | C110: 1275400537 | F110: 34798 | G110: JOHNSON ELECTRIC NORTH AMERICA INC. | H110: Tax ID JEG120120DD4 BOULEVARD MORELOS NO. 1109 MEGA PARQUE INDUSTRIAL AEROPUERTO DE CALERA C.P. 98519 CALERA ZACATECAS MX | I110: XEXX010101000 | J110: JE | K110: W03 | L110: C&S-INTERNAL-SWO-HJM-MX | M110: FLOW | N110: 1 | O110: 1 | P110: 1205-12C0014EN | Q110: C | R110: CE.YY.TERMINAL | S110: TERMINAL(OLD PN:1205-12C0006-T1) | T110: TT45ASA | U110: 50950080017 | W110: 48000 | X110: SEA | Y110: CIP | Z110: CIP | AA110: MANZANILLO | AB110: YANTIAN | AC110: MANZANILLO | AD110: 46083 | AE110: 46146 | AF110: 46092 | AG110: FGD-JCE | AH110: 6126708 | AI110: 46085 | AJ110: 46086 | AK110: 48000 | AL110: 34798 | AM110: 101513755369 | AN110: 46086 | AO110: 46086.63 | AP110: USD | AQ110: 0.01199 | AR110: 575.52 | AS110: USD | AT110: 575.52 | AU110: JOHN JH SHI | AV110: MSC-SEA-GEN | AW110: MANZANILLO EXPRESS V.2611E | AX110: 46092 | AY110: 46141 | AZ110: MSDU6089696 | BA110: 40HQ | BB110: MEDUWH352686 | BC110: 24000 | BD110: KG | BE110: 11.61385 | BF110: 10.68 | BG110: MM | BH110: 398 | BI110: 298 | BJ110: 155 | BK110: 6 | BL110: KG | BM110: 31.2277 | BN110: 21.36 | BO110: 31.2277 | BP110: MM | BQ110: 800 | BR110: 300 | BS110: 608 | BT110: 0 | BU110: 1 | BV110: 1 | BW110: 2 | BX110: 0 | BY110: 2 | BZ110: 0 | CA110: 48000 | CB110: 48000 | CC110: 21.36 | CD110: C-PAL-507001 | CE110: C-BOX-001105 | CG110: JE IM OU | CN110: M19 | CO110: 1152-5YY0221EN | CP110: CSGU6547742 | CQ110: 739.4928 | CR110: =IFERROR(CQ110/(SUMIFS(CQ:CQ,CP:CP,CP110)),100%) -> 0.090394982 | CS110: =CR110*$CS$2 -> 225.98745
...

Sheet land
B1: {=_xlfn.SEQUENCE(1,63)} -> 1 | C1: 2 | D1: 3 | E1: 4 | F1: 5 | G1: 6 | H1: 7 | I1: 8 | J1: 9 | K1: 10 | L1: 11 | M1: 12 | N1: 13 | O1: 14 | P1: 15 | Q1: 16 | R1: 17 | S1: 18 | T1: 19 | U1: 20 | V1: 21 | W1: 22 | X1: 23 | Y1: 24 | Z1: 25 | AA1: 26 | AB1: 27 | AC1: 28 | AD1: 29 | AE1: 30 | AF1: 31 | AG1: 32 | AH1: 33 | AI1: 34 | AJ1: 35 | AK1: 36 | AL1: 37 | AM1: 38 | AN1: 39 | AO1: 40 | AP1: 41 | AQ1: 42 | AR1: 43 | AS1: 44 | AT1: 45 | AU1: 46 | AV1: 47 | AW1: 48 | AX1: 49 | AY1: 50 | AZ1: 51 | BA1: 52 | BB1: 53 | BC1: 54 | BD1: 55 | BE1: 56 | BF1: 57 | BG1: 58 | BH1: 59 | BI1: 60 | BJ1: 61 | BK1: 62 | BL1: 63 | BS1: {=_xlfn.TOROW(IF($B$2:$BL$2="x",_xlfn.ANCHORARRAY(B1),1/"0"),3)} -> 1 | BT1: 2 | BU1: 3 | BV1: 4 | BW1: 51 | BX1: 54 | BZ1: 1200
B2: x | C2: x | D2: x | E2: x | AZ2: x | BC2: x | BS2: {=_xlfn.TOROW(IF($B$2:$BL$2="x",$B$5:$BL$5,1/0),3)} -> Inbound/Outbound | BT2: Method | BU2: Reference | BV2: BU | BW2: Peso Bruto (Kgs) | BX2: No. Parte Prov. | BZ2: Cost
